Workbook

Sheet POA — Three year summary
A1: POA — Three year summary
A2: POA — Financial Forecast · Main Scenario
A4: Variable / dimension | B4: Forecast year start | C4: Forecast year end | D4: Annual subscription revenue | E4: Annual contingency revenue | F4: Annual total revenue | G4: Annual gross profit | H4: Annual operating overhead | I4: Annual acquisition spend | J4: Annual EBITDA | K4: Annual net cash flow | L4: Year end cash | M4: Year end active protocols | N4: Year end subscription ARR | O4: Year end total annualized run rate
A5: Year 1 | B5: =DATE(2026,10,1) -> 46296 | C5: =DATE(2027,9,1) -> 46631 | D5: =SUM('Model inputs'!B129,'Model inputs'!B130,'Model inputs'!B131) -> 395500 | E5: =SUM('Model inputs'!B132,'Model inputs'!B133,'Model inputs'!B134) -> 51333.123 | F5: =SUM('Model inputs'!B135,'Model inputs'!B136,'Model inputs'!B137) -> 446833.12 | G5: =SUM('Model inputs'!B138,'Model inputs'!B139,'Model inputs'!B140) -> 445939.46 | H5: =SUM('Model inputs'!B141,'Model inputs'!B142,'Model inputs'!B143) -> 327300 | I5: =SUM('Model inputs'!B144,'Model inputs'!B145,'Model inputs'!B146) -> 222333.33 | J5: =SUM('Model inputs'!B147,'Model inputs'!B148,'Model inputs'!B149) -> -103693.88 | K5: =SUM('Model inputs'!B150,'Model inputs'!B151,'Model inputs'!B152) -> -103693.88 | L5: =IF('Model inputs'!B190=0,"",SUM('Model inputs'!B153,'Model inputs'!B154,'Model inputs'!B155,'Model inputs'!B156,'Model inputs'!B157,'Model inputs'!B158,'Model inputs'!B159,'Model inputs'!B160,'Model inputs'!B161,'Model inputs'!B162,'Model inputs'!B163,'Model inputs'!B164,'Model inputs'!B165,'Model inputs'!B166,'Model inputs'!B167,'Model inputs'!B168,'Model inputs'!B169,'Model inputs'!B170,'Model inputs'!B171,'Model inputs'!B172,'Model inputs'!B173,'Model inputs'!B174,'Model inputs'!B175,'Model inputs'!B176,'Model inputs'!B177,'Model inputs'!B178,'Model inputs'!B179,'Model inputs'!B180,'Model inputs'!B181,'Model inputs'!B182,'Model inputs'!B183,'Model inputs'!B184,'Model inputs'!B185,'Model inputs'!B186,'Model inputs'!B187,'Model inputs'!B188,'Model inputs'!B189)) -> 396306.12 | M5: =IF('Model inputs'!B228=0,"",SUM('Model inputs'!B191,'Model inputs'!B192,'Model inputs'!B193,'Model inputs'!B194,'Model inputs'!B195,'Model inputs'!B196,'Model inputs'!B197,'Model inputs'!B198,'Model inputs'!B199,'Model inputs'!B200,'Model inputs'!B201,'Model inputs'!B202,'Model inputs'!B203,'Model inputs'!B204,'Model inputs'!B205,'Model inputs'!B206,'Model inputs'!B207,'Model inputs'!B208,'Model inputs'!B209,'Model inputs'!B210,'Model inputs'!B211,'Model inputs'!B212,'Model inputs'!B213,'Model inputs'!B214,'Model inputs'!B215,'Model inputs'!B216,'Model inputs'!B217,'Model inputs'!B218,'Model inputs'!B219,'Model inputs'!B220,'Model inputs'!B221,'Model inputs'!B222,'Model inputs'!B223,'Model inputs'!B224,'Model inputs'!B225,'Model inputs'!B226,'Model inputs'!B227)) -> 22 | N5: =IF('Model inputs'!B265=0,"",SUM('Model inputs'!B229,'Model inputs'!B230,'Model inputs'!B231,'Model inputs'!B232,'Model inputs'!B233,'Model inputs'!B234,'Model inputs'!B235,'Model inputs'!B236,'Model inputs'!B237,'Model inputs'!B238,'Model inputs'!B239,'Model inputs'!B240,'Model inputs'!B241,'Model inputs'!B242,'Model inputs'!B243,'Model inputs'!B244,'Model inputs'!B245,'Model inputs'!B246,'Model inputs'!B247,'Model inputs'!B248,'Model inputs'!B249,'Model inputs'!B250,'Model inputs'!B251,'Model inputs'!B252,'Model inputs'!B253,'Model inputs'!B254,'Model inputs'!B255,'Model inputs'!B256,'Model inputs'!B257,'Model inputs'!B258,'Model inputs'!B259,'Model inputs'!B260,'Model inputs'!B261,'Model inputs'!B262,'Model inputs'!B263,'Model inputs'!B264)) -> 924000 | O5: =IF('Model inputs'!B302=0,"",SUM('Model inputs'!B266,'Model inputs'!B267,'Model inputs'!B268,'Model inputs'!B269,'Model inputs'!B270,'Model inputs'!B271,'Model inputs'!B272,'Model inputs'!B273,'Model inputs'!B274,'Model inputs'!B275,'Model inputs'!B276,'Model inputs'!B277,'Model inputs'!B278,'Model inputs'!B279,'Model inputs'!B280,'Model inputs'!B281,'Model inputs'!B282,'Model inputs'!B283,'Model inputs'!B284,'Model inputs'!B285,'Model inputs'!B286,'Model inputs'!B287,'Model inputs'!B288,'Model inputs'!B289,'Model inputs'!B290,'Model inputs'!B291,'Model inputs'!B292,'Model inputs'!B293,'Model inputs'!B294,'Model inputs'!B295,'Model inputs'!B296,'Model inputs'!B297,'Model inputs'!B298,'Model inputs'!B299,'Model inputs'!B300,'Model inputs'!B301)) -> 1120000
A6: Year 2 | B6: =DATE(2027,10,1) -> 46661 | C6: =DATE(2028,9,1) -> 46997 | D6: =SUM('Model inputs'!B303,'Model inputs'!B304,'Model inputs'!B305) -> 2677500 | E6: =SUM('Model inputs'!B306,'Model inputs'!B307,'Model inputs'!B308) -> 987359.01 | F6: =SUM('Model inputs'!B309,'Model inputs'!B310,'Model inputs'!B311) -> 3664859 | G6: =SUM('Model inputs'!B312,'Model inputs'!B313,'Model inputs'!B314) -> 3657529.3 | H6: =SUM('Model inputs'!B315,'Model inputs'!B316,'Model inputs'!B317) -> 1198700 | I6: =SUM('Model inputs'!B318,'Model inputs'!B319,'Model inputs'!B320) -> 868085.71 | J6: =SUM('Model inputs'!B321,'Model inputs'!B322,'Model inputs'!B323) -> 1590743.6 | K6: =SUM('Model inputs'!B324,'Model inputs'!B325,'Model inputs'!B326) -> 1590743.6 | L6: =IF('Model inputs'!B364=0,"",SUM('Model inputs'!B327,'Model inputs'!B328,'Model inputs'!B329,'Model inputs'!B330,'Model inputs'!B331,'Model inputs'!B332,'Model inputs'!B333,'Model inputs'!B334,'Model inputs'!B335,'Model inputs'!B336,'Model inputs'!B337,'Model inputs'!B338,'Model inputs'!B339,'Model inputs'!B340,'Model inputs'!B341,'Model inputs'!B342,'Model inputs'!B343,'Model inputs'!B344,'Model inputs'!B345,'Model inputs'!B346,'Model inputs'!B347,'Model inputs'!B348,'Model inputs'!B349,'Model inputs'!B350,'Model inputs'!B351,'Model inputs'!B352,'Model inputs'!B353,'Model inputs'!B354,'Model inputs'!B355,'Model inputs'!B356,'Model inputs'!B357,'Model inputs'!B358,'Model inputs'!B359,'Model inputs'!B360,'Model inputs'!B361,'Model inputs'!B362,'Model inputs'!B363)) -> 1987049.7 | M6: =IF('Model inputs'!B402=0,"",SUM('Model inputs'!B365,'Model inputs'!B366,'Model inputs'!B367,'Model inputs'!B368,'Model inputs'!B369,'Model inputs'!B370,'Model inputs'!B371,'Model inputs'!B372,'Model inputs'!B373,'Model inputs'!B374,'Model inputs'!B375,'Model inputs'!B376,'Model inputs'!B377,'Model inputs'!B378,'Model inputs'!B379,'Model inputs'!B380,'Model inputs'!B381,'Model inputs'!B382,'Model inputs'!B383,'Model inputs'!B384,'Model inputs'!B385,'Model inputs'!B386,'Model inputs'!B387,'Model inputs'!B388,'Model inputs'!B389,'Model inputs'!B390,'Model inputs'!B391,'Model inputs'!B392,'Model inputs'!B393,'Model inputs'!B394,'Model inputs'!B395,'Model inputs'!B396,'Model inputs'!B397,'Model inputs'!B398,'Model inputs'!B399,'Model inputs'!B400,'Model inputs'!B401)) -> 100 | N6: =IF('Model inputs'!B439=0,"",SUM('Model inputs'!B403,'Model inputs'!B404,'Model inputs'!B405,'Model inputs'!B406,'Model inputs'!B407,'Model inputs'!B408,'Model inputs'!B409,'Model inputs'!B410,'Model inputs'!B411,'Model inputs'!B412,'Model inputs'!B413,'Model inputs'!B414,'Model inputs'!B415,'Model inputs'!B416,'Model inputs'!B417,'Model inputs'!B418,'Model inputs'!B419,'Model inputs'!B420,'Model inputs'!B421,'Model inputs'!B422,'Model inputs'!B423,'Model inputs'!B424,'Model inputs'!B425,'Model inputs'!B426,'Model inputs'!B427,'Model inputs'!B428,'Model inputs'!B429,'Model inputs'!B430,'Model inputs'!B431,'Model inputs'!B432,'Model inputs'!B433,'Model inputs'!B434,'Model inputs'!B435,'Model inputs'!B436,'Model inputs'!B437,'Model inputs'!B438)) -> 4200000 | O6: =IF('Model inputs'!B476=0,"",SUM('Model inputs'!B440,'Model inputs'!B441,'Model inputs'!B442,'Model inputs'!B443,'Model inputs'!B444,'Model inputs'!B445,'Model inputs'!B446,'Model inputs'!B447,'Model inputs'!B448,'Model inputs'!B449,'Model inputs'!B450,'Model inputs'!B451,'Model inputs'!B452,'Model inputs'!B453,'Model inputs'!B454,'Model inputs'!B455,'Model inputs'!B456,'Model inputs'!B457,'Model inputs'!B458,'Model inputs'!B459,'Model inputs'!B460,'Model inputs'!B461,'Model inputs'!B462,'Model inputs'!B463,'Model inputs'!B464,'Model inputs'!B465,'Model inputs'!B466,'Model inputs'!B467,'Model inputs'!B468,'Model inputs'!B469,'Model inputs'!B470,'Model inputs'!B471,'Model inputs'!B472,'Model inputs'!B473,'Model inputs'!B474,'Model inputs'!B475)) -> 6000000
A7: Year 3 | B7: =DATE(2028,10,1) -> 47027 | C7: =DATE(2029,9,1) -> 47362 | D7: =SUM('Model inputs'!B477,'Model inputs'!B478,'Model inputs'!B479) -> 5670000 | E7: =SUM('Model inputs'!B480,'Model inputs'!B481,'Model inputs'!B482) -> 2897916.7 | F7: =SUM('Model inputs'!B483,'Model inputs'!B484,'Model inputs'!B485) -> 8567916.7 | G7: =SUM('Model inputs'!B486,'Model inputs'!B487,'Model inputs'!B488) -> 8550780.8 | H7: =SUM('Model inputs'!B489,'Model inputs'!B490,'Model inputs'!B491) -> 2117500 | I7: =SUM('Model inputs'!B492,'Model inputs'!B493,'Model inputs'!B494) -> 893714.29 | J7: =SUM('Model inputs'!B495,'Model inputs'!B496,'Model inputs'!B497) -> 5539566.5 | K7: =SUM('Model inputs'!B498,'Model inputs'!B499,'Model inputs'!B500) -> 5539566.5 | L7: =IF('Model inputs'!B538=0,"",SUM('Model inputs'!B501,'Model inputs'!B502,'Model inputs'!B503,'Model inputs'!B504,'Model inputs'!B505,'Model inputs'!B506,'Model inputs'!B507,'Model inputs'!B508,'Model inputs'!B509,'Model inputs'!B510,'Model inputs'!B511,'Model inputs'!B512,'Model inputs'!B513,'Model inputs'!B514,'Model inputs'!B515,'Model inputs'!B516,'Model inputs'!B517,'Model inputs'!B518,'Model inputs'!B519,'Model inputs'!B520,'Model inputs'!B521,'Model inputs'!B522,'Model inputs'!B523,'Model inputs'!B524,'Model inputs'!B525,'Model inputs'!B526,'Model inputs'!B527,'Model inputs'!B528,'Model inputs'!B529,'Model inputs'!B530,'Model inputs'!B531,'Model inputs'!B532,'Model inputs'!B533,'Model inputs'!B534,'Model inputs'!B535,'Model inputs'!B536,'Model inputs'!B537)) -> 7526616.2 | M7: =IF('Model inputs'!B576=0,"",SUM('Model inputs'!B539,'Model inputs'!B540,'Model inputs'!B541,'Model inputs'!B542,'Model inputs'!B543,'Model inputs'!B544,'Model inputs'!B545,'Model inputs'!B546,'Model inputs'!B547,'Model inputs'!B548,'Model inputs'!B549,'Model inputs'!B550,'Model inputs'!B551,'Model inputs'!B552,'Model inputs'!B553,'Model inputs'!B554,'Model inputs'!B555,'Model inputs'!B556,'Model inputs'!B557,'Model inputs'!B558,'Model inputs'!B559,'Model inputs'!B560,'Model inputs'!B561,'Model inputs'!B562,'Model inputs'!B563,'Model inputs'!B564,'Model inputs'!B565,'Model inputs'!B566,'Model inputs'!B567,'Model inputs'!B568,'Model inputs'!B569,'Model inputs'!B570,'Model inputs'!B571,'Model inputs'!B572,'Model inputs'!B573,'Model inputs'!B574,'Model inputs'!B575)) -> 160 | N7: =IF('Model inputs'!B613=0,"",SUM('Model inputs'!B577,'Model inputs'!B578,'Model inputs'!B579,'Model inputs'!B580,'Model inputs'!B581,'Model inputs'!B582,'Model inputs'!B583,'Model inputs'!B584,'Model inputs'!B585,'Model inputs'!B586,'Model inputs'!B587,'Model inputs'!B588,'Model inputs'!B589,'Model inputs'!B590,'Model inputs'!B591,'Model inputs'!B592,'Model inputs'!B593,'Model inputs'!B594,'Model inputs'!B595,'Model inputs'!B596,'Model inputs'!B597,'Model inputs'!B598,'Model inputs'!B599,'Model inputs'!B600,'Model inputs'!B601,'Model inputs'!B602,'Model inputs'!B603,'Model inputs'!B604,'Model inputs'!B605,'Model inputs'!B606,'Model inputs'!B607,'Model inputs'!B608,'Model inputs'!B609,'Model inputs'!B610,'Model inputs'!B611,'Model inputs'!B612)) -> 6720000 | O7: =IF('Model inputs'!B650=0,"",SUM('Model inputs'!B614,'Model inputs'!B615,'Model inputs'!B616,'Model inputs'!B617,'Model inputs'!B618,'Model inputs'!B619,'Model inputs'!B620,'Model inputs'!B621,'Model inputs'!B622,'Model inputs'!B623,'Model inputs'!B624,'Model inputs'!B625,'Model inputs'!B626,'Model inputs'!B627,'Model inputs'!B628,'Model inputs'!B629,'Model inputs'!B630,'Model inputs'!B631,'Model inputs'!B632,'Model inputs'!B633,'Model inputs'!B634,'Model inputs'!B635,'Model inputs'!B636,'Model inputs'!B637,'Model inputs'!B638,'Model inputs'!B639,'Model inputs'!B640,'Model inputs'!B641,'Model inputs'!B642,'Model inputs'!B643,'Model inputs'!B644,'Model inputs'!B645,'Model inputs'!B646,'Model inputs'!B647,'Model inputs'!B648,'Model inputs'!B649)) -> 10560000

Sheet POA — Monthly financial forecas
A1: POA — Monthly financial forecast
A2: POA — Financial Forecast · Main Scenario
A4: Variable / dimension | B4: 2026-10 | C4: 2026-11 | D4: 2026-12 | E4: 2027-01 | F4: 2027-02 | G4: 2027-03 | H4: 2027-04 | I4: 2027-05 | J4: 2027-06 | K4: 2027-07 | L4: 2027-08 | M4: 2027-09 | N4: 2027-10 | O4: 2027-11 | P4: 2027-12 | Q4: 2028-01 | R4: 2028-02 | S4: 2028-03 | T4: 2028-04 | U4: 2028-05 | V4: 2028-06 | W4: 2028-07 | X4: 2028-08 | Y4: 2028-09 | Z4: 2028-10 | AA4: 2028-11 | AB4: 2028-12 | AC4: 2029-01 | AD4: 2029-02 | AE4: 2029-03 | AF4: 2029-04 | AG4: 2029-05 | AH4: 2029-06 | AI4: 2029-07 | AJ4: 2029-08 | AK4: 2029-09
A5: Forecast month | B5: =DATEDIF(DATE(2026,10,1),DATE(2026,10,1),"M")+1 -> 1 | C5: =DATEDIF(DATE(2026,10,1),DATE(2026,11,1),"M")+1 -> 2 | D5: =DATEDIF(DATE(2026,10,1),DATE(2026,12,1),"M")+1 -> 3 | E5: =DATEDIF(DATE(2026,10,1),DATE(2027,1,1),"M")+1 -> 4 | F5: =DATEDIF(DATE(2026,10,1),DATE(2027,2,1),"M")+1 -> 5 | G5: =DATEDIF(DATE(2026,10,1),DATE(2027,3,1),"M")+1 -> 6 | H5: =DATEDIF(DATE(2026,10,1),DATE(2027,4,1),"M")+1 -> 7 | I5: =DATEDIF(DATE(2026,10,1),DATE(2027,5,1),"M")+1 -> 8 | J5: =DATEDIF(DATE(2026,10,1),DATE(2027,6,1),"M")+1 -> 9 | K5: =DATEDIF(DATE(2026,10,1),DATE(2027,7,1),"M")+1 -> 10 | L5: =DATEDIF(DATE(2026,10,1),DATE(2027,8,1),"M")+1 -> 11 | M5: =DATEDIF(DATE(2026,10,1),DATE(2027,9,1),"M")+1 -> 12 | N5: =DATEDIF(DATE(2026,10,1),DATE(2027,10,1),"M")+1 -> 13 | O5: =DATEDIF(DATE(2026,10,1),DATE(2027,11,1),"M")+1 -> 14 | P5: =DATEDIF(DATE(2026,10,1),DATE(2027,12,1),"M")+1 -> 15 | Q5: =DATEDIF(DATE(2026,10,1),DATE(2028,1,1),"M")+1 -> 16 | R5: =DATEDIF(DATE(2026,10,1),DATE(2028,2,1),"M")+1 -> 17 | S5: =DATEDIF(DATE(2026,10,1),DATE(2028,3,1),"M")+1 -> 18 | T5: =DATEDIF(DATE(2026,10,1),DATE(2028,4,1),"M")+1 -> 19 | U5: =DATEDIF(DATE(2026,10,1),DATE(2028,5,1),"M")+1 -> 20 | V5: =DATEDIF(DATE(2026,10,1),DATE(2028,6,1),"M")+1 -> 21 | W5: =DATEDIF(DATE(2026,10,1),DATE(2028,7,1),"M")+1 -> 22 | X5: =DATEDIF(DATE(2026,10,1),DATE(2028,8,1),"M")+1 -> 23 | Y5: =DATEDIF(DATE(2026,10,1),DATE(2028,9,1),"M")+1 -> 24 | Z5: =DATEDIF(DATE(2026,10,1),DATE(2028,10,1),"M")+1 -> 25 | AA5: =DATEDIF(DATE(2026,10,1),DATE(2028,11,1),"M")+1 -> 26 | AB5: =DATEDIF(DATE(2026,10,1),DATE(2028,12,1),"M")+1 -> 27 | AC5: =DATEDIF(DATE(2026,10,1),DATE(2029,1,1),"M")+1 -> 28 | AD5: =DATEDIF(DATE(2026,10,1),DATE(2029,2,1),"M")+1 -> 29 | AE5: =DATEDIF(DATE(2026,10,1),DATE(2029,3,1),"M")+1 -> 30 | AF5: =DATEDIF(DATE(2026,10,1),DATE(2029,4,1),"M")+1 -> 31 | AG5: =DATEDIF(DATE(2026,10,1),DATE(2029,5,1),"M")+1 -> 32 | AH5: =DATEDIF(DATE(2026,10,1),DATE(2029,6,1),"M")+1 -> 33 | AI5: =DATEDIF(DATE(2026,10,1),DATE(2029,7,1),"M")+1 -> 34 | AJ5: =DATEDIF(DATE(2026,10,1),DATE(2029,8,1),"M")+1 -> 35 | AK5: =DATEDIF(DATE(2026,10,1),DATE(2029,9,1),"M")+1 -> 36
A6: Monthly churn rate | B6: =1/('Model inputs'!AM30*12) -> 0.023809524 | C6: =1/('Model inputs'!AM30*12) -> 0.023809524 | D6: =1/('Model inputs'!AM30*12) -> 0.023809524 | E6: =1/('Model inputs'!AM30*12) -> 0.023809524 | F6: =1/('Model inputs'!AM30*12) -> 0.023809524 | G6: =1/('Model inputs'!AM30*12) -> 0.023809524 | H6: =1/('Model inputs'!AM30*12) -> 0.023809524 | I6: =1/('Model inputs'!AM30*12) -> 0.023809524 | J6: =1/('Model inputs'!AM30*12) -> 0.023809524 | K6: =1/('Model inputs'!AM30*12) -> 0.023809524 | L6: =1/('Model inputs'!AM30*12) -> 0.023809524 | M6: =1/('Model inputs'!AM30*12) -> 0.023809524 | N6: =1/('Model inputs'!AM30*12) -> 0.023809524 | O6: =1/('Model inputs'!AM30*12) -> 0.023809524 | P6: =1/('Model inputs'!AM30*12) -> 0.023809524 | Q6: =1/('Model inputs'!AM30*12) -> 0.023809524 | R6: =1/('Model inputs'!AM30*12) -> 0.023809524 | S6: =1/('Model inputs'!AM30*12) -> 0.023809524 | T6: =1/('Model inputs'!AM30*12) -> 0.023809524 | U6: =1/('Model inputs'!AM30*12) -> 0.023809524 | V6: =1/('Model inputs'!AM30*12) -> 0.023809524 | W6: =1/('Model inputs'!AM30*12) -> 0.023809524 | X6: =1/('Model inputs'!AM30*12) -> 0.023809524 | Y6: =1/('Model inputs'!AM30*12) -> 0.023809524 | Z6: =1/('Model inputs'!AM30*12) -> 0.023809524 | AA6: =1/('Model inputs'!AM30*12) -> 0.023809524 | AB6: =1/('Model inputs'!AM30*12) -> 0.023809524 | AC6: =1/('Model inputs'!AM30*12) -> 0.023809524 | AD6: =1/('Model inputs'!AM30*12) -> 0.023809524 | AE6: =1/('Model inputs'!AM30*12) -> 0.023809524 | AF6: =1/('Model inputs'!AM30*12) -> 0.023809524 | AG6: =1/('Model inputs'!AM30*12) -> 0.023809524 | AH6: =1/('Model inputs'!AM30*12) -> 0.023809524 | AI6: =1/('Model inputs'!AM30*12) -> 0.023809524 | AJ6: =1/('Model inputs'!AM30*12) -> 0.023809524 | AK6: =1/('Model inputs'!AM30*12) -> 0.023809524
A7: Active protocols | B7: =IF(AND('Model inputs'!AM106="",'Model inputs'!B652=""),"",MIN('Model inputs'!AM106,'Model inputs'!B652)) -> 1 | C7: =IF(AND('Model inputs'!AM106="",'Model inputs'!B654=""),"",MIN('Model inputs'!AM106,'Model inputs'!B654)) -> 2 | D7: =IF(AND('Model inputs'!AM106="",'Model inputs'!B656=""),"",MIN('Model inputs'!AM106,'Model inputs'!B656)) -> 3 | E7: =IF(AND('Model inputs'!AM106="",'Model inputs'!B658=""),"",MIN('Model inputs'!AM106,'Model inputs'!B658)) -> 4 | F7: =IF(AND('Model inputs'!AM106="",'Model inputs'!B660=""),"",MIN('Model inputs'!AM106,'Model inputs'!B660)) -> 5 | G7: =IF(AND('Model inputs'!AM106="",'Model inputs'!B662=""),"",MIN('Model inputs'!AM106,'Model inputs'!B662)) -> 6 | H7: =IF(AND('Model inputs'!AM106="",'Model inputs'!B664=""),"",MIN('Model inputs'!AM106,'Model inputs'!B664)) -> 8.6666667 | I7: =IF(AND('Model inputs'!AM106="",'Model inputs'!B666=""),"",MIN('Model inputs'!AM106,'Model inputs'!B666)) -> 11.333333 | J7: =IF(AND('Model inputs'!AM106="",'Model inputs'!B668=""),"",MIN('Model inputs'!AM106,'Model inputs'!B668)) -> 14 | K7: =IF(AND('Model inputs'!AM106="",'Model inputs'!B670=""),"",MIN('Model inputs'!AM106,'Model inputs'!B670)) -> 16.666667 | L7: =IF(AND('Model inputs'!AM106="",'Model inputs'!B672=""),"",MIN('Model inputs'!AM106,'Model inputs'!B672)) -> 19.333333 | M7: =IF(AND('Model inputs'!AM106="",'Model inputs'!B674=""),"",MIN('Model inputs'!AM106,'Model inputs'!B674)) -> 22 | N7: =IF(AND('Model inputs'!AM106="",'Model inputs'!B676=""),"",MIN('Model inputs'!AM106,'Model inputs'!B676)) -> 28.333333 | O7: =IF(AND('Model inputs'!AM106="",'Model inputs'!B678=""),"",MIN('Model inputs'!AM106,'Model inputs'!B678)) -> 34.666667 | P7: =IF(AND('Model inputs'!AM106="",'Model inputs'!B680=""),"",MIN('Model inputs'!AM106,'Model inputs'!B680)) -> 41 | Q7: =IF(AND('Model inputs'!AM106="",'Model inputs'!B682=""),"",MIN('Model inputs'!AM106,'Model inputs'!B682)) -> 47.333333 | R7: =IF(AND('Model inputs'!AM106="",'Model inputs'!B684=""),"",MIN('Model inputs'!AM106,'Model inputs'!B684)) -> 53.666667 | S7: =IF(AND('Model inputs'!AM106="",'Model inputs'!B686=""),"",MIN('Model inputs'!AM106,'Model inputs'!B686)) -> 60 | T7: =IF(AND('Model inputs'!AM106="",'Model inputs'!B688=""),"",MIN('Model inputs'!AM106,'Model inputs'!B688)) -> 66.666667 | U7: =IF(AND('Model inputs'!AM106="",'Model inputs'!B690=""),"",MIN('Model inputs'!AM106,'Model inputs'!B690)) -> 73.333333 | V7: =IF(AND('Model inputs'!AM106="",'Model inputs'!B692=""),"",MIN('Model inputs'!AM106,'Model inputs'!B692)) -> 80 | W7: =IF(AND('Model inputs'!AM106="",'Model inputs'!B694=""),"",MIN('Model inputs'!AM106,'Model inputs'!B694)) -> 86.666667 | X7: =IF(AND('Model inputs'!AM106="",'Model inputs'!B696=""),"",MIN('Model inputs'!AM106,'Model inputs'!B696)) -> 93.333333 | Y7: =IF(AND('Model inputs'!AM106="",'Model inputs'!B698=""),"",MIN('Model inputs'!AM106,'Model inputs'!B698)) -> 100 | Z7: =IF(AND('Model inputs'!AM106="",'Model inputs'!B700=""),"",MIN('Model inputs'!AM106,'Model inputs'!B700)) -> 105.83333 | AA7: =IF(AND('Model inputs'!AM106="",'Model inputs'!B702=""),"",MIN('Model inputs'!AM106,'Model inputs'!B702)) -> 111.66667 | AB7: =IF(AND('Model inputs'!AM106="",'Model inputs'!B704=""),"",MIN('Model inputs'!AM106,'Model inputs'!B704)) -> 117.5 | AC7: =IF(AND('Model inputs'!AM106="",'Model inputs'!B706=""),"",MIN('Model inputs'!AM106,'Model inputs'!B706)) -> 123.33333 | AD7: =IF(AND('Model inputs'!AM106="",'Model inputs'!B708=""),"",MIN('Model inputs'!AM106,'Model inputs'!B708)) -> 129.16667 | AE7: =IF(AND('Model inputs'!AM106="",'Model inputs'!B710=""),"",MIN('Model inputs'!AM106,'Model inputs'!B710)) -> 135 | AF7: =IF(AND('Model inputs'!AM106="",'Model inputs'!B712=""),"",MIN('Model inputs'!AM106,'Model inputs'!B712)) -> 139.16667 | AG7: =IF(AND('Model inputs'!AM106="",'Model inputs'!B714=""),"",MIN('Model inputs'!AM106,'Model inputs'!B714)) -> 143.33333 | AH7: =IF(AND('Model inputs'!AM106="",'Model inputs'!B716=""),"",MIN('Model inputs'!AM106,'Model inputs'!B716)) -> 147.5 | AI7: =IF(AND('Model inputs'!AM106="",'Model inputs'!B718=""),"",MIN('Model inputs'!AM106,'Model inputs'!B718)) -> 151.66667 | AJ7: =IF(AND('Model inputs'!AM106="",'Model inputs'!B720=""),"",MIN('Model inputs'!AM106,'Model inputs'!B720)) -> 155.83333 | AK7: =IF(AND('Model inputs'!AM106="",'Model inputs'!B722=""),"",MIN('Model inputs'!AM106,'Model inputs'!B722)) -> 160
A8: Opening active protocols | B8: =IF('Model inputs'!B7="","",'Model inputs'!B7) -> 0 | C8: =IF('POA — Monthly financial forecas'!B7="","",'POA — Monthly financial forecas'!B7) -> 1 | D8: =IF('POA — Monthly financial forecas'!C7="","",'POA — Monthly financial forecas'!C7) -> 2 | E8: =IF('POA — Monthly financial forecas'!D7="","",'POA — Monthly financial forecas'!D7) -> 3 | F8: =IF('POA — Monthly financial forecas'!E7="","",'POA — Monthly financial forecas'!E7) -> 4 | G8: =IF('POA — Monthly financial forecas'!F7="","",'POA — Monthly financial forecas'!F7) -> 5 | H8: =IF('POA — Monthly financial forecas'!G7="","",'POA — Monthly financial forecas'!G7) -> 6 | I8: =IF('POA — Monthly financial forecas'!H7="","",'POA — Monthly financial forecas'!H7) -> 8.6666667 | J8: =IF('POA — Monthly financial forecas'!I7="","",'POA — Monthly financial forecas'!I7) -> 11.333333 | ... AK8: =IF('POA — Monthly financial forecas'!AJ7="","",'POA — Monthly financial forecas'!AJ7) -> 155.83333
A9: Churned protocols | B9: ='POA — Monthly financial forecas'!B8*'POA — Monthly financial forecas'!B6 -> 0 | C9: ='POA — Monthly financial forecas'!C8*'POA — Monthly financial forecas'!C6 -> 0.023809524 | D9: ='POA — Monthly financial forecas'!D8*'POA — Monthly financial forecas'!D6 -> 0.047619048 | E9: ='POA — Monthly financial forecas'!E8*'POA — Monthly financial forecas'!E6 -> 0.071428571 | F9: ='POA — Monthly financial forecas'!F8*'POA — Monthly financial forecas'!F6 -> 0.095238095 | G9: ='POA — Monthly financial forecas'!G8*'POA — Monthly financial forecas'!G6 -> 0.11904762 | H9: ='POA — Monthly financial forecas'!H8*'POA — Monthly financial forecas'!H6 -> 0.14285714 | I9: ='POA — Monthly financial forecas'!I8*'POA — Monthly financial forecas'!I6 -> 0.20634921 | ... AK9: ='POA — Monthly financial forecas'!AK8*'POA — Monthly financial forecas'!AK6 -> 3.7103175
A10: Net protocol additions | B10: ='POA — Monthly financial forecas'!B7-'POA — Monthly financial forecas'!B8 -> 1 | C10: ='POA — Monthly financial forecas'!C7-'POA — Monthly financial forecas'!C8 -> 1 | D10: ='POA — Monthly financial forecas'!D7-'POA — Monthly financial forecas'!D8 -> 1 | E10: ='POA — Monthly financial forecas'!E7-'POA — Monthly financial forecas'!E8 -> 1 | F10: ='POA — Monthly financial forecas'!F7-'POA — Monthly financial forecas'!F8 -> 1 | G10: ='POA — Monthly financial forecas'!G7-'POA — Monthly financial forecas'!G8 -> 1 | H10: ='POA — Monthly financial forecas'!H7-'POA — Monthly financial forecas'!H8 -> 2.6666667 | I10: ='POA — Monthly financial forecas'!I7-'POA — Monthly financial forecas'!I8 -> 2.6666667 | ... AK10: ='POA — Monthly financial forecas'!AK7-'POA — Monthly financial forecas'!AK8 -> 4.1666667
A11: Gross acquired protocols | B11: =MAX('POA — Monthly financial forecas'!B10+'POA — Monthly financial forecas'!B9,0) -> 1 | C11: =MAX('POA — Monthly financial forecas'!C10+'POA — Monthly financial forecas'!C9,0) -> 1.0238095 | D11: =MAX('POA — Monthly financial forecas'!D10+'POA — Monthly financial forecas'!D9,0) -> 1.047619 | E11: =MAX('POA — Monthly financial forecas'!E10+'POA — Monthly financial forecas'!E9,0) -> 1.0714286 | F11: =MAX('POA — Monthly financial forecas'!F10+'POA — Monthly financial forecas'!F9,0) -> 1.0952381 | G11: =MAX('POA — Monthly financial forecas'!G10+'POA — Monthly financial forecas'!G9,0) -> 1.1190476 | H11: =MAX('POA — Monthly financial forecas'!H10+'POA — Monthly financial forecas'!H9,0) -> 2.8095238 | I11: =MAX('POA — Monthly financial forecas'!I10+'POA — Monthly financial forecas'!I9,0) -> 2.8730159 | ... AK11: =MAX('POA — Monthly financial forecas'!AK10+'POA — Monthly financial forecas'!AK9,0) -> 7.8769841
A12: Market penetration | B12: ='POA — Monthly financial forecas'!B7/'Model inputs'!AM106 -> 0.005 | C12: ='POA — Monthly financial forecas'!C7/'Model inputs'!AM106 -> 0.01 | D12: ='POA — Monthly financial forecas'!D7/'Model inputs'!AM106 -> 0.015 | E12: ='POA — Monthly financial forecas'!E7/'Model inputs'!AM106 -> 0.02 | F12: ='POA — Monthly financial forecas'!F7/'Model inputs'!AM106 -> 0.025 | G12: ='POA — Monthly financial forecas'!G7/'Model inputs'!AM106 -> 0.03 | H12: ='POA — Monthly financial forecas'!H7/'Model inputs'!AM106 -> 0.043333333 | I12: ='POA — Monthly financial forecas'!I7/'Model inputs'!AM106 -> 0.056666667 | J12: ='POA — Monthly financial forecas'!J7/'Model inputs'!AM106 -> 0.07 | K12: ='POA — Monthly financial forecas'!K7/'Model inputs'!AM106 -> 0.083333333 | L12: ='POA — Monthly financial forecas'!L7/'Model inputs'!AM106 -> 0.096666667 | M12: ='POA — Monthly financial forecas'!M7/'Model inputs'!AM106 -> 0.11 | N12: ='POA — Monthly financial forecas'!N7/'Model inputs'!AM106 -> 0.14166667 | O12: ='POA — Monthly financial forecas'!O7/'Model inputs'!AM106 -> 0.17333333 | P12: ='POA — Monthly financial forecas'!P7/'Model inputs'!AM106 -> 0.205 | Q12: ='POA — Monthly financial forecas'!Q7/'Model inputs'!AM106 -> 0.23666667 | R12: ='POA — Monthly financial forecas'!R7/'Model inputs'!AM106 -> 0.26833333 | S12: ='POA — Monthly financial forecas'!S7/'Model inputs'!AM106 -> 0.3 | T12: ='POA — Monthly financial forecas'!T7/'Model inputs'!AM106 -> 0.33333333 | U12: ='POA — Monthly financial forecas'!U7/'Model inputs'!AM106 -> 0.36666667 | V12: ='POA — Monthly financial forecas'!V7/'Model inputs'!AM106 -> 0.4 | W12: ='POA — Monthly financial forecas'!W7/'Model inputs'!AM106 -> 0.43333333 | X12: ='POA — Monthly financial forecas'!X7/'Model inputs'!AM106 -> 0.46666667 | Y12: ='POA — Monthly financial forecas'!Y7/'Model inputs'!AM106 -> 0.5 | Z12: ='POA — Monthly financial forecas'!Z7/'Model inputs'!AM106 -> 0.52916667 | AA12: ='POA — Monthly financial forecas'!AA7/'Model inputs'!AM106 -> 0.55833333 | AB12: ='POA — Monthly financial forecas'!AB7/'Model inputs'!AM106 -> 0.5875 | AC12: ='POA — Monthly financial forecas'!AC7/'Model inputs'!AM106 -> 0.61666667 | AD12: ='POA — Monthly financial forecas'!AD7/'Model inputs'!AM106 -> 0.64583333 | AE12: ='POA — Monthly financial forecas'!AE7/'Model inputs'!AM106 -> 0.675 | AF12: ='POA — Monthly financial forecas'!AF7/'Model inputs'!AM106 -> 0.69583333 | AG12: ='POA — Monthly financial forecas'!AG7/'Model inputs'!AM106 -> 0.71666667 | AH12: ='POA — Monthly financial forecas'!AH7/'Model inputs'!AM106 -> 0.7375 | AI12: ='POA — Monthly financial forecas'!AI7/'Model inputs'!AM106 -> 0.75833333 | AJ12: ='POA — Monthly financial forecas'!AJ7/'Model inputs'!AM106 -> 0.77916667 | AK12: ='POA — Monthly financial forecas'!AK7/'Model inputs'!AM106 -> 0.8
A13: Contingency revenue per active protocol | B13: =IF('Model inputs'!B723="",0,'Model inputs'!B723)/'Model inputs'!AM9*'Model inputs'!AM14*'Model inputs'!AM74 -> 20.833333 | C13: =IF('Model inputs'!B724="",0,'Model inputs'!B724)/'Model inputs'!AM9*'Model inputs'!AM14*'Model inputs'!AM74 -> 41.666667 | D13: =IF('Model inputs'!B725="",0,'Model inputs'!B725)/'Model inputs'!AM9*'Model inputs'!AM14*'Model inputs'!AM74 -> 62.5 | E13: =IF('Model inputs'!B726="",0,'Model inputs'!B726)/'Model inputs'!AM9*'Model inputs'!AM14*'Model inputs'!AM74 -> 83.333333 | F13: =IF('Model inputs'!B727="",0,'Model inputs'!B727)/'Model inputs'!AM9*'Model inputs'!AM14*'Model inputs'!AM74 -> 104.16667 | G13: =IF('Model inputs'!B728="",0,'Model inputs'!B728)/'Model inputs'!AM9*'Model inputs'!AM14*'Model inputs'!AM74 -> 125 | H13: =IF('Model inputs'!B729="",0,'Model inputs'!B729)/'Model inputs'!AM9*'Model inputs'!AM14*'Model inputs'!AM74 -> 227.90404 | I13: =IF('Model inputs'!B730="",0,'Model inputs'!B730)/'Model inputs'!AM9*'Model inputs'!AM14*'Model inputs'!AM74 -> 330.80808 | J13: =IF('Model inputs'!B731="",0,'Model inputs'!B731)/'Model inputs'!AM9*'Model inputs'!AM14*'Model inputs'!AM74 -> 433.71212 | K13: =IF('Model inputs'!B732="",0,'Model inputs'!B732)/'Model inputs'!AM9*'Model inputs'!AM14*'Model inputs'!AM74 -> 536.61616 | L13: =IF('Model inputs'!B733="",0,'Model inputs'!B733)/'Model inputs'!AM9*'Model inputs'!AM14*'Model inputs'!AM74 -> 639.5202 | M13: =IF('Model inputs'!B734="",0,'Model inputs'!B734)/'Model inputs'!AM9*'Model inputs'!AM14*'Model inputs'!AM74 -> 742.42424 | N13: =IF('Model inputs'!B735="",0,'Model inputs'!B735)/'Model inputs'!AM9*'Model inputs'!AM14*'Model inputs'!AM74 -> 827.0202 | O13: =IF('Model inputs'!B736="",0,'Model inputs'!B736)/'Model inputs'!AM9*'Model inputs'!AM14*'Model inputs'!AM74 -> 911.61616 | P13: =IF('Model inputs'!B737="",0,'Model inputs'!B737)/'Model inputs'!AM9*'Model inputs'!AM14*'Model inputs'!AM74 -> 996.21212 | Q13: =IF('Model inputs'!B738="",0,'Model inputs'!B738)/'Model inputs'!AM9*'Model inputs'!AM14*'Model inputs'!AM74 -> 1080.8081 | R13: =IF('Model inputs'!B739="",0,'Model inputs'!B739)/'Model inputs'!AM9*'Model inputs'!AM14*'Model inputs'!AM74 -> 1165.404 | S13: =IF('Model inputs'!B740="",0,'Model inputs'!B740)/'Model inputs'!AM9*'Model inputs'!AM14*'Model inputs'!AM74 -> 1250 | T13: =IF('Model inputs'!B741="",0,'Model inputs'!B741)/'Model inputs'!AM9*'Model inputs'!AM14*'Model inputs'!AM74 -> 1291.6667 | U13: =IF('Model inputs'!B742="",0,'Model inputs'!B742)/'Model inputs'!AM9*'Model inputs'!AM14*'Model inputs'!AM74 -> 1333.3333 | V13: =IF('Model inputs'!B743="",0,'Model inputs'!B743)/'Model inputs'!AM9*'Model inputs'!AM14*'Model inputs'!AM74 -> 1375 | W13: =IF('Model inputs'!B744="",0,'Model inputs'!B744)/'Model inputs'!AM9*'Model inputs'!AM14*'Model inputs'!AM74 -> 1416.6667 | X13: =IF('Model inputs'!B745="",0,'Model inputs'!B745)/'Model inputs'!AM9*'Model inputs'!AM14*'Model inputs'!AM74 -> 1458.3333 | Y13: =IF('Model inputs'!B746="",0,'Model inputs'!B746)/'Model inputs'!AM9*'Model inputs'!AM14*'Model inputs'!AM74 -> 1500 | Z13: =IF('Model inputs'!B747="",0,'Model inputs'!B747)/'Model inputs'!AM9*'Model inputs'!AM14*'Model inputs'!AM74 -> 1541.6667 | AA13: =IF('Model inputs'!B748="",0,'Model inputs'!B748)/'Model inputs'!AM9*'Model inputs'!AM14*'Model inputs'!AM74 -> 1583.3333 | AB13: =IF('Model inputs'!B749="",0,'Model inputs'!B749)/'Model inputs'!AM9*'Model inputs'!AM14*'Model inputs'!AM74 -> 1625 | AC13: =IF('Model inputs'!B750="",0,'Model inputs'!B750)/'Model inputs'!AM9*'Model inputs'!AM14*'Model inputs'!AM74 -> 1666.6667 | AD13: =IF('Model inputs'!B751="",0,'Model inputs'!B751)/'Model inputs'!AM9*'Model inputs'!AM14*'Model inputs'!AM74 -> 1708.3333 | AE13: =IF('Model inputs'!B752="",0,'Model inputs'!B752)/'Model inputs'!AM9*'Model inputs'!AM14*'Model inputs'!AM74 -> 1750 | AF13: =IF('Model inputs'!B753="",0,'Model inputs'!B753)/'Model inputs'!AM9*'Model inputs'!AM14*'Model inputs'!AM74 -> 1791.6667 | AG13: =IF('Model inputs'!B754="",0,'Model inputs'!B754)/'Model inputs'!AM9*'Model inputs'!AM14*'Model inputs'!AM74 -> 1833.3333 | AH13: =IF('Model inputs'!B755="",0,'Model inputs'!B755)/'Model inputs'!AM9*'Model inputs'!AM14*'Model inputs'!AM74 -> 1875 | AI13: =IF('Model inputs'!B756="",0,'Model inputs'!B756)/'Model inputs'!AM9*'Model inputs'!AM14*'Model inputs'!AM74 -> 1916.6667 | AJ13: =IF('Model inputs'!B757="",0,'Model inputs'!B757)/'Model inputs'!AM9*'Model inputs'!AM14*'Model inputs'!AM74 -> 1958.3333 | AK13: =IF('Model inputs'!B758="",0,'Model inputs'!B758)/'Model inputs'!AM9*'Model inputs'!AM14*'Model inputs'!AM74 -> 2000
A14: Active protocols by segment | B14: =SUM('POA — Monthly financial forecas'!B15,'POA — Monthly financial forecas'!B16,'POA — Monthly financial forecas'!B17) -> 1 | C14: =SUM('POA — Monthly financial forecas'!C15,'POA — Monthly financial forecas'!C16,'POA — Monthly financial forecas'!C17) -> 2 | D14: =SUM('POA — Monthly financial forecas'!D15,'POA — Monthly financial forecas'!D16,'POA — Monthly financial forecas'!D17) -> 3 | E14: =SUM('POA — Monthly financial forecas'!E15,'POA — Monthly financial forecas'!E16,'POA — Monthly financial forecas'!E17) -> 4 | F14: =SUM('POA — Monthly financial forecas'!F15,'POA — Monthly financial forecas'!F16,'POA — Monthly financial forecas'!F17) -> 5 | G14: =SUM('POA — Monthly financial forecas'!G15,'POA — Monthly financial forecas'!G16,'POA — Monthly financial forecas'!G17) -> 6 | H14: =SUM('POA — Monthly financial forecas'!H15,'POA — Monthly financial forecas'!H16,'POA — Monthly financial forecas'!H17) -> 8.6666667 | I14: =SUM('POA — Monthly financial forecas'!I15,'POA — Monthly financial forecas'!I16,'POA — Monthly financial forecas'!I17) -> 11.333333 | ... AK14: =SUM('POA — Monthly financial forecas'!AK15,'POA — Monthly financial forecas'!AK16,'POA — Monthly financial forecas'!AK17) -> 160
A15: DEX | B15: ='POA — Monthly financial forecas'!B7*'Model inputs'!AM76 -> 0.3 | C15: ='POA — Monthly financial forecas'!C7*'Model inputs'!AM76 -> 0.6 | D15: ='POA — Monthly financial forecas'!D7*'Model inputs'!AM76 -> 0.9 | E15: ='POA — Monthly financial forecas'!E7*'Model inputs'!AM76 -> 1.2 | F15: ='POA — Monthly financial forecas'!F7*'Model inputs'!AM76 -> 1.5 | G15: ='POA — Monthly financial forecas'!G7*'Model inputs'!AM76 -> 1.8 | H15: ='POA — Monthly financial forecas'!H7*'Model inputs'!AM76 -> 2.6 | I15: ='POA — Monthly financial forecas'!I7*'Model inputs'!AM76 -> 3.4 | J15: ='POA — Monthly financial forecas'!J7*'Model inputs'!AM76 -> 4.2 | K15: ='POA — Monthly financial forecas'!K7*'Model inputs'!AM76 -> 5 | L15: ='POA — Monthly financial forecas'!L7*'Model inputs'!AM76 -> 5.8 | M15: ='POA — Monthly financial forecas'!M7*'Model inputs'!AM76 -> 6.6 | N15: ='POA — Monthly financial forecas'!N7*'Model inputs'!AM76 -> 8.5 | O15: ='POA — Monthly financial forecas'!O7*'Model inputs'!AM76 -> 10.4 | P15: ='POA — Monthly financial forecas'!P7*'Model inputs'!AM76 -> 12.3 | Q15: ='POA — Monthly financial forecas'!Q7*'Model inputs'!AM76 -> 14.2 | R15: ='POA — Monthly financial forecas'!R7*'Model inputs'!AM76 -> 16.1 | S15: ='POA — Monthly financial forecas'!S7*'Model inputs'!AM76 -> 18 | T15: ='POA — Monthly financial forecas'!T7*'Model inputs'!AM76 -> 20 | U15: ='POA — Monthly financial forecas'!U7*'Model inputs'!AM76 -> 22 | V15: ='POA — Monthly financial forecas'!V7*'Model inputs'!AM76 -> 24 | W15: ='POA — Monthly financial forecas'!W7*'Model inputs'!AM76 -> 26 | X15: ='POA — Monthly financial forecas'!X7*'Model inputs'!AM76 -> 28 | Y15: ='POA — Monthly financial forecas'!Y7*'Model inputs'!AM76 -> 30 | Z15: ='POA — Monthly financial forecas'!Z7*'Model inputs'!AM76 -> 31.75 | AA15: ='POA — Monthly financial forecas'!AA7*'Model inputs'!AM76 -> 33.5 | AB15: ='POA — Monthly financial forecas'!AB7*'Model inputs'!AM76 -> 35.25 | AC15: ='POA — Monthly financial forecas'!AC7*'Model inputs'!AM76 -> 37 | AD15: ='POA — Monthly financial forecas'!AD7*'Model inputs'!AM76 -> 38.75 | AE15: ='POA — Monthly financial forecas'!AE7*'Model inputs'!AM76 -> 40.5 | AF15: ='POA — Monthly financial forecas'!AF7*'Model inputs'!AM76 -> 41.75 | AG15: ='POA — Monthly financial forecas'!AG7*'Model inputs'!AM76 -> 43 | AH15: ='POA — Monthly financial forecas'!AH7*'Model inputs'!AM76 -> 44.25 | AI15: ='POA — Monthly financial forecas'!AI7*'Model inputs'!AM76 -> 45.5 | AJ15: ='POA — Monthly financial forecas'!AJ7*'Model inputs'!AM76 -> 46.75 | AK15: ='POA — Monthly financial forecas'!AK7*'Model inputs'!AM76 -> 48
A16: Lending | B16: ='POA — Monthly financial forecas'!B7*'Model inputs'!AM77 -> 0.4 | C16: ='POA — Monthly financial forecas'!C7*'Model inputs'!AM77 -> 0.8 | D16: ='POA — Monthly financial forecas'!D7*'Model inputs'!AM77 -> 1.2 | E16: ='POA — Monthly financial forecas'!E7*'Model inputs'!AM77 -> 1.6 | F16: ='POA — Monthly financial forecas'!F7*'Model inputs'!AM77 -> 2 | G16: ='POA — Monthly financial forecas'!G7*'Model inputs'!AM77 -> 2.4 | H16: ='POA — Monthly financial forecas'!H7*'Model inputs'!AM77 -> 3.4666667 | I16: ='POA — Monthly financial forecas'!I7*'Model inputs'!AM77 -> 4.5333333 | J16: ='POA — Monthly financial forecas'!J7*'Model inputs'!AM77 -> 5.6 | K16: ='POA — Monthly financial forecas'!K7*'Model inputs'!AM77 -> 6.6666667 | L16: ='POA — Monthly financial forecas'!L7*'Model inputs'!AM77 -> 7.7333333 | M16: ='POA — Monthly financial forecas'!M7*'Model inputs'!AM77 -> 8.8 | N16: ='POA — Monthly financial forecas'!N7*'Model inputs'!AM77 -> 11.333333 | O16: ='POA — Monthly financial forecas'!O7*'Model inputs'!AM77 -> 13.866667 | P16: ='POA — Monthly financial forecas'!P7*'Model inputs'!AM77 -> 16.4 | Q16: ='POA — Monthly financial forecas'!Q7*'Model inputs'!AM77 -> 18.933333 | R16: ='POA — Monthly financial forecas'!R7*'Model inputs'!AM77 -> 21.466667 | S16: ='POA — Monthly financial forecas'!S7*'Model inputs'!AM77 -> 24 | T16: ='POA — Monthly financial forecas'!T7*'Model inputs'!AM77 -> 26.666667 | U16: ='POA — Monthly financial forecas'!U7*'Model inputs'!AM77 -> 29.333333 | V16: ='POA — Monthly financial forecas'!V7*'Model inputs'!AM77 -> 32 | W16: ='POA — Monthly financial forecas'!W7*'Model inputs'!AM77 -> 34.666667 | X16: ='POA — Monthly financial forecas'!X7*'Model inputs'!AM77 -> 37.333333 | Y16: ='POA — Monthly financial forecas'!Y7*'Model inputs'!AM77 -> 40 | Z16: ='POA — Monthly financial forecas'!Z7*'Model inputs'!AM77 -> 42.333333 | AA16: ='POA — Monthly financial forecas'!AA7*'Model inputs'!AM77 -> 44.666667 | AB16: ='POA — Monthly financial forecas'!AB7*'Model inputs'!AM77 -> 47 | AC16: ='POA — Monthly financial forecas'!AC7*'Model inputs'!AM77 -> 49.333333 | AD16: ='POA — Monthly financial forecas'!AD7*'Model inputs'!AM77 -> 51.666667 | AE16: ='POA — Monthly financial forecas'!AE7*'Model inputs'!AM77 -> 54 | AF16: ='POA — Monthly financial forecas'!AF7*'Model inputs'!AM77 -> 55.666667 | AG16: ='POA — Monthly financial forecas'!AG7*'Model inputs'!AM77 -> 57.333333 | AH16: ='POA — Monthly financial forecas'!AH7*'Model inputs'!AM77 -> 59 | AI16: ='POA — Monthly financial forecas'!AI7*'Model inputs'!AM77 -> 60.666667 | AJ16: ='POA — Monthly financial forecas'!AJ7*'Model inputs'!AM77 -> 62.333333 | AK16: ='POA — Monthly financial forecas'!AK7*'Model inputs'!AM77 -> 64
A17: Liquid staking | B17: ='POA — Monthly financial forecas'!B7*'Model inputs'!AM78 -> 0.3 | C17: ='POA — Monthly financial forecas'!C7*'Model inputs'!AM78 -> 0.6 | D17: ='POA — Monthly financial forecas'!D7*'Model inputs'!AM78 -> 0.9 | E17: ='POA — Monthly financial forecas'!E7*'Model inputs'!AM78 -> 1.2 | F17: ='POA — Monthly financial forecas'!F7*'Model inputs'!AM78 -> 1.5 | G17: ='POA — Monthly financial forecas'!G7*'Model inputs'!AM78 -> 1.8 | H17: ='POA — Monthly financial forecas'!H7*'Model inputs'!AM78 -> 2.6 | I17: ='POA — Monthly financial forecas'!I7*'Model inputs'!AM78 -> 3.4 | J17: ='POA — Monthly financial forecas'!J7*'Model inputs'!AM78 -> 4.2 | K17: ='POA — Monthly financial forecas'!K7*'Model inputs'!AM78 -> 5 | L17: ='POA — Monthly financial forecas'!L7*'Model inputs'!AM78 -> 5.8 | M17: ='POA — Monthly financial forecas'!M7*'Model inputs'!AM78 -> 6.6 | N17: ='POA — Monthly financial forecas'!N7*'Model inputs'!AM78 -> 8.5 | O17: ='POA — Monthly financial forecas'!O7*'Model inputs'!AM78 -> 10.4 | P17: ='POA — Monthly financial forecas'!P7*'Model inputs'!AM78 -> 12.3 | Q17: ='POA — Monthly financial forecas'!Q7*'Model inputs'!AM78 -> 14.2 | R17: ='POA — Monthly financial forecas'!R7*'Model inputs'!AM78 -> 16.1 | S17: ='POA — Monthly financial forecas'!S7*'Model inputs'!AM78 -> 18 | T17: ='POA — Monthly financial forecas'!T7*'Model inputs'!AM78 -> 20 | U17: ='POA — Monthly financial forecas'!U7*'Model inputs'!AM78 -> 22 | V17: ='POA — Monthly financial forecas'!V7*'Model inputs'!AM78 -> 24 | W17: ='POA — Monthly financial forecas'!W7*'Model inputs'!AM78 -> 26 | X17: ='POA — Monthly financial forecas'!X7*'Model inputs'!AM78 -> 28 | Y17: ='POA — Monthly financial forecas'!Y7*'Model inputs'!AM78 -> 30 | Z17: ='POA — Monthly financial forecas'!Z7*'Model inputs'!AM78 -> 31.75 | AA17: ='POA — Monthly financial forecas'!AA7*'Model inputs'!AM78 -> 33.5 | AB17: ='POA — Monthly financial forecas'!AB7*'Model inputs'!AM78 -> 35.25 | AC17: ='POA — Monthly financial forecas'!AC7*'Model inputs'!AM78 -> 37 | AD17: ='POA — Monthly financial forecas'!AD7*'Model inputs'!AM78 -> 38.75 | AE17: ='POA — Monthly financial forecas'!AE7*'Model inputs'!AM78 -> 40.5 | AF17: ='POA — Monthly financial forecas'!AF7*'Model inputs'!AM78 -> 41.75 | AG17: ='POA — Monthly financial forecas'!AG7*'Model inputs'!AM78 -> 43 | AH17: ='POA — Monthly financial forecas'!AH7*'Model inputs'!AM78 -> 44.25 | AI17: ='POA — Monthly financial forecas'!AI7*'Model inputs'!AM78 -> 45.5 | AJ17: ='POA — Monthly financial forecas'!AJ7*'Model inputs'!AM78 -> 46.75 | AK17: ='POA — Monthly financial forecas'!AK7*'Model inputs'!AM78 -> 48
A18: Subscription MRR | B18: =SUM('POA — Monthly financial forecas'!B19,'POA — Monthly financial forecas'!B20,'POA — Monthly financial forecas'!B21) -> 3500 | C18: =SUM('POA — Monthly financial forecas'!C19,'POA — Monthly financial forecas'!C20,'POA — Monthly financial forecas'!C21) -> 7000 | D18: =SUM('POA — Monthly financial forecas'!D19,'POA — Monthly financial forecas'!D20,'POA — Monthly financial forecas'!D21) -> 10500 | E18: =SUM('POA — Monthly financial forecas'!E19,'POA — Monthly financial forecas'!E20,'POA — Monthly financial forecas'!E21) -> 14000 | F18: =SUM('POA — Monthly financial forecas'!F19,'POA — Monthly financial forecas'!F20,'POA — Monthly financial forecas'!F21) -> 17500 | G18: =SUM('POA — Monthly financial forecas'!G19,'POA — Monthly financial forecas'!G20,'POA — Monthly financial forecas'!G21) -> 21000 | H18: =SUM('POA — Monthly financial forecas'!H19,'POA — Monthly financial forecas'!H20,'POA — Monthly financial forecas'!H21) -> 30333.333 | I18: =SUM('POA — Monthly financial forecas'!I19,'POA — Monthly financial forecas'!I20,'POA — Monthly financial forecas'!I21) -> 39666.667 | ... AK18: =SUM('POA — Monthly financial forecas'!AK19,'POA — Monthly financial forecas'!AK20,'POA — Monthly financial forecas'!AK21) -> 560000
A19: DEX | B19: ='POA — Monthly financial forecas'!B15*'Model inputs'!AM43 -> 1050 | C19: ='POA — Monthly financial forecas'!C15*'Model inputs'!AM43 -> 2100 | D19: ='POA — Monthly financial forecas'!D15*'Model inputs'!AM43 -> 3150 | E19: ='POA — Monthly financial forecas'!E15*'Model inputs'!AM43 -> 4200 | F19: ='POA — Monthly financial forecas'!F15*'Model inputs'!AM43 -> 5250 | G19: ='POA — Monthly financial forecas'!G15*'Model inputs'!AM43 -> 6300 | H19: ='POA — Monthly financial forecas'!H15*'Model inputs'!AM43 -> 9100 | I19: ='POA — Monthly financial forecas'!I15*'Model inputs'!AM43 -> 11900 | J19: ='POA — Monthly financial forecas'!J15*'Model inputs'!AM43 -> 14700 | K19: ='POA — Monthly financial forecas'!K15*'Model inputs'!AM43 -> 17500 | L19: ='POA — Monthly financial forecas'!L15*'Model inputs'!AM43 -> 20300 | M19: ='POA — Monthly financial forecas'!M15*'Model inputs'!AM43 -> 23100 | N19: ='POA — Monthly financial forecas'!N15*'Model inputs'!AM43 -> 29750 | O19: ='POA — Monthly financial forecas'!O15*'Model inputs'!AM43 -> 36400 | P19: ='POA — Monthly financial forecas'!P15*'Model inputs'!AM43 -> 43050 | Q19: ='POA — Monthly financial forecas'!Q15*'Model inputs'!AM43 -> 49700 | R19: ='POA — Monthly financial forecas'!R15*'Model inputs'!AM43 -> 56350 | S19: ='POA — Monthly financial forecas'!S15*'Model inputs'!AM43 -> 63000 | T19: ='POA — Monthly financial forecas'!T15*'Model inputs'!AM43 -> 70000 | U19: ='POA — Monthly financial forecas'!U15*'Model inputs'!AM43 -> 77000 | V19: ='POA — Monthly financial forecas'!V15*'Model inputs'!AM43 -> 84000 | W19: ='POA — Monthly financial forecas'!W15*'Model inputs'!AM43 -> 91000 | X19: ='POA — Monthly financial forecas'!X15*'Model inputs'!AM43 -> 98000 | Y19: ='POA — Monthly financial forecas'!Y15*'Model inputs'!AM43 -> 105000 | Z19: ='POA — Monthly financial forecas'!Z15*'Model inputs'!AM43 -> 111125 | AA19: ='POA — Monthly financial forecas'!AA15*'Model inputs'!AM43 -> 117250 | AB19: ='POA — Monthly financial forecas'!AB15*'Model inputs'!AM43 -> 123375 | AC19: ='POA — Monthly financial forecas'!AC15*'Model inputs'!AM43 -> 129500 | AD19: ='POA — Monthly financial forecas'!AD15*'Model inputs'!AM43 -> 135625 | AE19: ='POA — Monthly financial forecas'!AE15*'Model inputs'!AM43 -> 141750 | AF19: ='POA — Monthly financial forecas'!AF15*'Model inputs'!AM43 -> 146125 | AG19: ='POA — Monthly financial forecas'!AG15*'Model inputs'!AM43 -> 150500 | AH19: ='POA — Monthly financial forecas'!AH15*'Model inputs'!AM43 -> 154875 | AI19: ='POA — Monthly financial forecas'!AI15*'Model inputs'!AM43 -> 159250 | AJ19: ='POA — Monthly financial forecas'!AJ15*'Model inputs'!AM43 -> 163625 | AK19: ='POA — Monthly financial forecas'!AK15*'Model inputs'!AM43 -> 168000
A20: Lending | B20: ='POA — Monthly financial forecas'!B16*'Model inputs'!AM43 -> 1400 | C20: ='POA — Monthly financial forecas'!C16*'Model inputs'!AM43 -> 2800 | D20: ='POA — Monthly financial forecas'!D16*'Model inputs'!AM43 -> 4200 | E20: ='POA — Monthly financial forecas'!E16*'Model inputs'!AM43 -> 5600 | F20: ='POA — Monthly financial forecas'!F16*'Model inputs'!AM43 -> 7000 | G20: ='POA — Monthly financial forecas'!G16*'Model inputs'!AM43 -> 8400 | H20: ='POA — Monthly financial forecas'!H16*'Model inputs'!AM43 -> 12133.333 | I20: ='POA — Monthly financial forecas'!I16*'Model inputs'!AM43 -> 15866.667 | J20: ='POA — Monthly financial forecas'!J16*'Model inputs'!AM43 -> 19600 | K20: ='POA — Monthly financial forecas'!K16*'Model inputs'!AM43 -> 23333.333 | L20: ='POA — Monthly financial forecas'!L16*'Model inputs'!AM43 -> 27066.667 | M20: ='POA — Monthly financial forecas'!M16*'Model inputs'!AM43 -> 30800 | N20: ='POA — Monthly financial forecas'!N16*'Model inputs'!AM43 -> 39666.667 | O20: ='POA — Monthly financial forecas'!O16*'Model inputs'!AM43 -> 48533.333 | P20: ='POA — Monthly financial forecas'!P16*'Model inputs'!AM43 -> 57400 | Q20: ='POA — Monthly financial forecas'!Q16*'Model inputs'!AM43 -> 66266.667 | R20: ='POA — Monthly financial forecas'!R16*'Model inputs'!AM43 -> 75133.333 | S20: ='POA — Monthly financial forecas'!S16*'Model inputs'!AM43 -> 84000 | T20: ='POA — Monthly financial forecas'!T16*'Model inputs'!AM43 -> 93333.333 | U20: ='POA — Monthly financial forecas'!U16*'Model inputs'!AM43 -> 102666.67 | V20: ='POA — Monthly financial forecas'!V16*'Model inputs'!AM43 -> 112000 | W20: ='POA — Monthly financial forecas'!W16*'Model inputs'!AM43 -> 121333.33 | X20: ='POA — Monthly financial forecas'!X16*'Model inputs'!AM43 -> 130666.67 | Y20: ='POA — Monthly financial forecas'!Y16*'Model inputs'!AM43 -> 140000 | Z20: ='POA — Monthly financial forecas'!Z16*'Model inputs'!AM43 -> 148166.67 | AA20: ='POA — Monthly financial forecas'!AA16*'Model inputs'!AM43 -> 156333.33 | AB20: ='POA — Monthly financial forecas'!AB16*'Model inputs'!AM43 -> 164500 | AC20: ='POA — Monthly financial forecas'!AC16*'Model inputs'!AM43 -> 172666.67 | AD20: ='POA — Monthly financial forecas'!AD16*'Model inputs'!AM43 -> 180833.33 | AE20: ='POA — Monthly financial forecas'!AE16*'Model inputs'!AM43 -> 189000 | AF20: ='POA — Monthly financial forecas'!AF16*'Model inputs'!AM43 -> 194833.33 | AG20: ='POA — Monthly financial forecas'!AG16*'Model inputs'!AM43 -> 200666.67 | AH20: ='POA — Monthly financial forecas'!AH16*'Model inputs'!AM43 -> 206500 | AI20: ='POA — Monthly financial forecas'!AI16*'Model inputs'!AM43 -> 212333.33 | AJ20: ='POA — Monthly financial forecas'!AJ16*'Model inputs'!AM43 -> 218166.67 | AK20: ='POA — Monthly financial forecas'!AK16*'Model inputs'!AM43 -> 224000
A21: Liquid staking | B21: ='POA — Monthly financial forecas'!B17*'Model inputs'!AM43 -> 1050 | C21: ='POA — Monthly financial forecas'!C17*'Model inputs'!AM43 -> 2100 | D21: ='POA — Monthly financial forecas'!D17*'Model inputs'!AM43 -> 3150 | E21: ='POA — Monthly financial forecas'!E17*'Model inputs'!AM43 -> 4200 | F21: ='POA — Monthly financial forecas'!F17*'Model inputs'!AM43 -> 5250 | G21: ='POA — Monthly financial forecas'!G17*'Model inputs'!AM43 -> 6300 | H21: ='POA — Monthly financial forecas'!H17*'Model inputs'!AM43 -> 9100 | I21: ='POA — Monthly financial forecas'!I17*'Model inputs'!AM43 -> 11900 | J21: ='POA — Monthly financial forecas'!J17*'Model inputs'!AM43 -> 14700 | K21: ='POA — Monthly financial forecas'!K17*'Model inputs'!AM43 -> 17500 | L21: ='POA — Monthly financial forecas'!L17*'Model inputs'!AM43 -> 20300 | M21: ='POA — Monthly financial forecas'!M17*'Model inputs'!AM43 -> 23100 | N21: ='POA — Monthly financial forecas'!N17*'Model inputs'!AM43 -> 29750 | O21: ='POA — Monthly financial forecas'!O17*'Model inputs'!AM43 -> 36400 | P21: ='POA — Monthly financial forecas'!P17*'Model inputs'!AM43 -> 43050 | Q21: ='POA — Monthly financial forecas'!Q17*'Model inputs'!AM43 -> 49700 | R21: ='POA — Monthly financial forecas'!R17*'Model inputs'!AM43 -> 56350 | S21: ='POA — Monthly financial forecas'!S17*'Model inputs'!AM43 -> 63000 | T21: ='POA — Monthly financial forecas'!T17*'Model inputs'!AM43 -> 70000 | U21: ='POA — Monthly financial forecas'!U17*'Model inputs'!AM43 -> 77000 | V21: ='POA — Monthly financial forecas'!V17*'Model inputs'!AM43 -> 84000 | W21: ='POA — Monthly financial forecas'!W17*'Model inputs'!AM43 -> 91000 | X21: ='POA — Monthly financial forecas'!X17*'Model inputs'!AM43 -> 98000 | Y21: ='POA — Monthly financial forecas'!Y17*'Model inputs'!AM43 -> 105000 | Z21: ='POA — Monthly financial forecas'!Z17*'Model inputs'!AM43 -> 111125 | AA21: ='POA — Monthly financial forecas'!AA17*'Model inputs'!AM43 -> 117250 | AB21: ='POA — Monthly financial forecas'!AB17*'Model inputs'!AM43 -> 123375 | AC21: ='POA — Monthly financial forecas'!AC17*'Model inputs'!AM43 -> 129500 | AD21: ='POA — Monthly financial forecas'!AD17*'Model inputs'!AM43 -> 135625 | AE21: ='POA — Monthly financial forecas'!AE17*'Model inputs'!AM43 -> 141750 | AF21: ='POA — Monthly financial forecas'!AF17*'Model inputs'!AM43 -> 146125 | AG21: ='POA — Monthly financial forecas'!AG17*'Model inputs'!AM43 -> 150500 | AH21: ='POA — Monthly financial forecas'!AH17*'Model inputs'!AM43 -> 154875 | AI21: ='POA — Monthly financial forecas'!AI17*'Model inputs'!AM43 -> 159250 | AJ21: ='POA — Monthly financial forecas'!AJ17*'Model inputs'!AM43 -> 163625 | AK21: ='POA — Monthly financial forecas'!AK17*'Model inputs'!AM43 -> 168000
A22: Contingency fee revenue | B22: =SUM('POA — Monthly financial forecas'!B23,'POA — Monthly financial forecas'!B24,'POA — Monthly financial forecas'!B25) -> 20.833333 | C22: =SUM('POA — Monthly financial forecas'!C23,'POA — Monthly financial forecas'!C24,'POA — Monthly financial forecas'!C25) -> 83.333333 | D22: =SUM('POA — Monthly financial forecas'!D23,'POA — Monthly financial forecas'!D24,'POA — Monthly financial forecas'!D25) -> 187.5 | E22: =SUM('POA — Monthly financial forecas'!E23,'POA — Monthly financial forecas'!E24,'POA — Monthly financial forecas'!E25) -> 333.33333 | F22: =SUM('POA — Monthly financial forecas'!F23,'POA — Monthly financial forecas'!F24,'POA — Monthly financial forecas'!F25) -> 520.83333 | G22: =SUM('POA — Monthly financial forecas'!G23,'POA — Monthly financial forecas'!G24,'POA — Monthly financial forecas'!G25) -> 750 | H22: =SUM('POA — Monthly financial forecas'!H23,'POA — Monthly financial forecas'!H24,'POA — Monthly financial forecas'!H25) -> 1975.1684 | I22: =SUM('POA — Monthly financial forecas'!I23,'POA — Monthly financial forecas'!I24,'POA — Monthly financial forecas'!I25) -> 3749.1582 | ... AK22: =SUM('POA — Monthly financial forecas'!AK23,'POA — Monthly financial forecas'!AK24,'POA — Monthly financial forecas'!AK25) -> 320000
A23: DEX | B23: ='POA — Monthly financial forecas'!B15*'POA — Monthly financial forecas'!B13 -> 6.25 | C23: ='POA — Monthly financial forecas'!C15*'POA — Monthly financial forecas'!C13 -> 25 | D23: ='POA — Monthly financial forecas'!D15*'POA — Monthly financial forecas'!D13 -> 56.25 | E23: ='POA — Monthly financial forecas'!E15*'POA — Monthly financial forecas'!E13 -> 100 | F23: ='POA — Monthly financial forecas'!F15*'POA — Monthly financial forecas'!F13 -> 156.25 | G23: ='POA — Monthly financial forecas'!G15*'POA — Monthly financial forecas'!G13 -> 225 | H23: ='POA — Monthly financial forecas'!H15*'POA — Monthly financial forecas'!H13 -> 592.55051 | I23: ='POA — Monthly financial forecas'!I15*'POA — Monthly financial forecas'!I13 -> 1124.7475 | ... AK23: ='POA — Monthly financial forecas'!AK15*'POA — Monthly financial forecas'!AK13 -> 96000
A24: Lending | B24: ='POA — Monthly financial forecas'!B16*'POA — Monthly financial forecas'!B13 -> 8.3333333 | C24: ='POA — Monthly financial forecas'!C16*'POA — Monthly financial forecas'!C13 -> 33.333333 | D24: ='POA — Monthly financial forecas'!D16*'POA — Monthly financial forecas'!D13 -> 75 | E24: ='POA — Monthly financial forecas'!E16*'POA — Monthly financial forecas'!E13 -> 133.33333 | F24: ='POA — Monthly financial forecas'!F16*'POA — Monthly financial forecas'!F13 -> 208.33333 | G24: ='POA — Monthly financial forecas'!G16*'POA — Monthly financial forecas'!G13 -> 300 | H24: ='POA — Monthly financial forecas'!H16*'POA — Monthly financial forecas'!H13 -> 790.06734 | I24: ='POA — Monthly financial forecas'!I16*'POA — Monthly financial forecas'!I13 -> 1499.6633 | ... AK24: ='POA — Monthly financial forecas'!AK16*'POA — Monthly financial forecas'!AK13 -> 128000
A25: Liquid staking | B25: ='POA — Monthly financial forecas'!B17*'POA — Monthly financial forecas'!B13 -> 6.25 | C25: ='POA — Monthly financial forecas'!C17*'POA — Monthly financial forecas'!C13 -> 25 | D25: ='POA — Monthly financial forecas'!D17*'POA — Monthly financial forecas'!D13 -> 56.25 | E25: ='POA — Monthly financial forecas'!E17*'POA — Monthly financial forecas'!E13 -> 100 | F25: ='POA — Monthly financial forecas'!F17*'POA — Monthly financial forecas'!F13 -> 156.25 | G25: ='POA — Monthly financial forecas'!G17*'POA — Monthly financial forecas'!G13 -> 225 | H25: ='POA — Monthly financial forecas'!H17*'POA — Monthly financial forecas'!H13 -> 592.55051 | I25: ='POA — Monthly financial forecas'!I17*'POA — Monthly financial forecas'!I13 -> 1124.7475 | ... AK25: ='POA — Monthly financial forecas'!AK17*'POA — Monthly financial forecas'!AK13 -> 96000
A26: Verified losses recovered and disbursed | B26: ='POA — Monthly financial forecas'!B22/'Model inputs'!AM14 -> 416.66667 | C26: ='POA — Monthly financial forecas'!C22/'Model inputs'!AM14 -> 1666.6667 | D26: ='POA — Monthly financial forecas'!D22/'Model inputs'!AM14 -> 3750 | E26: ='POA — Monthly financial forecas'!E22/'Model inputs'!AM14 -> 6666.6667 | F26: ='POA — Monthly financial forecas'!F22/'Model inputs'!AM14 -> 10416.667 | G26: ='POA — Monthly financial forecas'!G22/'Model inputs'!AM14 -> 15000 | H26: ='POA — Monthly financial forecas'!H22/'Model inputs'!AM14 -> 39503.367 | I26: ='POA — Monthly financial forecas'!I22/'Model inputs'!AM14 -> 74983.165 | J26: ='POA — Monthly financial forecas'!J22/'Model inputs'!AM14 -> 121439.39 | K26: ='POA — Monthly financial forecas'!K22/'Model inputs'!AM14 -> 178872.05 | L26: ='POA — Monthly financial forecas'!L22/'Model inputs'!AM14 -> 247281.14 | M26: ='POA — Monthly financial forecas'!M22/'Model inputs'!AM14 -> 326666.67 | N26: ='POA — Monthly financial forecas'!N22/'Model inputs'!AM14 -> 468644.78 | O26: ='POA — Monthly financial forecas'!O22/'Model inputs'!AM14 -> 632053.87 | P26: ='POA — Monthly financial forecas'!P22/'Model inputs'!AM14 -> 816893.94 | Q26: ='POA — Monthly financial forecas'!Q22/'Model inputs'!AM14 -> 1023165 | R26: ='POA — Monthly financial forecas'!R22/'Model inputs'!AM14 -> 1250867 | S26: ='POA — Monthly financial forecas'!S22/'Model inputs'!AM14 -> 1500000 | T26: ='POA — Monthly financial forecas'!T22/'Model inputs'!AM14 -> 1722222.2 | U26: ='POA — Monthly financial forecas'!U22/'Model inputs'!AM14 -> 1955555.6 | V26: ='POA — Monthly financial forecas'!V22/'Model inputs'!AM14 -> 2200000 | W26: ='POA — Monthly financial forecas'!W22/'Model inputs'!AM14 -> 2455555.6 | X26: ='POA — Monthly financial forecas'!X22/'Model inputs'!AM14 -> 2722222.2 | Y26: ='POA — Monthly financial forecas'!Y22/'Model inputs'!AM14 -> 3000000 | Z26: ='POA — Monthly financial forecas'!Z22/'Model inputs'!AM14 -> 3263194.4 | AA26: ='POA — Monthly financial forecas'!AA22/'Model inputs'!AM14 -> 3536111.1 | AB26: ='POA — Monthly financial forecas'!AB22/'Model inputs'!AM14 -> 3818750 | AC26: ='POA — Monthly financial forecas'!AC22/'Model inputs'!AM14 -> 4111111.1 | AD26: ='POA — Monthly financial forecas'!AD22/'Model inputs'!AM14 -> 4413194.4 | AE26: ='POA — Monthly financial forecas'!AE22/'Model inputs'!AM14 -> 4725000 | AF26: ='POA — Monthly financial forecas'!AF22/'Model inputs'!AM14 -> 4986805.6 | AG26: ='POA — Monthly financial forecas'!AG22/'Model inputs'!AM14 -> 5255555.6 | AH26: ='POA — Monthly financial forecas'!AH22/'Model inputs'!AM14 -> 5531250 | AI26: ='POA — Monthly financial forecas'!AI22/'Model inputs'!AM14 -> 5813888.9 | AJ26: ='POA — Monthly financial forecas'!AJ22/'Model inputs'!AM14 -> 6103472.2 | AK26: ='POA — Monthly financial forecas'!AK22/'Model inputs'!AM14 -> 6400000
A27: Total revenue | B27: ='POA — Monthly financial forecas'!B18+'POA — Monthly financial forecas'!B22 -> 3520.8333 | C27: ='POA — Monthly financial forecas'!C18+'POA — Monthly financial forecas'!C22 -> 7083.3333 | D27: ='POA — Monthly financial forecas'!D18+'POA — Monthly financial forecas'!D22 -> 10687.5 | E27: ='POA — Monthly financial forecas'!E18+'POA — Monthly financial forecas'!E22 -> 14333.333 | F27: ='POA — Monthly financial forecas'!F18+'POA — Monthly financial forecas'!F22 -> 18020.833 | G27: ='POA — Monthly financial forecas'!G18+'POA — Monthly financial forecas'!G22 -> 21750 | H27: ='POA — Monthly financial forecas'!H18+'POA — Monthly financial forecas'!H22 -> 32308.502 | I27: ='POA — Monthly financial forecas'!I18+'POA — Monthly financial forecas'!I22 -> 43415.825 | ... AK27: ='POA — Monthly financial forecas'!AK18+'POA — Monthly financial forecas'!AK22 -> 880000
A28: Contracted subscription ARR | B28: ='POA — Monthly financial forecas'!B18*12 -> 42000 | C28: ='POA — Monthly financial forecas'!C18*12 -> 84000 | D28: ='POA — Monthly financial forecas'!D18*12 -> 126000 | E28: ='POA — Monthly financial forecas'!E18*12 -> 168000 | F28: ='POA — Monthly financial forecas'!F18*12 -> 210000 | G28: ='POA — Monthly financial forecas'!G18*12 -> 252000 | H28: ='POA — Monthly financial forecas'!H18*12 -> 364000 | I28: ='POA — Monthly financial forecas'!I18*12 -> 476000 | ... AK28: ='POA — Monthly financial forecas'!AK18*12 -> 6720000
A29: Total revenue annualized run rate | B29: ='POA — Monthly financial forecas'!B27*12 -> 42250 | C29: ='POA — Monthly financial forecas'!C27*12 -> 85000 | D29: ='POA — Monthly financial forecas'!D27*12 -> 128250 | E29: ='POA — Monthly financial forecas'!E27*12 -> 172000 | F29: ='POA — Monthly financial forecas'!F27*12 -> 216250 | G29: ='POA — Monthly financial forecas'!G27*12 -> 261000 | H29: ='POA — Monthly financial forecas'!H27*12 -> 387702.02 | I29: ='POA — Monthly financial forecas'!I27*12 -> 520989.9 | ... AK29: ='POA — Monthly financial forecas'!AK27*12 -> 10560000
A30: Investigated incidents | B30: ='POA — Monthly financial forecas'!B7*'Model inputs'!AM38 -> 100 | C30: ='POA — Monthly financial forecas'!C7*'Model inputs'!AM38 -> 200 | D30: ='POA — Monthly financial forecas'!D7*'Model inputs'!AM38 -> 300 | E30: ='POA — Monthly financial forecas'!E7*'Model inputs'!AM38 -> 400 | F30: ='POA — Monthly financial forecas'!F7*'Model inputs'!AM38 -> 500 | G30: ='POA — Monthly financial forecas'!G7*'Model inputs'!AM38 -> 600 | H30: ='POA — Monthly financial forecas'!H7*'Model inputs'!AM38 -> 866.66667 | I30: ='POA — Monthly financial forecas'!I7*'Model inputs'!AM38 -> 1133.3333 | J30: ='POA — Monthly financial forecas'!J7*'Model inputs'!AM38 -> 1400 | K30: ='POA — Monthly financial forecas'!K7*'Model inputs'!AM38 -> 1666.6667 | L30: ='POA — Monthly financial forecas'!L7*'Model inputs'!AM38 -> 1933.3333 | M30: ='POA — Monthly financial forecas'!M7*'Model inputs'!AM38 -> 2200 | N30: ='POA — Monthly financial forecas'!N7*'Model inputs'!AM38 -> 2833.3333 | O30: ='POA — Monthly financial forecas'!O7*'Model inputs'!AM38 -> 3466.6667 | P30: ='POA — Monthly financial forecas'!P7*'Model inputs'!AM38 -> 4100 | Q30: ='POA — Monthly financial forecas'!Q7*'Model inputs'!AM38 -> 4733.3333 | R30: ='POA — Monthly financial forecas'!R7*'Model inputs'!AM38 -> 5366.6667 | S30: ='POA — Monthly financial forecas'!S7*'Model inputs'!AM38 -> 6000 | T30: ='POA — Monthly financial forecas'!T7*'Model inputs'!AM38 -> 6666.6667 | U30: ='POA — Monthly financial forecas'!U7*'Model inputs'!AM38 -> 7333.3333 | V30: ='POA — Monthly financial forecas'!V7*'Model inputs'!AM38 -> 8000 | W30: ='POA — Monthly financial forecas'!W7*'Model inputs'!AM38 -> 8666.6667 | X30: ='POA — Monthly financial forecas'!X7*'Model inputs'!AM38 -> 9333.3333 | Y30: ='POA — Monthly financial forecas'!Y7*'Model inputs'!AM38 -> 10000 | Z30: ='POA — Monthly financial forecas'!Z7*'Model inputs'!AM38 -> 10583.333 | AA30: ='POA — Monthly financial forecas'!AA7*'Model inputs'!AM38 -> 11166.667 | AB30: ='POA — Monthly financial forecas'!AB7*'Model inputs'!AM38 -> 11750 | AC30: ='POA — Monthly financial forecas'!AC7*'Model inputs'!AM38 -> 12333.333 | AD30: ='POA — Monthly financial forecas'!AD7*'Model inputs'!AM38 -> 12916.667 | AE30: ='POA — Monthly financial forecas'!AE7*'Model inputs'!AM38 -> 13500 | AF30: ='POA — Monthly financial forecas'!AF7*'Model inputs'!AM38 -> 13916.667 | AG30: ='POA — Monthly financial forecas'!AG7*'Model inputs'!AM38 -> 14333.333 | AH30: ='POA — Monthly financial forecas'!AH7*'Model inputs'!AM38 -> 14750 | AI30: ='POA — Monthly financial forecas'!AI7*'Model inputs'!AM38 -> 15166.667 | AJ30: ='POA — Monthly financial forecas'!AJ7*'Model inputs'!AM38 -> 15583.333 | AK30: ='POA — Monthly financial forecas'!AK7*'Model inputs'!AM38 -> 16000
A31: LLM inference delivery cost | B31: ='POA — Monthly financial forecas'!B30*'Model inputs'!AM39 -> 3.8 | C31: ='POA — Monthly financial forecas'!C30*'Model inputs'!AM39 -> 7.6 | D31: ='POA — Monthly financial forecas'!D30*'Model inputs'!AM39 -> 11.4 | E31: ='POA — Monthly financial forecas'!E30*'Model inputs'!AM39 -> 15.2 | F31: ='POA — Monthly financial forecas'!F30*'Model inputs'!AM39 -> 19 | G31: ='POA — Monthly financial forecas'!G30*'Model inputs'!AM39 -> 22.8 | H31: ='POA — Monthly financial forecas'!H30*'Model inputs'!AM39 -> 32.933333 | I31: ='POA — Monthly financial forecas'!I30*'Model inputs'!AM39 -> 43.066667 | J31: ='POA — Monthly financial forecas'!J30*'Model inputs'!AM39 -> 53.2 | K31: ='POA — Monthly financial forecas'!K30*'Model inputs'!AM39 -> 63.333333 | L31: ='POA — Monthly financial forecas'!L30*'Model inputs'!AM39 -> 73.466667 | M31: ='POA — Monthly financial forecas'!M30*'Model inputs'!AM39 -> 83.6 | N31: ='POA — Monthly financial forecas'!N30*'Model inputs'!AM39 -> 107.66667 | O31: ='POA — Monthly financial forecas'!O30*'Model inputs'!AM39 -> 131.73333 | P31: ='POA — Monthly financial forecas'!P30*'Model inputs'!AM39 -> 155.8 | Q31: ='POA — Monthly financial forecas'!Q30*'Model inputs'!AM39 -> 179.86667 | R31: ='POA — Monthly financial forecas'!R30*'Model inputs'!AM39 -> 203.93333 | S31: ='POA — Monthly financial forecas'!S30*'Model inputs'!AM39 -> 228 | T31: ='POA — Monthly financial forecas'!T30*'Model inputs'!AM39 -> 253.33333 | U31: ='POA — Monthly financial forecas'!U30*'Model inputs'!AM39 -> 278.66667 | V31: ='POA — Monthly financial forecas'!V30*'Model inputs'!AM39 -> 304 | W31: ='POA — Monthly financial forecas'!W30*'Model inputs'!AM39 -> 329.33333 | X31: ='POA — Monthly financial forecas'!X30*'Model inputs'!AM39 -> 354.66667 | Y31: ='POA — Monthly financial forecas'!Y30*'Model inputs'!AM39 -> 380 | Z31: ='POA — Monthly financial forecas'!Z30*'Model inputs'!AM39 -> 402.16667 | AA31: ='POA — Monthly financial forecas'!AA30*'Model inputs'!AM39 -> 424.33333 | AB31: ='POA — Monthly financial forecas'!AB30*'Model inputs'!AM39 -> 446.5 | AC31: ='POA — Monthly financial forecas'!AC30*'Model inputs'!AM39 -> 468.66667 | AD31: ='POA — Monthly financial forecas'!AD30*'Model inputs'!AM39 -> 490.83333 | AE31: ='POA — Monthly financial forecas'!AE30*'Model inputs'!AM39 -> 513 | AF31: ='POA — Monthly financial forecas'!AF30*'Model inputs'!AM39 -> 528.83333 | AG31: ='POA — Monthly financial forecas'!AG30*'Model inputs'!AM39 -> 544.66667 | AH31: ='POA — Monthly financial forecas'!AH30*'Model inputs'!AM39 -> 560.5 | AI31: ='POA — Monthly financial forecas'!AI30*'Model inputs'!AM39 -> 576.33333 | AJ31: ='POA — Monthly financial forecas'!AJ30*'Model inputs'!AM39 -> 592.16667 | AK31: ='POA — Monthly financial forecas'!AK30*'Model inputs'!AM39 -> 608
A32: Archive RPC delivery cost | B32: ='POA — Monthly financial forecas'!B30*'Model inputs'!AM8 -> 0.3 | C32: ='POA — Monthly financial forecas'!C30*'Model inputs'!AM8 -> 0.6 | D32: ='POA — Monthly financial forecas'!D30*'Model inputs'!AM8 -> 0.9 | E32: ='POA — Monthly financial forecas'!E30*'Model inputs'!AM8 -> 1.2 | F32: ='POA — Monthly financial forecas'!F30*'Model inputs'!AM8 -> 1.5 | G32: ='POA — Monthly financial forecas'!G30*'Model inputs'!AM8 -> 1.8 | H32: ='POA — Monthly financial forecas'!H30*'Model inputs'!AM8 -> 2.6 | I32: ='POA — Monthly financial forecas'!I30*'Model inputs'!AM8 -> 3.4 | J32: ='POA — Monthly financial forecas'!J30*'Model inputs'!AM8 -> 4.2 | K32: ='POA — Monthly financial forecas'!K30*'Model inputs'!AM8 -> 5 | L32: ='POA — Monthly financial forecas'!L30*'Model inputs'!AM8 -> 5.8 | M32: ='POA — Monthly financial forecas'!M30*'Model inputs'!AM8 -> 6.6 | N32: ='POA — Monthly financial forecas'!N30*'Model inputs'!AM8 -> 8.5 | O32: ='POA — Monthly financial forecas'!O30*'Model inputs'!AM8 -> 10.4 | P32: ='POA — Monthly financial forecas'!P30*'Model inputs'!AM8 -> 12.3 | Q32: ='POA — Monthly financial forecas'!Q30*'Model inputs'!AM8 -> 14.2 | R32: ='POA — Monthly financial forecas'!R30*'Model inputs'!AM8 -> 16.1 | S32: ='POA — Monthly financial forecas'!S30*'Model inputs'!AM8 -> 18 | T32: ='POA — Monthly financial forecas'!T30*'Model inputs'!AM8 -> 20 | U32: ='POA — Monthly financial forecas'!U30*'Model inputs'!AM8 -> 22 | V32: ='POA — Monthly financial forecas'!V30*'Model inputs'!AM8 -> 24 | W32: ='POA — Monthly financial forecas'!W30*'Model inputs'!AM8 -> 26 | X32: ='POA — Monthly financial forecas'!X30*'Model inputs'!AM8 -> 28 | Y32: ='POA — Monthly financial forecas'!Y30*'Model inputs'!AM8 -> 30 | Z32: ='POA — Monthly financial forecas'!Z30*'Model inputs'!AM8 -> 31.75 | AA32: ='POA — Monthly financial forecas'!AA30*'Model inputs'!AM8 -> 33.5 | AB32: ='POA — Monthly financial forecas'!AB30*'Model inputs'!AM8 -> 35.25 | AC32: ='POA — Monthly financial forecas'!AC30*'Model inputs'!AM8 -> 37 | AD32: ='POA — Monthly financial forecas'!AD30*'Model inputs'!AM8 -> 38.75 | AE32: ='POA — Monthly financial forecas'!AE30*'Model inputs'!AM8 -> 40.5 | AF32: ='POA — Monthly financial forecas'!AF30*'Model inputs'!AM8 -> 41.75 | AG32: ='POA — Monthly financial forecas'!AG30*'Model inputs'!AM8 -> 43 | AH32: ='POA — Monthly financial forecas'!AH30*'Model inputs'!AM8 -> 44.25 | AI32: ='POA — Monthly financial forecas'!AI30*'Model inputs'!AM8 -> 45.5 | AJ32: ='POA — Monthly financial forecas'!AJ30*'Model inputs'!AM8 -> 46.75 | AK32: ='POA — Monthly financial forecas'!AK30*'Model inputs'!AM8 -> 48
A33: Telemetry delivery cost | B33: ='POA — Monthly financial forecas'!B30*'Model inputs'!AM84 -> 0.1 | C33: ='POA — Monthly financial forecas'!C30*'Model inputs'!AM84 -> 0.2 | D33: ='POA — Monthly financial forecas'!D30*'Model inputs'!AM84 -> 0.3 | E33: ='POA — Monthly financial forecas'!E30*'Model inputs'!AM84 -> 0.4 | F33: ='POA — Monthly financial forecas'!F30*'Model inputs'!AM84 -> 0.5 | G33: ='POA — Monthly financial forecas'!G30*'Model inputs'!AM84 -> 0.6 | H33: ='POA — Monthly financial forecas'!H30*'Model inputs'!AM84 -> 0.86666667 | I33: ='POA — Monthly financial forecas'!I30*'Model inputs'!AM84 -> 1.1333333 | J33: ='POA — Monthly financial forecas'!J30*'Model inputs'!AM84 -> 1.4 | K33: ='POA — Monthly financial forecas'!K30*'Model inputs'!AM84 -> 1.6666667 | L33: ='POA — Monthly financial forecas'!L30*'Model inputs'!AM84 -> 1.9333333 | M33: ='POA — Monthly financial forecas'!M30*'Model inputs'!AM84 -> 2.2 | N33: ='POA — Monthly financial forecas'!N30*'Model inputs'!AM84 -> 2.8333333 | O33: ='POA — Monthly financial forecas'!O30*'Model inputs'!AM84 -> 3.4666667 | P33: ='POA — Monthly financial forecas'!P30*'Model inputs'!AM84 -> 4.1 | Q33: ='POA — Monthly financial forecas'!Q30*'Model inputs'!AM84 -> 4.7333333 | R33: ='POA — Monthly financial forecas'!R30*'Model inputs'!AM84 -> 5.3666667 | S33: ='POA — Monthly financial forecas'!S30*'Model inputs'!AM84 -> 6 | T33: ='POA — Monthly financial forecas'!T30*'Model inputs'!AM84 -> 6.6666667 | U33: ='POA — Monthly financial forecas'!U30*'Model inputs'!AM84 -> 7.3333333 | V33: ='POA — Monthly financial forecas'!V30*'Model inputs'!AM84 -> 8 | W33: ='POA — Monthly financial forecas'!W30*'Model inputs'!AM84 -> 8.6666667 | X33: ='POA — Monthly financial forecas'!X30*'Model inputs'!AM84 -> 9.3333333 | Y33: ='POA — Monthly financial forecas'!Y30*'Model inputs'!AM84 -> 10 | Z33: ='POA — Monthly financial forecas'!Z30*'Model inputs'!AM84 -> 10.583333 | AA33: ='POA — Monthly financial forecas'!AA30*'Model inputs'!AM84 -> 11.166667 | AB33: ='POA — Monthly financial forecas'!AB30*'Model inputs'!AM84 -> 11.75 | AC33: ='POA — Monthly financial forecas'!AC30*'Model inputs'!AM84 -> 12.333333 | AD33: ='POA — Monthly financial forecas'!AD30*'Model inputs'!AM84 -> 12.916667 | AE33: ='POA — Monthly financial forecas'!AE30*'Model inputs'!AM84 -> 13.5 | AF33: ='POA — Monthly financial forecas'!AF30*'Model inputs'!AM84 -> 13.916667 | AG33: ='POA — Monthly financial forecas'!AG30*'Model inputs'!AM84 -> 14.333333 | AH33: ='POA — Monthly financial forecas'!AH30*'Model inputs'!AM84 -> 14.75 | AI33: ='POA — Monthly financial forecas'!AI30*'Model inputs'!AM84 -> 15.166667 | AJ33: ='POA — Monthly financial forecas'!AJ30*'Model inputs'!AM84 -> 15.583333 | AK33: ='POA — Monthly financial forecas'!AK30*'Model inputs'!AM84 -> 16
A34: Contract registration gas cost | B34: ='POA — Monthly financial forecas'!B30*'Model inputs'!AM35 -> 2 | C34: ='POA — Monthly financial forecas'!C30*'Model inputs'!AM35 -> 4 | D34: ='POA — Monthly financial forecas'!D30*'Model inputs'!AM35 -> 6 | E34: ='POA — Monthly financial forecas'!E30*'Model inputs'!AM35 -> 8 | F34: ='POA — Monthly financial forecas'!F30*'Model inputs'!AM35 -> 10 | G34: ='POA — Monthly financial forecas'!G30*'Model inputs'!AM35 -> 12 | H34: ='POA — Monthly financial forecas'!H30*'Model inputs'!AM35 -> 17.333333 | I34: ='POA — Monthly financial forecas'!I30*'Model inputs'!AM35 -> 22.666667 | J34: ='POA — Monthly financial forecas'!J30*'Model inputs'!AM35 -> 28 | K34: ='POA — Monthly financial forecas'!K30*'Model inputs'!AM35 -> 33.333333 | L34: ='POA — Monthly financial forecas'!L30*'Model inputs'!AM35 -> 38.666667 | M34: ='POA — Monthly financial forecas'!M30*'Model inputs'!AM35 -> 44 | N34: ='POA — Monthly financial forecas'!N30*'Model inputs'!AM35 -> 56.666667 | O34: ='POA — Monthly financial forecas'!O30*'Model inputs'!AM35 -> 69.333333 | P34: ='POA — Monthly financial forecas'!P30*'Model inputs'!AM35 -> 82 | Q34: ='POA — Monthly financial forecas'!Q30*'Model inputs'!AM35 -> 94.666667 | R34: ='POA — Monthly financial forecas'!R30*'Model inputs'!AM35 -> 107.33333 | S34: ='POA — Monthly financial forecas'!S30*'Model inputs'!AM35 -> 120 | T34: ='POA — Monthly financial forecas'!T30*'Model inputs'!AM35 -> 133.33333 | U34: ='POA — Monthly financial forecas'!U30*'Model inputs'!AM35 -> 146.66667 | V34: ='POA — Monthly financial forecas'!V30*'Model inputs'!AM35 -> 160 | W34: ='POA — Monthly financial forecas'!W30*'Model inputs'!AM35 -> 173.33333 | X34: ='POA — Monthly financial forecas'!X30*'Model inputs'!AM35 -> 186.66667 | Y34: ='POA — Monthly financial forecas'!Y30*'Model inputs'!AM35 -> 200 | Z34: ='POA — Monthly financial forecas'!Z30*'Model inputs'!AM35 -> 211.66667 | AA34: ='POA — Monthly financial forecas'!AA30*'Model inputs'!AM35 -> 223.33333 | AB34: ='POA — Monthly financial forecas'!AB30*'Model inputs'!AM35 -> 235 | AC34: ='POA — Monthly financial forecas'!AC30*'Model inputs'!AM35 -> 246.66667 | AD34: ='POA — Monthly financial forecas'!AD30*'Model inputs'!AM35 -> 258.33333 | AE34: ='POA — Monthly financial forecas'!AE30*'Model inputs'!AM35 -> 270 | AF34: ='POA — Monthly financial forecas'!AF30*'Model inputs'!AM35 -> 278.33333 | AG34: ='POA — Monthly financial forecas'!AG30*'Model inputs'!AM35 -> 286.66667 | AH34: ='POA — Monthly financial forecas'!AH30*'Model inputs'!AM35 -> 295 | AI34: ='POA — Monthly financial forecas'!AI30*'Model inputs'!AM35 -> 303.33333 | AJ34: ='POA — Monthly financial forecas'!AJ30*'Model inputs'!AM35 -> 311.66667 | AK34: ='POA — Monthly financial forecas'!AK30*'Model inputs'!AM35 -> 320
A35: Incident COGS | B35: ='POA — Monthly financial forecas'!B31+'POA — Monthly financial forecas'!B32+'POA — Monthly financial forecas'!B33+'POA — Monthly financial forecas'!B34 -> 6.2 | C35: ='POA — Monthly financial forecas'!C31+'POA — Monthly financial forecas'!C32+'POA — Monthly financial forecas'!C33+'POA — Monthly financial forecas'!C34 -> 12.4 | D35: ='POA — Monthly financial forecas'!D31+'POA — Monthly financial forecas'!D32+'POA — Monthly financial forecas'!D33+'POA — Monthly financial forecas'!D34 -> 18.6 | E35: ='POA — Monthly financial forecas'!E31+'POA — Monthly financial forecas'!E32+'POA — Monthly financial forecas'!E33+'POA — Monthly financial forecas'!E34 -> 24.8 | F35: ='POA — Monthly financial forecas'!F31+'POA — Monthly financial forecas'!F32+'POA — Monthly financial forecas'!F33+'POA — Monthly financial forecas'!F34 -> 31 | G35: ='POA — Monthly financial forecas'!G31+'POA — Monthly financial forecas'!G32+'POA — Monthly financial forecas'!G33+'POA — Monthly financial forecas'!G34 -> 37.2 | H35: ='POA — Monthly financial forecas'!H31+'POA — Monthly financial forecas'!H32+'POA — Monthly financial forecas'!H33+'POA — Monthly financial forecas'!H34 -> 53.733333 | I35: ='POA — Monthly financial forecas'!I31+'POA — Monthly financial forecas'!I32+'POA — Monthly financial forecas'!I33+'POA — Monthly financial forecas'!I34 -> 70.266667 | ... AK35: ='POA — Monthly financial forecas'!AK31+'POA — Monthly financial forecas'!AK32+'POA — Monthly financial forecas'!AK33+'POA — Monthly financial forecas'!AK34 -> 992
A36: Other delivery cost provision | B36: =MAX('POA — Monthly financial forecas'!B27*'Model inputs'!AM31-'POA — Monthly financial forecas'!B35,0) -> 0.84166667 | C36: =MAX('POA — Monthly financial forecas'!C27*'Model inputs'!AM31-'POA — Monthly financial forecas'!C35,0) -> 1.7666667 | D36: =MAX('POA — Monthly financial forecas'!D27*'Model inputs'!AM31-'POA — Monthly financial forecas'!D35,0) -> 2.775 | E36: =MAX('POA — Monthly financial forecas'!E27*'Model inputs'!AM31-'POA — Monthly financial forecas'!E35,0) -> 3.8666667 | F36: =MAX('POA — Monthly financial forecas'!F27*'Model inputs'!AM31-'POA — Monthly financial forecas'!F35,0) -> 5.0416667 | G36: =MAX('POA — Monthly financial forecas'!G27*'Model inputs'!AM31-'POA — Monthly financial forecas'!G35,0) -> 6.3 | H36: =MAX('POA — Monthly financial forecas'!H27*'Model inputs'!AM31-'POA — Monthly financial forecas'!H35,0) -> 10.88367 | I36: =MAX('POA — Monthly financial forecas'!I27*'Model inputs'!AM31-'POA — Monthly financial forecas'!I35,0) -> 16.564983 | J36: =MAX('POA — Monthly financial forecas'!J27*'Model inputs'!AM31-'POA — Monthly financial forecas'!J35,0) -> 23.343939 | K36: =MAX('POA — Monthly financial forecas'!K27*'Model inputs'!AM31-'POA — Monthly financial forecas'!K35,0) -> 31.220539 | L36: =MAX('POA — Monthly financial forecas'!L27*'Model inputs'!AM31-'POA — Monthly financial forecas'!L35,0) -> 40.194781 | M36: =MAX('POA — Monthly financial forecas'!M27*'Model inputs'!AM31-'POA — Monthly financial forecas'!M35,0) -> 50.266667 | N36: =MAX('POA — Monthly financial forecas'!N27*'Model inputs'!AM31-'POA — Monthly financial forecas'!N35,0) -> 69.531145 | O36: =MAX('POA — Monthly financial forecas'!O27*'Model inputs'!AM31-'POA — Monthly financial forecas'!O35,0) -> 90.938721 | P36: =MAX('POA — Monthly financial forecas'!P27*'Model inputs'!AM31-'POA — Monthly financial forecas'!P35,0) -> 114.48939 | Q36: =MAX('POA — Monthly financial forecas'!Q27*'Model inputs'!AM31-'POA — Monthly financial forecas'!Q35,0) -> 140.18316 | R36: =MAX('POA — Monthly financial forecas'!R27*'Model inputs'!AM31-'POA — Monthly financial forecas'!R35,0) -> 168.02003 | S36: =MAX('POA — Monthly financial forecas'!S27*'Model inputs'!AM31-'POA — Monthly financial forecas'!S35,0) -> 198 | T36: =MAX('POA — Monthly financial forecas'!T27*'Model inputs'!AM31-'POA — Monthly financial forecas'!T35,0) -> 225.55556 | U36: =MAX('POA — Monthly financial forecas'!U27*'Model inputs'!AM31-'POA — Monthly financial forecas'!U35,0) -> 254.22222 | V36: =MAX('POA — Monthly financial forecas'!V27*'Model inputs'!AM31-'POA — Monthly financial forecas'!V35,0) -> 284 | W36: =MAX('POA — Monthly financial forecas'!W27*'Model inputs'!AM31-'POA — Monthly financial forecas'!W35,0) -> 314.88889 | X36: =MAX('POA — Monthly financial forecas'!X27*'Model inputs'!AM31-'POA — Monthly financial forecas'!X35,0) -> 346.88889 | Y36: =MAX('POA — Monthly financial forecas'!Y27*'Model inputs'!AM31-'POA — Monthly financial forecas'!Y35,0) -> 380 | Z36: =MAX('POA — Monthly financial forecas'!Z27*'Model inputs'!AM31-'POA — Monthly financial forecas'!Z35,0) -> 410.98611 | AA36: =MAX('POA — Monthly financial forecas'!AA27*'Model inputs'!AM31-'POA — Monthly financial forecas'!AA35,0) -> 442.94444 | AB36: =MAX('POA — Monthly financial forecas'!AB27*'Model inputs'!AM31-'POA — Monthly financial forecas'!AB35,0) -> 475.875 | AC36: =MAX('POA — Monthly financial forecas'!AC27*'Model inputs'!AM31-'POA — Monthly financial forecas'!AC35,0) -> 509.77778 | AD36: =MAX('POA — Monthly financial forecas'!AD27*'Model inputs'!AM31-'POA — Monthly financial forecas'!AD35,0) -> 544.65278 | AE36: =MAX('POA — Monthly financial forecas'!AE27*'Model inputs'!AM31-'POA — Monthly financial forecas'!AE35,0) -> 580.5 | AF36: =MAX('POA — Monthly financial forecas'!AF27*'Model inputs'!AM31-'POA — Monthly financial forecas'!AF35,0) -> 610.01389 | AG36: =MAX('POA — Monthly financial forecas'!AG27*'Model inputs'!AM31-'POA — Monthly financial forecas'!AG35,0) -> 640.22222 | AH36: =MAX('POA — Monthly financial forecas'!AH27*'Model inputs'!AM31-'POA — Monthly financial forecas'!AH35,0) -> 671.125 | AI36: =MAX('POA — Monthly financial forecas'!AI27*'Model inputs'!AM31-'POA — Monthly financial forecas'!AI35,0) -> 702.72222 | AJ36: =MAX('POA — Monthly financial forecas'!AJ27*'Model inputs'!AM31-'POA — Monthly financial forecas'!AJ35,0) -> 735.01389 | AK36: =MAX('POA — Monthly financial forecas'!AK27*'Model inputs'!AM31-'POA — Monthly financial forecas'!AK35,0) -> 768
A37: Total COGS | B37: ='POA — Monthly financial forecas'!B35+'POA — Monthly financial forecas'!B36 -> 7.0416667 | C37: ='POA — Monthly financial forecas'!C35+'POA — Monthly financial forecas'!C36 -> 14.166667 | D37: ='POA — Monthly financial forecas'!D35+'POA — Monthly financial forecas'!D36 -> 21.375 | E37: ='POA — Monthly financial forecas'!E35+'POA — Monthly financial forecas'!E36 -> 28.666667 | F37: ='POA — Monthly financial forecas'!F35+'POA — Monthly financial forecas'!F36 -> 36.041667 | G37: ='POA — Monthly financial forecas'!G35+'POA — Monthly financial forecas'!G36 -> 43.5 | H37: ='POA — Monthly financial forecas'!H35+'POA — Monthly financial forecas'!H36 -> 64.617003 | I37: ='POA — Monthly financial forecas'!I35+'POA — Monthly financial forecas'!I36 -> 86.83165 | ... AK37: ='POA — Monthly financial forecas'!AK35+'POA — Monthly financial forecas'!AK36 -> 1760
A38: Gross profit | B38: ='POA — Monthly financial forecas'!B27-'POA — Monthly financial forecas'!B37 -> 3513.7917 | C38: ='POA — Monthly financial forecas'!C27-'POA — Monthly financial forecas'!C37 -> 7069.1667 | D38: ='POA — Monthly financial forecas'!D27-'POA — Monthly financial forecas'!D37 -> 10666.125 | E38: ='POA — Monthly financial forecas'!E27-'POA — Monthly financial forecas'!E37 -> 14304.667 | F38: ='POA — Monthly financial forecas'!F27-'POA — Monthly financial forecas'!F37 -> 17984.792 | G38: ='POA — Monthly financial forecas'!G27-'POA — Monthly financial forecas'!G37 -> 21706.5 | H38: ='POA — Monthly financial forecas'!H27-'POA — Monthly financial forecas'!H37 -> 32243.885 | I38: ='POA — Monthly financial forecas'!I27-'POA — Monthly financial forecas'!I37 -> 43328.993 | ... AK38: ='POA — Monthly financial forecas'!AK27-'POA — Monthly financial forecas'!AK37 -> 878240
A39: Gross margin | B39: =IFERROR('POA — Monthly financial forecas'!B38/'POA — Monthly financial forecas'!B27,"") -> 0.998 | C39: =IFERROR('POA — Monthly financial forecas'!C38/'POA — Monthly financial forecas'!C27,"") -> 0.998 | D39: =IFERROR('POA — Monthly financial forecas'!D38/'POA — Monthly financial forecas'!D27,"") -> 0.998 | E39: =IFERROR('POA — Monthly financial forecas'!E38/'POA — Monthly financial forecas'!E27,"") -> 0.998 | F39: =IFERROR('POA — Monthly financial forecas'!F38/'POA — Monthly financial forecas'!F27,"") -> 0.998 | G39: =IFERROR('POA — Monthly financial forecas'!G38/'POA — Monthly financial forecas'!G27,"") -> 0.998 | H39: =IFERROR('POA — Monthly financial forecas'!H38/'POA — Monthly financial forecas'!H27,"") -> 0.998 | I39: =IFERROR('POA — Monthly financial forecas'!I38/'POA — Monthly financial forecas'!I27,"") -> 0.998 | ... AK39: =IFERROR('POA — Monthly financial forecas'!AK38/'POA — Monthly financial forecas'!AK27,"") -> 0.998
A40: Operating budget | B40: =IF('Model inputs'!B759="",0,'Model inputs'!B759)*'Model inputs'!AM60 -> 12083.333 | C40: =IF('Model inputs'!B760="",0,'Model inputs'!B760)*'Model inputs'!AM60 -> 14166.667 | D40: =IF('Model inputs'!B761="",0,'Model inputs'!B761)*'Model inputs'!AM60 -> 16250 | E40: =IF('Model inputs'!B762="",0,'Model inputs'!B762)*'Model inputs'!AM60 -> 18333.333 | F40: =IF('Model inputs'!B763="",0,'Model inputs'!B763)*'Model inputs'!AM60 -> 20416.667 | G40: =IF('Model inputs'!B764="",0,'Model inputs'!B764)*'Model inputs'!AM60 -> 22500 | H40: =IF('Model inputs'!B765="",0,'Model inputs'!B765)*'Model inputs'!AM60 -> 26716.667 | I40: =IF('Model inputs'!B766="",0,'Model inputs'!B766)*'Model inputs'!AM60 -> 30933.333 | J40: =IF('Model inputs'!B767="",0,'Model inputs'!B767)*'Model inputs'!AM60 -> 35150 | K40: =IF('Model inputs'!B768="",0,'Model inputs'!B768)*'Model inputs'!AM60 -> 39366.667 | L40: =IF('Model inputs'!B769="",0,'Model inputs'!B769)*'Model inputs'!AM60 -> 43583.333 | M40: =IF('Model inputs'!B770="",0,'Model inputs'!B770)*'Model inputs'!AM60 -> 47800 | N40: =IF('Model inputs'!B771="",0,'Model inputs'!B771)*'Model inputs'!AM60 -> 56200 | O40: =IF('Model inputs'!B772="",0,'Model inputs'!B772)*'Model inputs'!AM60 -> 64600 | P40: =IF('Model inputs'!B773="",0,'Model inputs'!B773)*'Model inputs'!AM60 -> 73000 | Q40: =IF('Model inputs'!B774="",0,'Model inputs'!B774)*'Model inputs'!AM60 -> 81400 | R40: =IF('Model inputs'!B775="",0,'Model inputs'!B775)*'Model inputs'!AM60 -> 89800 | S40: =IF('Model inputs'!B776="",0,'Model inputs'!B776)*'Model inputs'!AM60 -> 98200 | T40: =IF('Model inputs'!B777="",0,'Model inputs'!B777)*'Model inputs'!AM60 -> 105166.67 | U40: =IF('Model inputs'!B778="",0,'Model inputs'!B778)*'Model inputs'!AM60 -> 112133.33 | V40: =IF('Model inputs'!B779="",0,'Model inputs'!B779)*'Model inputs'!AM60 -> 119100 | W40: =IF('Model inputs'!B780="",0,'Model inputs'!B780)*'Model inputs'!AM60 -> 126066.67 | X40: =IF('Model inputs'!B781="",0,'Model inputs'!B781)*'Model inputs'!AM60 -> 133033.33 | Y40: =IF('Model inputs'!B782="",0,'Model inputs'!B782)*'Model inputs'!AM60 -> 140000 | Z40: =IF('Model inputs'!B783="",0,'Model inputs'!B783)*'Model inputs'!AM60 -> 145833.33 | AA40: =IF('Model inputs'!B784="",0,'Model inputs'!B784)*'Model inputs'!AM60 -> 151666.67 | AB40: =IF('Model inputs'!B785="",0,'Model inputs'!B785)*'Model inputs'!AM60 -> 157500 | AC40: =IF('Model inputs'!B786="",0,'Model inputs'!B786)*'Model inputs'!AM60 -> 163333.33 | AD40: =IF('Model inputs'!B787="",0,'Model inputs'!B787)*'Model inputs'!AM60 -> 169166.67 | AE40: =IF('Model inputs'!B788="",0,'Model inputs'!B788)*'Model inputs'!AM60 -> 175000 | AF40: =IF('Model inputs'!B789="",0,'Model inputs'!B789)*'Model inputs'!AM60 -> 180000 | AG40: =IF('Model inputs'!B790="",0,'Model inputs'!B790)*'Model inputs'!AM60 -> 185000 | AH40: =IF('Model inputs'!B791="",0,'Model inputs'!B791)*'Model inputs'!AM60 -> 190000 | AI40: =IF('Model inputs'!B792="",0,'Model inputs'!B792)*'Model inputs'!AM60 -> 195000 | AJ40: =IF('Model inputs'!B793="",0,'Model inputs'!B793)*'Model inputs'!AM60 -> 200000 | AK40: =IF('Model inputs'!B794="",0,'Model inputs'!B794)*'Model inputs'!AM60 -> 205000
A41: Operating expenses by category | B41: =SUM('POA — Monthly financial forecas'!B42,'POA — Monthly financial forecas'!B43,'POA — Monthly financial forecas'!B44,'POA — Monthly financial forecas'!B45,'POA — Monthly financial forecas'!B46) -> 12083.333 | C41: =SUM('POA — Monthly financial forecas'!C42,'POA — Monthly financial forecas'!C43,'POA — Monthly financial forecas'!C44,'POA — Monthly financial forecas'!C45,'POA — Monthly financial forecas'!C46) -> 14166.667 | D41: =SUM('POA — Monthly financial forecas'!D42,'POA — Monthly financial forecas'!D43,'POA — Monthly financial forecas'!D44,'POA — Monthly financial forecas'!D45,'POA — Monthly financial forecas'!D46) -> 16250 | E41: =SUM('POA — Monthly financial forecas'!E42,'POA — Monthly financial forecas'!E43,'POA — Monthly financial forecas'!E44,'POA — Monthly financial forecas'!E45,'POA — Monthly financial forecas'!E46) -> 18333.333 | F41: =SUM('POA — Monthly financial forecas'!F42,'POA — Monthly financial forecas'!F43,'POA — Monthly financial forecas'!F44,'POA — Monthly financial forecas'!F45,'POA — Monthly financial forecas'!F46) -> 20416.667 | G41: =SUM('POA — Monthly financial forecas'!G42,'POA — Monthly financial forecas'!G43,'POA — Monthly financial forecas'!G44,'POA — Monthly financial forecas'!G45,'POA — Monthly financial forecas'!G46) -> 22500 | H41: =SUM('POA — Monthly financial forecas'!H42,'POA — Monthly financial forecas'!H43,'POA — Monthly financial forecas'!H44,'POA — Monthly financial forecas'!H45,'POA — Monthly financial forecas'!H46) -> 26716.667 | I41: =SUM('POA — Monthly financial forecas'!I42,'POA — Monthly financial forecas'!I43,'POA — Monthly financial forecas'!I44,'POA — Monthly financial forecas'!I45,'POA — Monthly financial forecas'!I46) -> 30933.333 | ... AK41: =SUM('POA — Monthly financial forecas'!AK42,'POA — Monthly financial forecas'!AK43,'POA — Monthly financial forecas'!AK44,'POA — Monthly financial forecas'!AK45,'POA — Monthly financial forecas'!AK46) -> 205000
A42: General and administrative | B42: ='POA — Monthly financial forecas'!B40*'Model inputs'!AM48 -> 604.16667 | C42: ='POA — Monthly financial forecas'!C40*'Model inputs'!AM48 -> 708.33333 | D42: ='POA — Monthly financial forecas'!D40*'Model inputs'!AM48 -> 812.5 | E42: ='POA — Monthly financial forecas'!E40*'Model inputs'!AM48 -> 916.66667 | F42: ='POA — Monthly financial forecas'!F40*'Model inputs'!AM48 -> 1020.8333 | G42: ='POA — Monthly financial forecas'!G40*'Model inputs'!AM48 -> 1125 | H42: ='POA — Monthly financial forecas'!H40*'Model inputs'!AM48 -> 1335.8333 | I42: ='POA — Monthly financial forecas'!I40*'Model inputs'!AM48 -> 1546.6667 | J42: ='POA — Monthly financial forecas'!J40*'Model inputs'!AM48 -> 1757.5 | K42: ='POA — Monthly financial forecas'!K40*'Model inputs'!AM48 -> 1968.3333 | L42: ='POA — Monthly financial forecas'!L40*'Model inputs'!AM48 -> 2179.1667 | M42: ='POA — Monthly financial forecas'!M40*'Model inputs'!AM48 -> 2390 | N42: ='POA — Monthly financial forecas'!N40*'Model inputs'!AM48 -> 2810 | O42: ='POA — Monthly financial forecas'!O40*'Model inputs'!AM48 -> 3230 | P42: ='POA — Monthly financial forecas'!P40*'Model inputs'!AM48 -> 3650 | Q42: ='POA — Monthly financial forecas'!Q40*'Model inputs'!AM48 -> 4070 | R42: ='POA — Monthly financial forecas'!R40*'Model inputs'!AM48 -> 4490 | S42: ='POA — Monthly financial forecas'!S40*'Model inputs'!AM48 -> 4910 | T42: ='POA — Monthly financial forecas'!T40*'Model inputs'!AM48 -> 5258.3333 | U42: ='POA — Monthly financial forecas'!U40*'Model inputs'!AM48 -> 5606.6667 | V42: ='POA — Monthly financial forecas'!V40*'Model inputs'!AM48 -> 5955 | W42: ='POA — Monthly financial forecas'!W40*'Model inputs'!AM48 -> 6303.3333 | X42: ='POA — Monthly financial forecas'!X40*'Model inputs'!AM48 -> 6651.6667 | Y42: ='POA — Monthly financial forecas'!Y40*'Model inputs'!AM48 -> 7000 | Z42: ='POA — Monthly financial forecas'!Z40*'Model inputs'!AM48 -> 7291.6667 | AA42: ='POA — Monthly financial forecas'!AA40*'Model inputs'!AM48 -> 7583.3333 | AB42: ='POA — Monthly financial forecas'!AB40*'Model inputs'!AM48 -> 7875 | AC42: ='POA — Monthly financial forecas'!AC40*'Model inputs'!AM48 -> 8166.6667 | AD42: ='POA — Monthly financial forecas'!AD40*'Model inputs'!AM48 -> 8458.3333 | AE42: ='POA — Monthly financial forecas'!AE40*'Model inputs'!AM48 -> 8750 | AF42: ='POA — Monthly financial forecas'!AF40*'Model inputs'!AM48 -> 9000 | AG42: ='POA — Monthly financial forecas'!AG40*'Model inputs'!AM48 -> 9250 | AH42: ='POA — Monthly financial forecas'!AH40*'Model inputs'!AM48 -> 9500 | AI42: ='POA — Monthly financial forecas'!AI40*'Model inputs'!AM48 -> 9750 | AJ42: ='POA — Monthly financial forecas'!AJ40*'Model inputs'!AM48 -> 10000 | AK42: ='POA — Monthly financial forecas'!AK40*'Model inputs'!AM48 -> 10250
A43: Legal security and insurance | B43: ='POA — Monthly financial forecas'!B40*'Model inputs'!AM49 -> 1208.3333 | C43: ='POA — Monthly financial forecas'!C40*'Model inputs'!AM49 -> 1416.6667 | D43: ='POA — Monthly financial forecas'!D40*'Model inputs'!AM49 -> 1625 | E43: ='POA — Monthly financial forecas'!E40*'Model inputs'!AM49 -> 1833.3333 | F43: ='POA — Monthly financial forecas'!F40*'Model inputs'!AM49 -> 2041.6667 | G43: ='POA — Monthly financial forecas'!G40*'Model inputs'!AM49 -> 2250 | H43: ='POA — Monthly financial forecas'!H40*'Model inputs'!AM49 -> 2671.6667 | I43: ='POA — Monthly financial forecas'!I40*'Model inputs'!AM49 -> 3093.3333 | J43: ='POA — Monthly financial forecas'!J40*'Model inputs'!AM49 -> 3515 | K43: ='POA — Monthly financial forecas'!K40*'Model inputs'!AM49 -> 3936.6667 | L43: ='POA — Monthly financial forecas'!L40*'Model inputs'!AM49 -> 4358.3333 | M43: ='POA — Monthly financial forecas'!M40*'Model inputs'!AM49 -> 4780 | N43: ='POA — Monthly financial forecas'!N40*'Model inputs'!AM49 -> 5620 | O43: ='POA — Monthly financial forecas'!O40*'Model inputs'!AM49 -> 6460 | P43: ='POA — Monthly financial forecas'!P40*'Model inputs'!AM49 -> 7300 | Q43: ='POA — Monthly financial forecas'!Q40*'Model inputs'!AM49 -> 8140 | R43: ='POA — Monthly financial forecas'!R40*'Model inputs'!AM49 -> 8980 | S43: ='POA — Monthly financial forecas'!S40*'Model inputs'!AM49 -> 9820 | T43: ='POA — Monthly financial forecas'!T40*'Model inputs'!AM49 -> 10516.667 | U43: ='POA — Monthly financial forecas'!U40*'Model inputs'!AM49 -> 11213.333 | V43: ='POA — Monthly financial forecas'!V40*'Model inputs'!AM49 -> 11910 | W43: ='POA — Monthly financial forecas'!W40*'Model inputs'!AM49 -> 12606.667 | X43: ='POA — Monthly financial forecas'!X40*'Model inputs'!AM49 -> 13303.333 | Y43: ='POA — Monthly financial forecas'!Y40*'Model inputs'!AM49 -> 14000 | Z43: ='POA — Monthly financial forecas'!Z40*'Model inputs'!AM49 -> 14583.333 | AA43: ='POA — Monthly financial forecas'!AA40*'Model inputs'!AM49 -> 15166.667 | AB43: ='POA — Monthly financial forecas'!AB40*'Model inputs'!AM49 -> 15750 | AC43: ='POA — Monthly financial forecas'!AC40*'Model inputs'!AM49 -> 16333.333 | AD43: ='POA — Monthly financial forecas'!AD40*'Model inputs'!AM49 -> 16916.667 | AE43: ='POA — Monthly financial forecas'!AE40*'Model inputs'!AM49 -> 17500 | AF43: ='POA — Monthly financial forecas'!AF40*'Model inputs'!AM49 -> 18000 | AG43: ='POA — Monthly financial forecas'!AG40*'Model inputs'!AM49 -> 18500 | AH43: ='POA — Monthly financial forecas'!AH40*'Model inputs'!AM49 -> 19000 | AI43: ='POA — Monthly financial forecas'!AI40*'Model inputs'!AM49 -> 19500 | AJ43: ='POA — Monthly financial forecas'!AJ40*'Model inputs'!AM49 -> 20000 | AK43: ='POA — Monthly financial forecas'!AK40*'Model inputs'!AM49 -> 20500
A44: Payroll and benefits | B44: ='POA — Monthly financial forecas'!B40*'Model inputs'!AM50 -> 7854.1667 | C44: ='POA — Monthly financial forecas'!C40*'Model inputs'!AM50 -> 9208.3333 | D44: ='POA — Monthly financial forecas'!D40*'Model inputs'!AM50 -> 10562.5 | E44: ='POA — Monthly financial forecas'!E40*'Model inputs'!AM50 -> 11916.667 | F44: ='POA — Monthly financial forecas'!F40*'Model inputs'!AM50 -> 13270.833 | G44: ='POA — Monthly financial forecas'!G40*'Model inputs'!AM50 -> 14625 | H44: ='POA — Monthly financial forecas'!H40*'Model inputs'!AM50 -> 17365.833 | I44: ='POA — Monthly financial forecas'!I40*'Model inputs'!AM50 -> 20106.667 | J44: ='POA — Monthly financial forecas'!J40*'Model inputs'!AM50 -> 22847.5 | K44: ='POA — Monthly financial forecas'!K40*'Model inputs'!AM50 -> 25588.333 | L44: ='POA — Monthly financial forecas'!L40*'Model inputs'!AM50 -> 28329.167 | M44: ='POA — Monthly financial forecas'!M40*'Model inputs'!AM50 -> 31070 | N44: ='POA — Monthly financial forecas'!N40*'Model inputs'!AM50 -> 36530 | O44: ='POA — Monthly financial forecas'!O40*'Model inputs'!AM50 -> 41990 | P44: ='POA — Monthly financial forecas'!P40*'Model inputs'!AM50 -> 47450 | Q44: ='POA — Monthly financial forecas'!Q40*'Model inputs'!AM50 -> 52910 | R44: ='POA — Monthly financial forecas'!R40*'Model inputs'!AM50 -> 58370 | S44: ='POA — Monthly financial forecas'!S40*'Model inputs'!AM50 -> 63830 | T44: ='POA — Monthly financial forecas'!T40*'Model inputs'!AM50 -> 68358.333 | U44: ='POA — Monthly financial forecas'!U40*'Model inputs'!AM50 -> 72886.667 | V44: ='POA — Monthly financial forecas'!V40*'Model inputs'!AM50 -> 77415 | W44: ='POA — Monthly financial forecas'!W40*'Model inputs'!AM50 -> 81943.333 | X44: ='POA — Monthly financial forecas'!X40*'Model inputs'!AM50 -> 86471.667 | Y44: ='POA — Monthly financial forecas'!Y40*'Model inputs'!AM50 -> 91000 | Z44: ='POA — Monthly financial forecas'!Z40*'Model inputs'!AM50 -> 94791.667 | AA44: ='POA — Monthly financial forecas'!AA40*'Model inputs'!AM50 -> 98583.333 | AB44: ='POA — Monthly financial forecas'!AB40*'Model inputs'!AM50 -> 102375 | AC44: ='POA — Monthly financial forecas'!AC40*'Model inputs'!AM50 -> 106166.67 | AD44: ='POA — Monthly financial forecas'!AD40*'Model inputs'!AM50 -> 109958.33 | AE44: ='POA — Monthly financial forecas'!AE40*'Model inputs'!AM50 -> 113750 | AF44: ='POA — Monthly financial forecas'!AF40*'Model inputs'!AM50 -> 117000 | AG44: ='POA — Monthly financial forecas'!AG40*'Model inputs'!AM50 -> 120250 | AH44: ='POA — Monthly financial forecas'!AH40*'Model inputs'!AM50 -> 123500 | AI44: ='POA — Monthly financial forecas'!AI40*'Model inputs'!AM50 -> 126750 | AJ44: ='POA — Monthly financial forecas'!AJ40*'Model inputs'!AM50 -> 130000 | AK44: ='POA — Monthly financial forecas'!AK40*'Model inputs'!AM50 -> 133250
A45: Product and infrastructure overhead | B45: ='POA — Monthly financial forecas'!B40*'Model inputs'!AM51 -> 1450 | C45: ='POA — Monthly financial forecas'!C40*'Model inputs'!AM51 -> 1700 | D45: ='POA — Monthly financial forecas'!D40*'Model inputs'!AM51 -> 1950 | E45: ='POA — Monthly financial forecas'!E40*'Model inputs'!AM51 -> 2200 | F45: ='POA — Monthly financial forecas'!F40*'Model inputs'!AM51 -> 2450 | G45: ='POA — Monthly financial forecas'!G40*'Model inputs'!AM51 -> 2700 | H45: ='POA — Monthly financial forecas'!H40*'Model inputs'!AM51 -> 3206 | I45: ='POA — Monthly financial forecas'!I40*'Model inputs'!AM51 -> 3712 | J45: ='POA — Monthly financial forecas'!J40*'Model inputs'!AM51 -> 4218 | K45: ='POA — Monthly financial forecas'!K40*'Model inputs'!AM51 -> 4724 | L45: ='POA — Monthly financial forecas'!L40*'Model inputs'!AM51 -> 5230 | M45: ='POA — Monthly financial forecas'!M40*'Model inputs'!AM51 -> 5736 | N45: ='POA — Monthly financial forecas'!N40*'Model inputs'!AM51 -> 6744 | O45: ='POA — Monthly financial forecas'!O40*'Model inputs'!AM51 -> 7752 | P45: ='POA — Monthly financial forecas'!P40*'Model inputs'!AM51 -> 8760 | Q45: ='POA — Monthly financial forecas'!Q40*'Model inputs'!AM51 -> 9768 | R45: ='POA — Monthly financial forecas'!R40*'Model inputs'!AM51 -> 10776 | S45: ='POA — Monthly financial forecas'!S40*'Model inputs'!AM51 -> 11784 | T45: ='POA — Monthly financial forecas'!T40*'Model inputs'!AM51 -> 12620 | U45: ='POA — Monthly financial forecas'!U40*'Model inputs'!AM51 -> 13456 | V45: ='POA — Monthly financial forecas'!V40*'Model inputs'!AM51 -> 14292 | W45: ='POA — Monthly financial forecas'!W40*'Model inputs'!AM51 -> 15128 | X45: ='POA — Monthly financial forecas'!X40*'Model inputs'!AM51 -> 15964 | Y45: ='POA — Monthly financial forecas'!Y40*'Model inputs'!AM51 -> 16800 | Z45: ='POA — Monthly financial forecas'!Z40*'Model inputs'!AM51 -> 17500 | AA45: ='POA — Monthly financial forecas'!AA40*'Model inputs'!AM51 -> 18200 | AB45: ='POA — Monthly financial forecas'!AB40*'Model inputs'!AM51 -> 18900 | AC45: ='POA — Monthly financial forecas'!AC40*'Model inputs'!AM51 -> 19600 | AD45: ='POA — Monthly financial forecas'!AD40*'Model inputs'!AM51 -> 20300 | AE45: ='POA — Monthly financial forecas'!AE40*'Model inputs'!AM51 -> 21000 | AF45: ='POA — Monthly financial forecas'!AF40*'Model inputs'!AM51 -> 21600 | AG45: ='POA — Monthly financial forecas'!AG40*'Model inputs'!AM51 -> 22200 | AH45: ='POA — Monthly financial forecas'!AH40*'Model inputs'!AM51 -> 22800 | AI45: ='POA — Monthly financial forecas'!AI40*'Model inputs'!AM51 -> 23400 | AJ45: ='POA — Monthly financial forecas'!AJ40*'Model inputs'!AM51 -> 24000 | AK45: ='POA — Monthly financial forecas'!AK40*'Model inputs'!AM51 -> 24600
A46: Sales and marketing overhead | B46: ='POA — Monthly financial forecas'!B40*'Model inputs'!AM52 -> 966.66667 | C46: ='POA — Monthly financial forecas'!C40*'Model inputs'!AM52 -> 1133.3333 | D46: ='POA — Monthly financial forecas'!D40*'Model inputs'!AM52 -> 1300 | E46: ='POA — Monthly financial forecas'!E40*'Model inputs'!AM52 -> 1466.6667 | F46: ='POA — Monthly financial forecas'!F40*'Model inputs'!AM52 -> 1633.3333 | G46: ='POA — Monthly financial forecas'!G40*'Model inputs'!AM52 -> 1800 | H46: ='POA — Monthly financial forecas'!H40*'Model inputs'!AM52 -> 2137.3333 | I46: ='POA — Monthly financial forecas'!I40*'Model inputs'!AM52 -> 2474.6667 | J46: ='POA — Monthly financial forecas'!J40*'Model inputs'!AM52 -> 2812 | K46: ='POA — Monthly financial forecas'!K40*'Model inputs'!AM52 -> 3149.3333 | L46: ='POA — Monthly financial forecas'!L40*'Model inputs'!AM52 -> 3486.6667 | M46: ='POA — Monthly financial forecas'!M40*'Model inputs'!AM52 -> 3824 | N46: ='POA — Monthly financial forecas'!N40*'Model inputs'!AM52 -> 4496 | O46: ='POA — Monthly financial forecas'!O40*'Model inputs'!AM52 -> 5168 | P46: ='POA — Monthly financial forecas'!P40*'Model inputs'!AM52 -> 5840 | Q46: ='POA — Monthly financial forecas'!Q40*'Model inputs'!AM52 -> 6512 | R46: ='POA — Monthly financial forecas'!R40*'Model inputs'!AM52 -> 7184 | S46: ='POA — Monthly financial forecas'!S40*'Model inputs'!AM52 -> 7856 | T46: ='POA — Monthly financial forecas'!T40*'Model inputs'!AM52 -> 8413.3333 | U46: ='POA — Monthly financial forecas'!U40*'Model inputs'!AM52 -> 8970.6667 | V46: ='POA — Monthly financial forecas'!V40*'Model inputs'!AM52 -> 9528 | W46: ='POA — Monthly financial forecas'!W40*'Model inputs'!AM52 -> 10085.333 | X46: ='POA — Monthly financial forecas'!X40*'Model inputs'!AM52 -> 10642.667 | Y46: ='POA — Monthly financial forecas'!Y40*'Model inputs'!AM52 -> 11200 | Z46: ='POA — Monthly financial forecas'!Z40*'Model inputs'!AM52 -> 11666.667 | AA46: ='POA — Monthly financial forecas'!AA40*'Model inputs'!AM52 -> 12133.333 | AB46: ='POA — Monthly financial forecas'!AB40*'Model inputs'!AM52 -> 12600 | AC46: ='POA — Monthly financial forecas'!AC40*'Model inputs'!AM52 -> 13066.667 | AD46: ='POA — Monthly financial forecas'!AD40*'Model inputs'!AM52 -> 13533.333 | AE46: ='POA — Monthly financial forecas'!AE40*'Model inputs'!AM52 -> 14000 | AF46: ='POA — Monthly financial forecas'!AF40*'Model inputs'!AM52 -> 14400 | AG46: ='POA — Monthly financial forecas'!AG40*'Model inputs'!AM52 -> 14800 | AH46: ='POA — Monthly financial forecas'!AH40*'Model inputs'!AM52 -> 15200 | AI46: ='POA — Monthly financial forecas'!AI40*'Model inputs'!AM52 -> 15600 | AJ46: ='POA — Monthly financial forecas'!AJ40*'Model inputs'!AM52 -> 16000 | AK46: ='POA — Monthly financial forecas'!AK40*'Model inputs'!AM52 -> 16400
A47: Customer acquisition spend | B47: ='POA — Monthly financial forecas'!B11*'Model inputs'!AM11*'Model inputs'!AM10 -> 9200 | C47: ='POA — Monthly financial forecas'!C11*'Model inputs'!AM11*'Model inputs'!AM10 -> 9419.0476 | D47: ='POA — Monthly financial forecas'!D11*'Model inputs'!AM11*'Model inputs'!AM10 -> 9638.0952 | E47: ='POA — Monthly financial forecas'!E11*'Model inputs'!AM11*'Model inputs'!AM10 -> 9857.1429 | F47: ='POA — Monthly financial forecas'!F11*'Model inputs'!AM11*'Model inputs'!AM10 -> 10076.19 | G47: ='POA — Monthly financial forecas'!G11*'Model inputs'!AM11*'Model inputs'!AM10 -> 10295.238 | H47: ='POA — Monthly financial forecas'!H11*'Model inputs'!AM11*'Model inputs'!AM10 -> 25847.619 | I47: ='POA — Monthly financial forecas'!I11*'Model inputs'!AM11*'Model inputs'!AM10 -> 26431.746 | J47: ='POA — Monthly financial forecas'!J11*'Model inputs'!AM11*'Model inputs'!AM10 -> 27015.873 | K47: ='POA — Monthly financial forecas'!K11*'Model inputs'!AM11*'Model inputs'!AM10 -> 27600 | L47: ='POA — Monthly financial forecas'!L11*'Model inputs'!AM11*'Model inputs'!AM10 -> 28184.127 | M47: ='POA — Monthly financial forecas'!M11*'Model inputs'!AM11*'Model inputs'!AM10 -> 28768.254 | N47: ='POA — Monthly financial forecas'!N11*'Model inputs'!AM11*'Model inputs'!AM10 -> 63085.714 | O47: ='POA — Monthly financial forecas'!O11*'Model inputs'!AM11*'Model inputs'!AM10 -> 64473.016 | P47: ='POA — Monthly financial forecas'!P11*'Model inputs'!AM11*'Model inputs'!AM10 -> 65860.317 | Q47: ='POA — Monthly financial forecas'!Q11*'Model inputs'!AM11*'Model inputs'!AM10 -> 67247.619 | R47: ='POA — Monthly financial forecas'!R11*'Model inputs'!AM11*'Model inputs'!AM10 -> 68634.921 | S47: ='POA — Monthly financial forecas'!S11*'Model inputs'!AM11*'Model inputs'!AM10 -> 70022.222 | T47: ='POA — Monthly financial forecas'!T11*'Model inputs'!AM11*'Model inputs'!AM10 -> 74476.19 | U47: ='POA — Monthly financial forecas'!U11*'Model inputs'!AM11*'Model inputs'!AM10 -> 75936.508 | V47: ='POA — Monthly financial forecas'!V11*'Model inputs'!AM11*'Model inputs'!AM10 -> 77396.825 | W47: ='POA — Monthly financial forecas'!W11*'Model inputs'!AM11*'Model inputs'!AM10 -> 78857.143 | X47: ='POA — Monthly financial forecas'!X11*'Model inputs'!AM11*'Model inputs'!AM10 -> 80317.46 | Y47: ='POA — Monthly financial forecas'!Y11*'Model inputs'!AM11*'Model inputs'!AM10 -> 81777.778 | Z47: ='POA — Monthly financial forecas'!Z11*'Model inputs'!AM11*'Model inputs'!AM10 -> 75571.429 | AA47: ='POA — Monthly financial forecas'!AA11*'Model inputs'!AM11*'Model inputs'!AM10 -> 76849.206 | AB47: ='POA — Monthly financial forecas'!AB11*'Model inputs'!AM11*'Model inputs'!AM10 -> 78126.984 | AC47: ='POA — Monthly financial forecas'!AC11*'Model inputs'!AM11*'Model inputs'!AM10 -> 79404.762 | AD47: ='POA — Monthly financial forecas'!AD11*'Model inputs'!AM11*'Model inputs'!AM10 -> 80682.54 | AE47: ='POA — Monthly financial forecas'!AE11*'Model inputs'!AM11*'Model inputs'!AM10 -> 81960.317 | AF47: ='POA — Monthly financial forecas'!AF11*'Model inputs'!AM11*'Model inputs'!AM10 -> 67904.762 | AG47: ='POA — Monthly financial forecas'!AG11*'Model inputs'!AM11*'Model inputs'!AM10 -> 68817.46 | AH47: ='POA — Monthly financial forecas'!AH11*'Model inputs'!AM11*'Model inputs'!AM10 -> 69730.159 | AI47: ='POA — Monthly financial forecas'!AI11*'Model inputs'!AM11*'Model inputs'!AM10 -> 70642.857 | AJ47: ='POA — Monthly financial forecas'!AJ11*'Model inputs'!AM11*'Model inputs'!AM10 -> 71555.556 | AK47: ='POA — Monthly financial forecas'!AK11*'Model inputs'!AM11*'Model inputs'!AM10 -> 72468.254
A48: Total operating expenses | B48: ='POA — Monthly financial forecas'!B41+'POA — Monthly financial forecas'!B47 -> 21283.333 | C48: ='POA — Monthly financial forecas'!C41+'POA — Monthly financial forecas'!C47 -> 23585.714 | D48: ='POA — Monthly financial forecas'!D41+'POA — Monthly financial forecas'!D47 -> 25888.095 | E48: ='POA — Monthly financial forecas'!E41+'POA — Monthly financial forecas'!E47 -> 28190.476 | F48: ='POA — Monthly financial forecas'!F41+'POA — Monthly financial forecas'!F47 -> 30492.857 | G48: ='POA — Monthly financial forecas'!G41+'POA — Monthly financial forecas'!G47 -> 32795.238 | H48: ='POA — Monthly financial forecas'!H41+'POA — Monthly financial forecas'!H47 -> 52564.286 | I48: ='POA — Monthly financial forecas'!I41+'POA — Monthly financial forecas'!I47 -> 57365.079 | ... AK48: ='POA — Monthly financial forecas'!AK41+'POA — Monthly financial forecas'!AK47 -> 277468.25
A49: EBITDA | B49: ='POA — Monthly financial forecas'!B38-'POA — Monthly financial forecas'!B48 -> -17769.542 | C49: ='POA — Monthly financial forecas'!C38-'POA — Monthly financial forecas'!C48 -> -16516.548 | D49: ='POA — Monthly financial forecas'!D38-'POA — Monthly financial forecas'!D48 -> -15221.97 | E49: ='POA — Monthly financial forecas'!E38-'POA — Monthly financial forecas'!E48 -> -13885.81 | F49: ='POA — Monthly financial forecas'!F38-'POA — Monthly financial forecas'!F48 -> -12508.065 | G49: ='POA — Monthly financial forecas'!G38-'POA — Monthly financial forecas'!G48 -> -11088.738 | H49: ='POA — Monthly financial forecas'!H38-'POA — Monthly financial forecas'!H48 -> -20320.401 | I49: ='POA — Monthly financial forecas'!I38-'POA — Monthly financial forecas'!I48 -> -14036.086 | ... AK49: ='POA — Monthly financial forecas'!AK38-'POA — Monthly financial forecas'!AK48 -> 600771.75
A50: Cash taxes | B50: =MAX('POA — Monthly financial forecas'!B49,0)*'Model inputs'!AM12 -> 0 | C50: =MAX('POA — Monthly financial forecas'!C49,0)*'Model inputs'!AM12 -> 0 | D50: =MAX('POA — Monthly financial forecas'!D49,0)*'Model inputs'!AM12 -> 0 | E50: =MAX('POA — Monthly financial forecas'!E49,0)*'Model inputs'!AM12 -> 0 | F50: =MAX('POA — Monthly financial forecas'!F49,0)*'Model inputs'!AM12 -> 0 | G50: =MAX('POA — Monthly financial forecas'!G49,0)*'Model inputs'!AM12 -> 0 | H50: =MAX('POA — Monthly financial forecas'!H49,0)*'Model inputs'!AM12 -> 0 | I50: =MAX('POA — Monthly financial forecas'!I49,0)*'Model inputs'!AM12 -> 0 | J50: =MAX('POA — Monthly financial forecas'!J49,0)*'Model inputs'!AM12 -> 0 | K50: =MAX('POA — Monthly financial forecas'!K49,0)*'Model inputs'!AM12 -> 0 | L50: =MAX('POA — Monthly financial forecas'!L49,0)*'Model inputs'!AM12 -> 0 | M50: =MAX('POA — Monthly financial forecas'!M49,0)*'Model inputs'!AM12 -> 0 | N50: =MAX('POA — Monthly financial forecas'!N49,0)*'Model inputs'!AM12 -> 0 | O50: =MAX('POA — Monthly financial forecas'!O49,0)*'Model inputs'!AM12 -> 0 | P50: =MAX('POA — Monthly financial forecas'!P49,0)*'Model inputs'!AM12 -> 0 | Q50: =MAX('POA — Monthly financial forecas'!Q49,0)*'Model inputs'!AM12 -> 0 | R50: =MAX('POA — Monthly financial forecas'!R49,0)*'Model inputs'!AM12 -> 0 | S50: =MAX('POA — Monthly financial forecas'!S49,0)*'Model inputs'!AM12 -> 0 | T50: =MAX('POA — Monthly financial forecas'!T49,0)*'Model inputs'!AM12 -> 0 | U50: =MAX('POA — Monthly financial forecas'!U49,0)*'Model inputs'!AM12 -> 0 | V50: =MAX('POA — Monthly financial forecas'!V49,0)*'Model inputs'!AM12 -> 0 | W50: =MAX('POA — Monthly financial forecas'!W49,0)*'Model inputs'!AM12 -> 0 | X50: =MAX('POA — Monthly financial forecas'!X49,0)*'Model inputs'!AM12 -> 0 | Y50: =MAX('POA — Monthly financial forecas'!Y49,0)*'Model inputs'!AM12 -> 0 | Z50: =MAX('POA — Monthly financial forecas'!Z49,0)*'Model inputs'!AM12 -> 0 | AA50: =MAX('POA — Monthly financial forecas'!AA49,0)*'Model inputs'!AM12 -> 0 | AB50: =MAX('POA — Monthly financial forecas'!AB49,0)*'Model inputs'!AM12 -> 0 | AC50: =MAX('POA — Monthly financial forecas'!AC49,0)*'Model inputs'!AM12 -> 0 | AD50: =MAX('POA — Monthly financial forecas'!AD49,0)*'Model inputs'!AM12 -> 0 | AE50: =MAX('POA — Monthly financial forecas'!AE49,0)*'Model inputs'!AM12 -> 0 | AF50: =MAX('POA — Monthly financial forecas'!AF49,0)*'Model inputs'!AM12 -> 0 | AG50: =MAX('POA — Monthly financial forecas'!AG49,0)*'Model inputs'!AM12 -> 0 | AH50: =MAX('POA — Monthly financial forecas'!AH49,0)*'Model inputs'!AM12 -> 0 | AI50: =MAX('POA — Monthly financial forecas'!AI49,0)*'Model inputs'!AM12 -> 0 | AJ50: =MAX('POA — Monthly financial forecas'!AJ49,0)*'Model inputs'!AM12 -> 0 | AK50: =MAX('POA — Monthly financial forecas'!AK49,0)*'Model inputs'!AM12 -> 0
A51: Capital expenditure | B51: =IF('Model inputs'!AM41="","",'Model inputs'!AM41) -> 0 | C51: =IF('Model inputs'!AM41="","",'Model inputs'!AM41) -> 0 | D51: =IF('Model inputs'!AM41="","",'Model inputs'!AM41) -> 0 | E51: =IF('Model inputs'!AM41="","",'Model inputs'!AM41) -> 0 | F51: =IF('Model inputs'!AM41="","",'Model inputs'!AM41) -> 0 | G51: =IF('Model inputs'!AM41="","",'Model inputs'!AM41) -> 0 | H51: =IF('Model inputs'!AM41="","",'Model inputs'!AM41) -> 0 | I51: =IF('Model inputs'!AM41="","",'Model inputs'!AM41) -> 0 | J51: =IF('Model inputs'!AM41="","",'Model inputs'!AM41) -> 0 | K51: =IF('Model inputs'!AM41="","",'Model inputs'!AM41) -> 0 | L51: =IF('Model inputs'!AM41="","",'Model inputs'!AM41) -> 0 | M51: =IF('Model inputs'!AM41="","",'Model inputs'!AM41) -> 0 | N51: =IF('Model inputs'!AM41="","",'Model inputs'!AM41) -> 0 | O51: =IF('Model inputs'!AM41="","",'Model inputs'!AM41) -> 0 | P51: =IF('Model inputs'!AM41="","",'Model inputs'!AM41) -> 0 | Q51: =IF('Model inputs'!AM41="","",'Model inputs'!AM41) -> 0 | R51: =IF('Model inputs'!AM41="","",'Model inputs'!AM41) -> 0 | S51: =IF('Model inputs'!AM41="","",'Model inputs'!AM41) -> 0 | T51: =IF('Model inputs'!AM41="","",'Model inputs'!AM41) -> 0 | U51: =IF('Model inputs'!AM41="","",'Model inputs'!AM41) -> 0 | V51: =IF('Model inputs'!AM41="","",'Model inputs'!AM41) -> 0 | W51: =IF('Model inputs'!AM41="","",'Model inputs'!AM41) -> 0 | X51: =IF('Model inputs'!AM41="","",'Model inputs'!AM41) -> 0 | Y51: =IF('Model inputs'!AM41="","",'Model inputs'!AM41) -> 0 | Z51: =IF('Model inputs'!AM41="","",'Model inputs'!AM41) -> 0 | AA51: =IF('Model inputs'!AM41="","",'Model inputs'!AM41) -> 0 | AB51: =IF('Model inputs'!AM41="","",'Model inputs'!AM41) -> 0 | AC51: =IF('Model inputs'!AM41="","",'Model inputs'!AM41) -> 0 | AD51: =IF('Model inputs'!AM41="","",'Model inputs'!AM41) -> 0 | AE51: =IF('Model inputs'!AM41="","",'Model inputs'!AM41) -> 0 | AF51: =IF('Model inputs'!AM41="","",'Model inputs'!AM41) -> 0 | AG51: =IF('Model inputs'!AM41="","",'Model inputs'!AM41) -> 0 | AH51: =IF('Model inputs'!AM41="","",'Model inputs'!AM41) -> 0 | AI51: =IF('Model inputs'!AM41="","",'Model inputs'!AM41) -> 0 | AJ51: =IF('Model inputs'!AM41="","",'Model inputs'!AM41) -> 0 | AK51: =IF('Model inputs'!AM41="","",'Model inputs'!AM41) -> 0
A52: Financing inflow | B52: =IF('Model inputs'!AM42="","",'Model inputs'!AM42) -> 0 | C52: =IF('Model inputs'!AM42="","",'Model inputs'!AM42) -> 0 | D52: =IF('Model inputs'!AM42="","",'Model inputs'!AM42) -> 0 | E52: =IF('Model inputs'!AM42="","",'Model inputs'!AM42) -> 0 | F52: =IF('Model inputs'!AM42="","",'Model inputs'!AM42) -> 0 | G52: =IF('Model inputs'!AM42="","",'Model inputs'!AM42) -> 0 | H52: =IF('Model inputs'!AM42="","",'Model inputs'!AM42) -> 0 | I52: =IF('Model inputs'!AM42="","",'Model inputs'!AM42) -> 0 | J52: =IF('Model inputs'!AM42="","",'Model inputs'!AM42) -> 0 | K52: =IF('Model inputs'!AM42="","",'Model inputs'!AM42) -> 0 | L52: =IF('Model inputs'!AM42="","",'Model inputs'!AM42) -> 0 | M52: =IF('Model inputs'!AM42="","",'Model inputs'!AM42) -> 0 | N52: =IF('Model inputs'!AM42="","",'Model inputs'!AM42) -> 0 | O52: =IF('Model inputs'!AM42="","",'Model inputs'!AM42) -> 0 | P52: =IF('Model inputs'!AM42="","",'Model inputs'!AM42) -> 0 | Q52: =IF('Model inputs'!AM42="","",'Model inputs'!AM42) -> 0 | R52: =IF('Model inputs'!AM42="","",'Model inputs'!AM42) -> 0 | S52: =IF('Model inputs'!AM42="","",'Model inputs'!AM42) -> 0 | T52: =IF('Model inputs'!AM42="","",'Model inputs'!AM42) -> 0 | U52: =IF('Model inputs'!AM42="","",'Model inputs'!AM42) -> 0 | V52: =IF('Model inputs'!AM42="","",'Model inputs'!AM42) -> 0 | W52: =IF('Model inputs'!AM42="","",'Model inputs'!AM42) -> 0 | X52: =IF('Model inputs'!AM42="","",'Model inputs'!AM42) -> 0 | Y52: =IF('Model inputs'!AM42="","",'Model inputs'!AM42) -> 0 | Z52: =IF('Model inputs'!AM42="","",'Model inputs'!AM42) -> 0 | AA52: =IF('Model inputs'!AM42="","",'Model inputs'!AM42) -> 0 | AB52: =IF('Model inputs'!AM42="","",'Model inputs'!AM42) -> 0 | AC52: =IF('Model inputs'!AM42="","",'Model inputs'!AM42) -> 0 | AD52: =IF('Model inputs'!AM42="","",'Model inputs'!AM42) -> 0 | AE52: =IF('Model inputs'!AM42="","",'Model inputs'!AM42) -> 0 | AF52: =IF('Model inputs'!AM42="","",'Model inputs'!AM42) -> 0 | AG52: =IF('Model inputs'!AM42="","",'Model inputs'!AM42) -> 0 | AH52: =IF('Model inputs'!AM42="","",'Model inputs'!AM42) -> 0 | AI52: =IF('Model inputs'!AM42="","",'Model inputs'!AM42) -> 0 | AJ52: =IF('Model inputs'!AM42="","",'Model inputs'!AM42) -> 0 | AK52: =IF('Model inputs'!AM42="","",'Model inputs'!AM42) -> 0
A53: Cash collections | B53: =IF('Model inputs'!B832=0,"",SUM('Model inputs'!B795,'Model inputs'!B796,'Model inputs'!B797,'Model inputs'!B798,'Model inputs'!B799,'Model inputs'!B800,'Model inputs'!B801,'Model inputs'!B802,'Model inputs'!B803,'Model inputs'!B804,'Model inputs'!B805,'Model inputs'!B806,'Model inputs'!B807,'Model inputs'!B808,'Model inputs'!B809,'Model inputs'!B810,'Model inputs'!B811,'Model inputs'!B812,'Model inputs'!B813,'Model inputs'!B814,'Model inputs'!B815,'Model inputs'!B816,'Model inputs'!B817,'Model inputs'!B818,'Model inputs'!B819,'Model inputs'!B820,'Model inputs'!B821,'Model inputs'!B822,'Model inputs'!B823,'Model inputs'!B824,'Model inputs'!B825,'Model inputs'!B826,'Model inputs'!B827,'Model inputs'!B828,'Model inputs'!B829,'Model inputs'!B830,'Model inputs'!B831)) -> 3520.8333 | C53: =IF('Model inputs'!B870=0,"",SUM('Model inputs'!B833,'Model inputs'!B834,'Model inputs'!B835,'Model inputs'!B836,'Model inputs'!B837,'Model inputs'!B838,'Model inputs'!B839,'Model inputs'!B840,'Model inputs'!B841,'Model inputs'!B842,'Model inputs'!B843,'Model inputs'!B844,'Model inputs'!B845,'Model inputs'!B846,'Model inputs'!B847,'Model inputs'!B848,'Model inputs'!B849,'Model inputs'!B850,'Model inputs'!B851,'Model inputs'!B852,'Model inputs'!B853,'Model inputs'!B854,'Model inputs'!B855,'Model inputs'!B856,'Model inputs'!B857,'Model inputs'!B858,'Model inputs'!B859,'Model inputs'!B860,'Model inputs'!B861,'Model inputs'!B862,'Model inputs'!B863,'Model inputs'!B864,'Model inputs'!B865,'Model inputs'!B866,'Model inputs'!B867,'Model inputs'!B868,'Model inputs'!B869)) -> 7083.3333 | D53: =IF('Model inputs'!B908=0,"",SUM('Model inputs'!B871,'Model inputs'!B872,'Model inputs'!B873,'Model inputs'!B874,'Model inputs'!B875,'Model inputs'!B876,'Model inputs'!B877,'Model inputs'!B878,'Model inputs'!B879,'Model inputs'!B880,'Model inputs'!B881,'Model inputs'!B882,'Model inputs'!B883,'Model inputs'!B884,'Model inputs'!B885,'Model inputs'!B886,'Model inputs'!B887,'Model inputs'!B888,'Model inputs'!B889,'Model inputs'!B890,'Model inputs'!B891,'Model inputs'!B892,'Model inputs'!B893,'Model inputs'!B894,'Model inputs'!B895,'Model inputs'!B896,'Model inputs'!B897,'Model inputs'!B898,'Model inputs'!B899,'Model inputs'!B900,'Model inputs'!B901,'Model inputs'!B902,'Model inputs'!B903,'Model inputs'!B904,'Model inputs'!B905,'Model inputs'!B906,'Model inputs'!B907)) -> 10687.5 | E53: =IF('Model inputs'!B946=0,"",SUM('Model inputs'!B909,'Model inputs'!B910,'Model inputs'!B911,'Model inputs'!B912,'Model inputs'!B913,'Model inputs'!B914,'Model inputs'!B915,'Model inputs'!B916,'Model inputs'!B917,'Model inputs'!B918,'Model inputs'!B919,'Model inputs'!B920,'Model inputs'!B921,'Model inputs'!B922,'Model inputs'!B923,'Model inputs'!B924,'Model inputs'!B925,'Model inputs'!B926,'Model inputs'!B927,'Model inputs'!B928,'Model inputs'!B929,'Model inputs'!B930,'Model inputs'!B931,'Model inputs'!B932,'Model inputs'!B933,'Model inputs'!B934,'Model inputs'!B935,'Model inputs'!B936,'Model inputs'!B937,'Model inputs'!B938,'Model inputs'!B939,'Model inputs'!B940,'Model inputs'!B941,'Model inputs'!B942,'Model inputs'!B943,'Model inputs'!B944,'Model inputs'!B945)) -> 14333.333 | F53: =IF('Model inputs'!B984=0,"",SUM('Model inputs'!B947,'Model inputs'!B948,'Model inputs'!B949,'Model inputs'!B950,'Model inputs'!B951,'Model inputs'!B952,'Model inputs'!B953,'Model inputs'!B954,'Model inputs'!B955,'Model inputs'!B956,'Model inputs'!B957,'Model inputs'!B958,'Model inputs'!B959,'Model inputs'!B960,'Model inputs'!B961,'Model inputs'!B962,'Model inputs'!B963,'Model inputs'!B964,'Model inputs'!B965,'Model inputs'!B966,'Model inputs'!B967,'Model inputs'!B968,'Model inputs'!B969,'Model inputs'!B970,'Model inputs'!B971,'Model inputs'!B972,'Model inputs'!B973,'Model inputs'!B974,'Model inputs'!B975,'Model inputs'!B976,'Model inputs'!B977,'Model inputs'!B978,'Model inputs'!B979,'Model inputs'!B980,'Model inputs'!B981,'Model inputs'!B982,'Model inputs'!B983)) -> 18020.833 | G53: =IF('Model inputs'!B1022=0,"",SUM('Model inputs'!B985,'Model inputs'!B986,'Model inputs'!B987,'Model inputs'!B988,'Model inputs'!B989,'Model inputs'!B990,'Model inputs'!B991,'Model inputs'!B992,'Model inputs'!B993,'Model inputs'!B994,'Model inputs'!B995,'Model inputs'!B996,'Model inputs'!B997,'Model inputs'!B998,'Model inputs'!B999,'Model inputs'!B1000,'Model inputs'!B1001,'Model inputs'!B1002,'Model inputs'!B1003,'Model inputs'!B1004,'Model inputs'!B1005,'Model inputs'!B1006,'Model inputs'!B1007,'Model inputs'!B1008,'Model inputs'!B1009,'Model inputs'!B1010,'Model inputs'!B1011,'Model inputs'!B1012,'Model inputs'!B1013,'Model inputs'!B1014,'Model inputs'!B1015,'Model inputs'!B1016,'Model inputs'!B1017,'Model inputs'!B1018,'Model inputs'!B1019,'Model inputs'!B1020,'Model inputs'!B1021)) -> 21750 | H53: =IF('Model inputs'!B1060=0,"",SUM('Model inputs'!B1023,'Model inputs'!B1024,'Model inputs'!B1025,'Model inputs'!B1026,'Model inputs'!B1027,'Model inputs'!B1028,'Model inputs'!B1029,'Model inputs'!B1030,'Model inputs'!B1031,'Model inputs'!B1032,'Model inputs'!B1033,'Model inputs'!B1034,'Model inputs'!B1035,'Model inputs'!B1036,'Model inputs'!B1037,'Model inputs'!B1038,'Model inputs'!B1039,'Model inputs'!B1040,'Model inputs'!B1041,'Model inputs'!B1042,'Model inputs'!B1043,'Model inputs'!B1044,'Model inputs'!B1045,'Model inputs'!B1046,'Model inputs'!B1047,'Model inputs'!B1048,'Model inputs'!B1049,'Model inputs'!B1050,'Model inputs'!B1051,'Model inputs'!B1052,'Model inputs'!B1053,'Model inputs'!B1054,'Model inputs'!B1055,'Model inputs'!B1056,'Model inputs'!B1057,'Model inputs'!B1058,'Model inputs'!B1059)) -> 32308.502 | I53: =IF('Model inputs'!B1098=0,"",SUM('Model inputs'!B1061,'Model inputs'!B1062,'Model inputs'!B1063,'Model inputs'!B1064,'Model inputs'!B1065,'Model inputs'!B1066,'Model inputs'!B1067,'Model inputs'!B1068,'Model inputs'!B1069,'Model inputs'!B1070,'Model inputs'!B1071,'Model inputs'!B1072,'Model inputs'!B1073,'Model inputs'!B1074,'Model inputs'!B1075,'Model inputs'!B1076,'Model inputs'!B1077,'Model inputs'!B1078,'Model inputs'!B1079,'Model inputs'!B1080,'Model inputs'!B1081,'Model inputs'!B1082,'Model inputs'!B1083,'Model inputs'!B1084,'Model inputs'!B1085,'Model inputs'!B1086,'Model inputs'!B1087,'Model inputs'!B1088,'Model inputs'!B1089,'Model inputs'!B1090,'Model inputs'!B1091,'Model inputs'!B1092,'Model inputs'!B1093,'Model inputs'!B1094,'Model inputs'!B1095,'Model inputs'!B1096,'Model inputs'!B1097)) -> 43415.825 | J53: =IF('Model inputs'!B1136=0,"",SUM('Model inputs'!B1099,'Model inputs'!B1100,'Model inputs'!B1101,'Model inputs'!B1102,'Model inputs'!B1103,'Model inputs'!B1104,'Model inputs'!B1105,'Model inputs'!B1106,'Model inputs'!B1107,'Model inputs'!B1108,'Model inputs'!B1109,'Model inputs'!B1110,'Model inputs'!B1111,'Model inputs'!B1112,'Model inputs'!B1113,'Model inputs'!B1114,'Model inputs'!B1115,'Model inputs'!B1116,'Model inputs'!B1117,'Model inputs'!B1118,'Model inputs'!B1119,'Model inputs'!B1120,'Model inputs'!B1121,'Model inputs'!B1122,'Model inputs'!B1123,'Model inputs'!B1124,'Model inputs'!B1125,'Model inputs'!B1126,'Model inputs'!B1127,'Model inputs'!B1128,'Model inputs'!B1129,'Model inputs'!B1130,'Model inputs'!B1131,'Model inputs'!B1132,'Model inputs'!B1133,'Model inputs'!B1134,'Model inputs'!B1135)) -> 55071.97 | K53: =IF('Model inputs'!B1174=0,"",SUM('Model inputs'!B1137,'Model inputs'!B1138,'Model inputs'!B1139,'Model inputs'!B1140,'Model inputs'!B1141,'Model inputs'!B1142,'Model inputs'!B1143,'Model inputs'!B1144,'Model inputs'!B1145,'Model inputs'!B1146,'Model inputs'!B1147,'Model inputs'!B1148,'Model inputs'!B1149,'Model inputs'!B1150,'Model inputs'!B1151,'Model inputs'!B1152,'Model inputs'!B1153,'Model inputs'!B1154,'Model inputs'!B1155,'Model inputs'!B1156,'Model inputs'!B1157,'Model inputs'!B1158,'Model inputs'!B1159,'Model inputs'!B1160,'Model inputs'!B1161,'Model inputs'!B1162,'Model inputs'!B1163,'Model inputs'!B1164,'Model inputs'!B1165,'Model inputs'!B1166,'Model inputs'!B1167,'Model inputs'!B1168,'Model inputs'!B1169,'Model inputs'!B1170,'Model inputs'!B1171,'Model inputs'!B1172,'Model inputs'!B1173)) -> 67276.936 | L53: =IF('Model inputs'!B1212=0,"",SUM('Model inputs'!B1175,'Model inputs'!B1176,'Model inputs'!B1177,'Model inputs'!B1178,'Model inputs'!B1179,'Model inputs'!B1180,'Model inputs'!B1181,'Model inputs'!B1182,'Model inputs'!B1183,'Model inputs'!B1184,'Model inputs'!B1185,'Model inputs'!B1186,'Model inputs'!B1187,'Model inputs'!B1188,'Model inputs'!B1189,'Model inputs'!B1190,'Model inputs'!B1191,'Model inputs'!B1192,'Model inputs'!B1193,'Model inputs'!B1194,'Model inputs'!B1195,'Model inputs'!B1196,'Model inputs'!B1197,'Model inputs'!B1198,'Model inputs'!B1199,'Model inputs'!B1200,'Model inputs'!B1201,'Model inputs'!B1202,'Model inputs'!B1203,'Model inputs'!B1204,'Model inputs'!B1205,'Model inputs'!B1206,'Model inputs'!B1207,'Model inputs'!B1208,'Model inputs'!B1209,'Model inputs'!B1210,'Model inputs'!B1211)) -> 80030.724 | M53: =IF('Model inputs'!B1250=0,"",SUM('Model inputs'!B1213,'Model inputs'!B1214,'Model inputs'!B1215,'Model inputs'!B1216,'Model inputs'!B1217,'Model inputs'!B1218,'Model inputs'!B1219,'Model inputs'!B1220,'Model inputs'!B1221,'Model inputs'!B1222,'Model inputs'!B1223,'Model inputs'!B1224,'Model inputs'!B1225,'Model inputs'!B1226,'Model inputs'!B1227,'Model inputs'!B1228,'Model inputs'!B1229,'Model inputs'!B1230,'Model inputs'!B1231,'Model inputs'!B1232,'Model inputs'!B1233,'Model inputs'!B1234,'Model inputs'!B1235,'Model inputs'!B1236,'Model inputs'!B1237,'Model inputs'!B1238,'Model inputs'!B1239,'Model inputs'!B1240,'Model inputs'!B1241,'Model inputs'!B1242,'Model inputs'!B1243,'Model inputs'!B1244,'Model inputs'!B1245,'Model inputs'!B1246,'Model inputs'!B1247,'Model inputs'!B1248,'Model inputs'!B1249)) -> 93333.333 | N53: =IF('Model inputs'!B1288=0,"",SUM('Model inputs'!B1251,'Model inputs'!B1252,'Model inputs'!B1253,'Model inputs'!B1254,'Model inputs'!B1255,'Model inputs'!B1256,'Model inputs'!B1257,'Model inputs'!B1258,'Model inputs'!B1259,'Model inputs'!B1260,'Model inputs'!B1261,'Model inputs'!B1262,'Model inputs'!B1263,'Model inputs'!B1264,'Model inputs'!B1265,'Model inputs'!B1266,'Model inputs'!B1267,'Model inputs'!B1268,'Model inputs'!B1269,'Model inputs'!B1270,'Model inputs'!B1271,'Model inputs'!B1272,'Model inputs'!B1273,'Model inputs'!B1274,'Model inputs'!B1275,'Model inputs'!B1276,'Model inputs'!B1277,'Model inputs'!B1278,'Model inputs'!B1279,'Model inputs'!B1280,'Model inputs'!B1281,'Model inputs'!B1282,'Model inputs'!B1283,'Model inputs'!B1284,'Model inputs'!B1285,'Model inputs'!B1286,'Model inputs'!B1287)) -> 122598.91 | O53: =IF('Model inputs'!B1326=0,"",SUM('Model inputs'!B1289,'Model inputs'!B1290,'Model inputs'!B1291,'Model inputs'!B1292,'Model inputs'!B1293,'Model inputs'!B1294,'Model inputs'!B1295,'Model inputs'!B1296,'Model inputs'!B1297,'Model inputs'!B1298,'Model inputs'!B1299,'Model inputs'!B1300,'Model inputs'!B1301,'Model inputs'!B1302,'Model inputs'!B1303,'Model inputs'!B1304,'Model inputs'!B1305,'Model inputs'!B1306,'Model inputs'!B1307,'Model inputs'!B1308,'Model inputs'!B1309,'Model inputs'!B1310,'Model inputs'!B1311,'Model inputs'!B1312,'Model inputs'!B1313,'Model inputs'!B1314,'Model inputs'!B1315,'Model inputs'!B1316,'Model inputs'!B1317,'Model inputs'!B1318,'Model inputs'!B1319,'Model inputs'!B1320,'Model inputs'!B1321,'Model inputs'!B1322,'Model inputs'!B1323,'Model inputs'!B1324,'Model inputs'!B1325)) -> 152936.03 | P53: =IF('Model inputs'!B1364=0,"",SUM('Model inputs'!B1327,'Model inputs'!B1328,'Model inputs'!B1329,'Model inputs'!B1330,'Model inputs'!B1331,'Model inputs'!B1332,'Model inputs'!B1333,'Model inputs'!B1334,'Model inputs'!B1335,'Model inputs'!B1336,'Model inputs'!B1337,'Model inputs'!B1338,'Model inputs'!B1339,'Model inputs'!B1340,'Model inputs'!B1341,'Model inputs'!B1342,'Model inputs'!B1343,'Model inputs'!B1344,'Model inputs'!B1345,'Model inputs'!B1346,'Model inputs'!B1347,'Model inputs'!B1348,'Model inputs'!B1349,'Model inputs'!B1350,'Model inputs'!B1351,'Model inputs'!B1352,'Model inputs'!B1353,'Model inputs'!B1354,'Model inputs'!B1355,'Model inputs'!B1356,'Model inputs'!B1357,'Model inputs'!B1358,'Model inputs'!B1359,'Model inputs'!B1360,'Model inputs'!B1361,'Model inputs'!B1362,'Model inputs'!B1363)) -> 184344.7 | Q53: =IF('Model inputs'!B1402=0,"",SUM('Model inputs'!B1365,'Model inputs'!B1366,'Model inputs'!B1367,'Model inputs'!B1368,'Model inputs'!B1369,'Model inputs'!B1370,'Model inputs'!B1371,'Model inputs'!B1372,'Model inputs'!B1373,'Model inputs'!B1374,'Model inputs'!B1375,'Model inputs'!B1376,'Model inputs'!B1377,'Model inputs'!B1378,'Model inputs'!B1379,'Model inputs'!B1380,'Model inputs'!B1381,'Model inputs'!B1382,'Model inputs'!B1383,'Model inputs'!B1384,'Model inputs'!B1385,'Model inputs'!B1386,'Model inputs'!B1387,'Model inputs'!B1388,'Model inputs'!B1389,'Model inputs'!B1390,'Model inputs'!B1391,'Model inputs'!B1392,'Model inputs'!B1393,'Model inputs'!B1394,'Model inputs'!B1395,'Model inputs'!B1396,'Model inputs'!B1397,'Model inputs'!B1398,'Model inputs'!B1399,'Model inputs'!B1400,'Model inputs'!B1401)) -> 216824.92 | R53: =IF('Model inputs'!B1440=0,"",SUM('Model inputs'!B1403,'Model inputs'!B1404,'Model inputs'!B1405,'Model inputs'!B1406,'Model inputs'!B1407,'Model inputs'!B1408,'Model inputs'!B1409,'Model inputs'!B1410,'Model inputs'!B1411,'Model inputs'!B1412,'Model inputs'!B1413,'Model inputs'!B1414,'Model inputs'!B1415,'Model inputs'!B1416,'Model inputs'!B1417,'Model inputs'!B1418,'Model inputs'!B1419,'Model inputs'!B1420,'Model inputs'!B1421,'Model inputs'!B1422,'Model inputs'!B1423,'Model inputs'!B1424,'Model inputs'!B1425,'Model inputs'!B1426,'Model inputs'!B1427,'Model inputs'!B1428,'Model inputs'!B1429,'Model inputs'!B1430,'Model inputs'!B1431,'Model inputs'!B1432,'Model inputs'!B1433,'Model inputs'!B1434,'Model inputs'!B1435,'Model inputs'!B1436,'Model inputs'!B1437,'Model inputs'!B1438,'Model inputs'!B1439)) -> 250376.68 | S53: =IF('Model inputs'!B1478=0,"",SUM('Model inputs'!B1441,'Model inputs'!B1442,'Model inputs'!B1443,'Model inputs'!B1444,'Model inputs'!B1445,'Model inputs'!B1446,'Model inputs'!B1447,'Model inputs'!B1448,'Model inputs'!B1449,'Model inputs'!B1450,'Model inputs'!B1451,'Model inputs'!B1452,'Model inputs'!B1453,'Model inputs'!B1454,'Model inputs'!B1455,'Model inputs'!B1456,'Model inputs'!B1457,'Model inputs'!B1458,'Model inputs'!B1459,'Model inputs'!B1460,'Model inputs'!B1461,'Model inputs'!B1462,'Model inputs'!B1463,'Model inputs'!B1464,'Model inputs'!B1465,'Model inputs'!B1466,'Model inputs'!B1467,'Model inputs'!B1468,'Model inputs'!B1469,'Model inputs'!B1470,'Model inputs'!B1471,'Model inputs'!B1472,'Model inputs'!B1473,'Model inputs'!B1474,'Model inputs'!B1475,'Model inputs'!B1476,'Model inputs'!B1477)) -> 285000 | T53: =IF('Model inputs'!B1516=0,"",SUM('Model inputs'!B1479,'Model inputs'!B1480,'Model inputs'!B1481,'Model inputs'!B1482,'Model inputs'!B1483,'Model inputs'!B1484,'Model inputs'!B1485,'Model inputs'!B1486,'Model inputs'!B1487,'Model inputs'!B1488,'Model inputs'!B1489,'Model inputs'!B1490,'Model inputs'!B1491,'Model inputs'!B1492,'Model inputs'!B1493,'Model inputs'!B1494,'Model inputs'!B1495,'Model inputs'!B1496,'Model inputs'!B1497,'Model inputs'!B1498,'Model inputs'!B1499,'Model inputs'!B1500,'Model inputs'!B1501,'Model inputs'!B1502,'Model inputs'!B1503,'Model inputs'!B1504,'Model inputs'!B1505,'Model inputs'!B1506,'Model inputs'!B1507,'Model inputs'!B1508,'Model inputs'!B1509,'Model inputs'!B1510,'Model inputs'!B1511,'Model inputs'!B1512,'Model inputs'!B1513,'Model inputs'!B1514,'Model inputs'!B1515)) -> 319444.44 | U53: =IF('Model inputs'!B1554=0,"",SUM('Model inputs'!B1517,'Model inputs'!B1518,'Model inputs'!B1519,'Model inputs'!B1520,'Model inputs'!B1521,'Model inputs'!B1522,'Model inputs'!B1523,'Model inputs'!B1524,'Model inputs'!B1525,'Model inputs'!B1526,'Model inputs'!B1527,'Model inputs'!B1528,'Model inputs'!B1529,'Model inputs'!B1530,'Model inputs'!B1531,'Model inputs'!B1532,'Model inputs'!B1533,'Model inputs'!B1534,'Model inputs'!B1535,'Model inputs'!B1536,'Model inputs'!B1537,'Model inputs'!B1538,'Model inputs'!B1539,'Model inputs'!B1540,'Model inputs'!B1541,'Model inputs'!B1542,'Model inputs'!B1543,'Model inputs'!B1544,'Model inputs'!B1545,'Model inputs'!B1546,'Model inputs'!B1547,'Model inputs'!B1548,'Model inputs'!B1549,'Model inputs'!B1550,'Model inputs'!B1551,'Model inputs'!B1552,'Model inputs'!B1553)) -> 354444.44 | V53: =IF('Model inputs'!B1592=0,"",SUM('Model inputs'!B1555,'Model inputs'!B1556,'Model inputs'!B1557,'Model inputs'!B1558,'Model inputs'!B1559,'Model inputs'!B1560,'Model inputs'!B1561,'Model inputs'!B1562,'Model inputs'!B1563,'Model inputs'!B1564,'Model inputs'!B1565,'Model inputs'!B1566,'Model inputs'!B1567,'Model inputs'!B1568,'Model inputs'!B1569,'Model inputs'!B1570,'Model inputs'!B1571,'Model inputs'!B1572,'Model inputs'!B1573,'Model inputs'!B1574,'Model inputs'!B1575,'Model inputs'!B1576,'Model inputs'!B1577,'Model inputs'!B1578,'Model inputs'!B1579,'Model inputs'!B1580,'Model inputs'!B1581,'Model inputs'!B1582,'Model inputs'!B1583,'Model inputs'!B1584,'Model inputs'!B1585,'Model inputs'!B1586,'Model inputs'!B1587,'Model inputs'!B1588,'Model inputs'!B1589,'Model inputs'!B1590,'Model inputs'!B1591)) -> 390000 | W53: =IF('Model inputs'!B1630=0,"",SUM('Model inputs'!B1593,'Model inputs'!B1594,'Model inputs'!B1595,'Model inputs'!B1596,'Model inputs'!B1597,'Model inputs'!B1598,'Model inputs'!B1599,'Model inputs'!B1600,'Model inputs'!B1601,'Model inputs'!B1602,'Model inputs'!B1603,'Model inputs'!B1604,'Model inputs'!B1605,'Model inputs'!B1606,'Model inputs'!B1607,'Model inputs'!B1608,'Model inputs'!B1609,'Model inputs'!B1610,'Model inputs'!B1611,'Model inputs'!B1612,'Model inputs'!B1613,'Model inputs'!B1614,'Model inputs'!B1615,'Model inputs'!B1616,'Model inputs'!B1617,'Model inputs'!B1618,'Model inputs'!B1619,'Model inputs'!B1620,'Model inputs'!B1621,'Model inputs'!B1622,'Model inputs'!B1623,'Model inputs'!B1624,'Model inputs'!B1625,'Model inputs'!B1626,'Model inputs'!B1627,'Model inputs'!B1628,'Model inputs'!B1629)) -> 426111.11 | X53: =IF('Model inputs'!B1668=0,"",SUM('Model inputs'!B1631,'Model inputs'!B1632,'Model inputs'!B1633,'Model inputs'!B1634,'Model inputs'!B1635,'Model inputs'!B1636,'Model inputs'!B1637,'Model inputs'!B1638,'Model inputs'!B1639,'Model inputs'!B1640,'Model inputs'!B1641,'Model inputs'!B1642,'Model inputs'!B1643,'Model inputs'!B1644,'Model inputs'!B1645,'Model inputs'!B1646,'Model inputs'!B1647,'Model inputs'!B1648,'Model inputs'!B1649,'Model inputs'!B1650,'Model inputs'!B1651,'Model inputs'!B1652,'Model inputs'!B1653,'Model inputs'!B1654,'Model inputs'!B1655,'Model inputs'!B1656,'Model inputs'!B1657,'Model inputs'!B1658,'Model inputs'!B1659,'Model inputs'!B1660,'Model inputs'!B1661,'Model inputs'!B1662,'Model inputs'!B1663,'Model inputs'!B1664,'Model inputs'!B1665,'Model inputs'!B1666,'Model inputs'!B1667)) -> 462777.78 | Y53: =IF('Model inputs'!B1706=0,"",SUM('Model inputs'!B1669,'Model inputs'!B1670,'Model inputs'!B1671,'Model inputs'!B1672,'Model inputs'!B1673,'Model inputs'!B1674,'Model inputs'!B1675,'Model inputs'!B1676,'Model inputs'!B1677,'Model inputs'!B1678,'Model inputs'!B1679,'Model inputs'!B1680,'Model inputs'!B1681,'Model inputs'!B1682,'Model inputs'!B1683,'Model inputs'!B1684,'Model inputs'!B1685,'Model inputs'!B1686,'Model inputs'!B1687,'Model inputs'!B1688,'Model inputs'!B1689,'Model inputs'!B1690,'Model inputs'!B1691,'Model inputs'!B1692,'Model inputs'!B1693,'Model inputs'!B1694,'Model inputs'!B1695,'Model inputs'!B1696,'Model inputs'!B1697,'Model inputs'!B1698,'Model inputs'!B1699,'Model inputs'!B1700,'Model inputs'!B1701,'Model inputs'!B1702,'Model inputs'!B1703,'Model inputs'!B1704,'Model inputs'!B1705)) -> 500000 | Z53: =IF('Model inputs'!B1744=0,"",SUM('Model inputs'!B1707,'Model inputs'!B1708,'Model inputs'!B1709,'Model inputs'!B1710,'Model inputs'!B1711,'Model inputs'!B1712,'Model inputs'!B1713,'Model inputs'!B1714,'Model inputs'!B1715,'Model inputs'!B1716,'Model inputs'!B1717,'Model inputs'!B1718,'Model inputs'!B1719,'Model inputs'!B1720,'Model inputs'!B1721,'Model inputs'!B1722,'Model inputs'!B1723,'Model inputs'!B1724,'Model inputs'!B1725,'Model inputs'!B1726,'Model inputs'!B1727,'Model inputs'!B1728,'Model inputs'!B1729,'Model inputs'!B1730,'Model inputs'!B1731,'Model inputs'!B1732,'Model inputs'!B1733,'Model inputs'!B1734,'Model inputs'!B1735,'Model inputs'!B1736,'Model inputs'!B1737,'Model inputs'!B1738,'Model inputs'!B1739,'Model inputs'!B1740,'Model inputs'!B1741,'Model inputs'!B1742,'Model inputs'!B1743)) -> 533576.39 | AA53: =IF('Model inputs'!B1782=0,"",SUM('Model inputs'!B1745,'Model inputs'!B1746,'Model inputs'!B1747,'Model inputs'!B1748,'Model inputs'!B1749,'Model inputs'!B1750,'Model inputs'!B1751,'Model inputs'!B1752,'Model inputs'!B1753,'Model inputs'!B1754,'Model inputs'!B1755,'Model inputs'!B1756,'Model inputs'!B1757,'Model inputs'!B1758,'Model inputs'!B1759,'Model inputs'!B1760,'Model inputs'!B1761,'Model inputs'!B1762,'Model inputs'!B1763,'Model inputs'!B1764,'Model inputs'!B1765,'Model inputs'!B1766,'Model inputs'!B1767,'Model inputs'!B1768,'Model inputs'!B1769,'Model inputs'!B1770,'Model inputs'!B1771,'Model inputs'!B1772,'Model inputs'!B1773,'Model inputs'!B1774,'Model inputs'!B1775,'Model inputs'!B1776,'Model inputs'!B1777,'Model inputs'!B1778,'Model inputs'!B1779,'Model inputs'!B1780,'Model inputs'!B1781)) -> 567638.89 | AB53: =IF('Model inputs'!B1820=0,"",SUM('Model inputs'!B1783,'Model inputs'!B1784,'Model inputs'!B1785,'Model inputs'!B1786,'Model inputs'!B1787,'Model inputs'!B1788,'Model inputs'!B1789,'Model inputs'!B1790,'Model inputs'!B1791,'Model inputs'!B1792,'Model inputs'!B1793,'Model inputs'!B1794,'Model inputs'!B1795,'Model inputs'!B1796,'Model inputs'!B1797,'Model inputs'!B1798,'Model inputs'!B1799,'Model inputs'!B1800,'Model inputs'!B1801,'Model inputs'!B1802,'Model inputs'!B1803,'Model inputs'!B1804,'Model inputs'!B1805,'Model inputs'!B1806,'Model inputs'!B1807,'Model inputs'!B1808,'Model inputs'!B1809,'Model inputs'!B1810,'Model inputs'!B1811,'Model inputs'!B1812,'Model inputs'!B1813,'Model inputs'!B1814,'Model inputs'!B1815,'Model inputs'!B1816,'Model inputs'!B1817,'Model inputs'!B1818,'Model inputs'!B1819)) -> 602187.5 | AC53: =IF('Model inputs'!B1858=0,"",SUM('Model inputs'!B1821,'Model inputs'!B1822,'Model inputs'!B1823,'Model inputs'!B1824,'Model inputs'!B1825,'Model inputs'!B1826,'Model inputs'!B1827,'Model inputs'!B1828,'Model inputs'!B1829,'Model inputs'!B1830,'Model inputs'!B1831,'Model inputs'!B1832,'Model inputs'!B1833,'Model inputs'!B1834,'Model inputs'!B1835,'Model inputs'!B1836,'Model inputs'!B1837,'Model inputs'!B1838,'Model inputs'!B1839,'Model inputs'!B1840,'Model inputs'!B1841,'Model inputs'!B1842,'Model inputs'!B1843,'Model inputs'!B1844,'Model inputs'!B1845,'Model inputs'!B1846,'Model inputs'!B1847,'Model inputs'!B1848,'Model inputs'!B1849,'Model inputs'!B1850,'Model inputs'!B1851,'Model inputs'!B1852,'Model inputs'!B1853,'Model inputs'!B1854,'Model inputs'!B1855,'Model inputs'!B1856,'Model inputs'!B1857)) -> 637222.22 | AD53: =IF('Model inputs'!B1896=0,"",SUM('Model inputs'!B1859,'Model inputs'!B1860,'Model inputs'!B1861,'Model inputs'!B1862,'Model inputs'!B1863,'Model inputs'!B1864,'Model inputs'!B1865,'Model inputs'!B1866,'Model inputs'!B1867,'Model inputs'!B1868,'Model inputs'!B1869,'Model inputs'!B1870,'Model inputs'!B1871,'Model inputs'!B1872,'Model inputs'!B1873,'Model inputs'!B1874,'Model inputs'!B1875,'Model inputs'!B1876,'Model inputs'!B1877,'Model inputs'!B1878,'Model inputs'!B1879,'Model inputs'!B1880,'Model inputs'!B1881,'Model inputs'!B1882,'Model inputs'!B1883,'Model inputs'!B1884,'Model inputs'!B1885,'Model inputs'!B1886,'Model inputs'!B1887,'Model inputs'!B1888,'Model inputs'!B1889,'Model inputs'!B1890,'Model inputs'!B1891,'Model inputs'!B1892,'Model inputs'!B1893,'Model inputs'!B1894,'Model inputs'!B1895)) -> 672743.06 | AE53: =IF('Model inputs'!B1934=0,"",SUM('Model inputs'!B1897,'Model inputs'!B1898,'Model inputs'!B1899,'Model inputs'!B1900,'Model inputs'!B1901,'Model inputs'!B1902,'Model inputs'!B1903,'Model inputs'!B1904,'Model inputs'!B1905,'Model inputs'!B1906,'Model inputs'!B1907,'Model inputs'!B1908,'Model inputs'!B1909,'Model inputs'!B1910,'Model inputs'!B1911,'Model inputs'!B1912,'Model inputs'!B1913,'Model inputs'!B1914,'Model inputs'!B1915,'Model inputs'!B1916,'Model inputs'!B1917,'Model inputs'!B1918,'Model inputs'!B1919,'Model inputs'!B1920,'Model inputs'!B1921,'Model inputs'!B1922,'Model inputs'!B1923,'Model inputs'!B1924,'Model inputs'!B1925,'Model inputs'!B1926,'Model inputs'!B1927,'Model inputs'!B1928,'Model inputs'!B1929,'Model inputs'!B1930,'Model inputs'!B1931,'Model inputs'!B1932,'Model inputs'!B1933)) -> 708750 | AF53: =IF('Model inputs'!B1972=0,"",SUM('Model inputs'!B1935,'Model inputs'!B1936,'Model inputs'!B1937,'Model inputs'!B1938,'Model inputs'!B1939,'Model inputs'!B1940,'Model inputs'!B1941,'Model inputs'!B1942,'Model inputs'!B1943,'Model inputs'!B1944,'Model inputs'!B1945,'Model inputs'!B1946,'Model inputs'!B1947,'Model inputs'!B1948,'Model inputs'!B1949,'Model inputs'!B1950,'Model inputs'!B1951,'Model inputs'!B1952,'Model inputs'!B1953,'Model inputs'!B1954,'Model inputs'!B1955,'Model inputs'!B1956,'Model inputs'!B1957,'Model inputs'!B1958,'Model inputs'!B1959,'Model inputs'!B1960,'Model inputs'!B1961,'Model inputs'!B1962,'Model inputs'!B1963,'Model inputs'!B1964,'Model inputs'!B1965,'Model inputs'!B1966,'Model inputs'!B1967,'Model inputs'!B1968,'Model inputs'!B1969,'Model inputs'!B1970,'Model inputs'!B1971)) -> 736423.61 | AG53: =IF('Model inputs'!B2010=0,"",SUM('Model inputs'!B1973,'Model inputs'!B1974,'Model inputs'!B1975,'Model inputs'!B1976,'Model inputs'!B1977,'Model inputs'!B1978,'Model inputs'!B1979,'Model inputs'!B1980,'Model inputs'!B1981,'Model inputs'!B1982,'Model inputs'!B1983,'Model inputs'!B1984,'Model inputs'!B1985,'Model inputs'!B1986,'Model inputs'!B1987,'Model inputs'!B1988,'Model inputs'!B1989,'Model inputs'!B1990,'Model inputs'!B1991,'Model inputs'!B1992,'Model inputs'!B1993,'Model inputs'!B1994,'Model inputs'!B1995,'Model inputs'!B1996,'Model inputs'!B1997,'Model inputs'!B1998,'Model inputs'!B1999,'Model inputs'!B2000,'Model inputs'!B2001,'Model inputs'!B2002,'Model inputs'!B2003,'Model inputs'!B2004,'Model inputs'!B2005,'Model inputs'!B2006,'Model inputs'!B2007,'Model inputs'!B2008,'Model inputs'!B2009)) -> 764444.44 | AH53: =IF('Model inputs'!B2048=0,"",SUM('Model inputs'!B2011,'Model inputs'!B2012,'Model inputs'!B2013,'Model inputs'!B2014,'Model inputs'!B2015,'Model inputs'!B2016,'Model inputs'!B2017,'Model inputs'!B2018,'Model inputs'!B2019,'Model inputs'!B2020,'Model inputs'!B2021,'Model inputs'!B2022,'Model inputs'!B2023,'Model inputs'!B2024,'Model inputs'!B2025,'Model inputs'!B2026,'Model inputs'!B2027,'Model inputs'!B2028,'Model inputs'!B2029,'Model inputs'!B2030,'Model inputs'!B2031,'Model inputs'!B2032,'Model inputs'!B2033,'Model inputs'!B2034,'Model inputs'!B2035,'Model inputs'!B2036,'Model inputs'!B2037,'Model inputs'!B2038,'Model inputs'!B2039,'Model inputs'!B2040,'Model inputs'!B2041,'Model inputs'!B2042,'Model inputs'!B2043,'Model inputs'!B2044,'Model inputs'!B2045,'Model inputs'!B2046,'Model inputs'!B2047)) -> 792812.5 | AI53: =IF('Model inputs'!B2086=0,"",SUM('Model inputs'!B2049,'Model inputs'!B2050,'Model inputs'!B2051,'Model inputs'!B2052,'Model inputs'!B2053,'Model inputs'!B2054,'Model inputs'!B2055,'Model inputs'!B2056,'Model inputs'!B2057,'Model inputs'!B2058,'Model inputs'!B2059,'Model inputs'!B2060,'Model inputs'!B2061,'Model inputs'!B2062,'Model inputs'!B2063,'Model inputs'!B2064,'Model inputs'!B2065,'Model inputs'!B2066,'Model inputs'!B2067,'Model inputs'!B2068,'Model inputs'!B2069,'Model inputs'!B2070,'Model inputs'!B2071,'Model inputs'!B2072,'Model inputs'!B2073,'Model inputs'!B2074,'Model inputs'!B2075,'Model inputs'!B2076,'Model inputs'!B2077,'Model inputs'!B2078,'Model inputs'!B2079,'Model inputs'!B2080,'Model inputs'!B2081,'Model inputs'!B2082,'Model inputs'!B2083,'Model inputs'!B2084,'Model inputs'!B2085)) -> 821527.78 | AJ53: =IF('Model inputs'!B2124=0,"",SUM('Model inputs'!B2087,'Model inputs'!B2088,'Model inputs'!B2089,'Model inputs'!B2090,'Model inputs'!B2091,'Model inputs'!B2092,'Model inputs'!B2093,'Model inputs'!B2094,'Model inputs'!B2095,'Model inputs'!B2096,'Model inputs'!B2097,'Model inputs'!B2098,'Model inputs'!B2099,'Model inputs'!B2100,'Model inputs'!B2101,'Model inputs'!B2102,'Model inputs'!B2103,'Model inputs'!B2104,'Model inputs'!B2105,'Model inputs'!B2106,'Model inputs'!B2107,'Model inputs'!B2108,'Model inputs'!B2109,'Model inputs'!B2110,'Model inputs'!B2111,'Model inputs'!B2112,'Model inputs'!B2113,'Model inputs'!B2114,'Model inputs'!B2115,'Model inputs'!B2116,'Model inputs'!B2117,'Model inputs'!B2118,'Model inputs'!B2119,'Model inputs'!B2120,'Model inputs'!B2121,'Model inputs'!B2122,'Model inputs'!B2123)) -> 850590.28 | AK53: =IF('Model inputs'!B2162=0,"",SUM('Model inputs'!B2125,'Model inputs'!B2126,'Model inputs'!B2127,'Model inputs'!B2128,'Model inputs'!B2129,'Model inputs'!B2130,'Model inputs'!B2131,'Model inputs'!B2132,'Model inputs'!B2133,'Model inputs'!B2134,'Model inputs'!B2135,'Model inputs'!B2136,'Model inputs'!B2137,'Model inputs'!B2138,'Model inputs'!B2139,'Model inputs'!B2140,'Model inputs'!B2141,'Model inputs'!B2142,'Model inputs'!B2143,'Model inputs'!B2144,'Model inputs'!B2145,'Model inputs'!B2146,'Model inputs'!B2147,'Model inputs'!B2148,'Model inputs'!B2149,'Model inputs'!B2150,'Model inputs'!B2151,'Model inputs'!B2152,'Model inputs'!B2153,'Model inputs'!B2154,'Model inputs'!B2155,'Model inputs'!B2156,'Model inputs'!B2157,'Model inputs'!B2158,'Model inputs'!B2159,'Model inputs'!B2160,'Model inputs'!B2161)) -> 880000
A54: Total cash outflow | B54: ='POA — Monthly financial forecas'!B37+'POA — Monthly financial forecas'!B48+'POA — Monthly financial forecas'!B50+'POA — Monthly financial forecas'!B51 -> 21290.375 | C54: ='POA — Monthly financial forecas'!C37+'POA — Monthly financial forecas'!C48+'POA — Monthly financial forecas'!C50+'POA — Monthly financial forecas'!C51 -> 23599.881 | D54: ='POA — Monthly financial forecas'!D37+'POA — Monthly financial forecas'!D48+'POA — Monthly financial forecas'!D50+'POA — Monthly financial forecas'!D51 -> 25909.47 | E54: ='POA — Monthly financial forecas'!E37+'POA — Monthly financial forecas'!E48+'POA — Monthly financial forecas'!E50+'POA — Monthly financial forecas'!E51 -> 28219.143 | F54: ='POA — Monthly financial forecas'!F37+'POA — Monthly financial forecas'!F48+'POA — Monthly financial forecas'!F50+'POA — Monthly financial forecas'!F51 -> 30528.899 | G54: ='POA — Monthly financial forecas'!G37+'POA — Monthly financial forecas'!G48+'POA — Monthly financial forecas'!G50+'POA — Monthly financial forecas'!G51 -> 32838.738 | H54: ='POA — Monthly financial forecas'!H37+'POA — Monthly financial forecas'!H48+'POA — Monthly financial forecas'!H50+'POA — Monthly financial forecas'!H51 -> 52628.903 | I54: ='POA — Monthly financial forecas'!I37+'POA — Monthly financial forecas'!I48+'POA — Monthly financial forecas'!I50+'POA — Monthly financial forecas'!I51 -> 57451.911 | ... AK54: ='POA — Monthly financial forecas'!AK37+'POA — Monthly financial forecas'!AK48+'POA — Monthly financial forecas'!AK50+'POA — Monthly financial forecas'!AK51 -> 279228.25
A55: Net cash flow | B55: ='POA — Monthly financial forecas'!B53-'POA — Monthly financial forecas'!B54+'POA — Monthly financial forecas'!B52 -> -17769.542 | C55: ='POA — Monthly financial forecas'!C53-'POA — Monthly financial forecas'!C54+'POA — Monthly financial forecas'!C52 -> -16516.548 | D55: ='POA — Monthly financial forecas'!D53-'POA — Monthly financial forecas'!D54+'POA — Monthly financial forecas'!D52 -> -15221.97 | E55: ='POA — Monthly financial forecas'!E53-'POA — Monthly financial forecas'!E54+'POA — Monthly financial forecas'!E52 -> -13885.81 | F55: ='POA — Monthly financial forecas'!F53-'POA — Monthly financial forecas'!F54+'POA — Monthly financial forecas'!F52 -> -12508.065 | G55: ='POA — Monthly financial forecas'!G53-'POA — Monthly financial forecas'!G54+'POA — Monthly financial forecas'!G52 -> -11088.738 | H55: ='POA — Monthly financial forecas'!H53-'POA — Monthly financial forecas'!H54+'POA — Monthly financial forecas'!H52 -> -20320.401 | I55: ='POA — Monthly financial forecas'!I53-'POA — Monthly financial forecas'!I54+'POA — Monthly financial forecas'!I52 -> -14036.086 | ... AK55: ='POA — Monthly financial forecas'!AK53-'POA — Monthly financial forecas'!AK54+'POA — Monthly financial forecas'!AK52 -> 600771.75
A56: Net cash burn | B56: =MAX(-'POA — Monthly financial forecas'!B55,0) -> 17769.542 | C56: =MAX(-'POA — Monthly financial forecas'!C55,0) -> 16516.548 | D56: =MAX(-'POA — Monthly financial forecas'!D55,0) -> 15221.97 | E56: =MAX(-'POA — Monthly financial forecas'!E55,0) -> 13885.81 | F56: =MAX(-'POA — Monthly financial forecas'!F55,0) -> 12508.065 | G56: =MAX(-'POA — Monthly financial forecas'!G55,0) -> 11088.738 | H56: =MAX(-'POA — Monthly financial forecas'!H55,0) -> 20320.401 | I56: =MAX(-'POA — Monthly financial forecas'!I55,0) -> 14036.086 | ... AK56: =MAX(-'POA — Monthly financial forecas'!AK55,0) -> 0
A57: Customer monthly gross profit | B57: =IFERROR('POA — Monthly financial forecas'!B38/'POA — Monthly financial forecas'!B7,0) -> 3513.7917 | C57: =IFERROR('POA — Monthly financial forecas'!C38/'POA — Monthly financial forecas'!C7,0) -> 3534.5833 | D57: =IFERROR('POA — Monthly financial forecas'!D38/'POA — Monthly financial forecas'!D7,0) -> 3555.375 | E57: =IFERROR('POA — Monthly financial forecas'!E38/'POA — Monthly financial forecas'!E7,0) -> 3576.1667 | F57: =IFERROR('POA — Monthly financial forecas'!F38/'POA — Monthly financial forecas'!F7,0) -> 3596.9583 | G57: =IFERROR('POA — Monthly financial forecas'!G38/'POA — Monthly financial forecas'!G7,0) -> 3617.75 | H57: =IFERROR('POA — Monthly financial forecas'!H38/'POA — Monthly financial forecas'!H7,0) -> 3720.4482 | I57: =IFERROR('POA — Monthly financial forecas'!I38/'POA — Monthly financial forecas'!I7,0) -> 3823.1465 | ... AK57: =IFERROR('POA — Monthly financial forecas'!AK38/'POA — Monthly financial forecas'!AK7,0) -> 5489
A58: Blended gross profit LTV | B58: ='POA — Monthly financial forecas'!B57*'Model inputs'!AM30*12 -> 147579.25 | C58: ='POA — Monthly financial forecas'!C57*'Model inputs'!AM30*12 -> 148452.5 | D58: ='POA — Monthly financial forecas'!D57*'Model inputs'!AM30*12 -> 149325.75 | E58: ='POA — Monthly financial forecas'!E57*'Model inputs'!AM30*12 -> 150199 | F58: ='POA — Monthly financial forecas'!F57*'Model inputs'!AM30*12 -> 151072.25 | G58: ='POA — Monthly financial forecas'!G57*'Model inputs'!AM30*12 -> 151945.5 | H58: ='POA — Monthly financial forecas'!H57*'Model inputs'!AM30*12 -> 156258.83 | I58: ='POA — Monthly financial forecas'!I57*'Model inputs'!AM30*12 -> 160572.15 | J58: ='POA — Monthly financial forecas'!J57*'Model inputs'!AM30*12 -> 164885.48 | K58: ='POA — Monthly financial forecas'!K57*'Model inputs'!AM30*12 -> 169198.8 | L58: ='POA — Monthly financial forecas'!L57*'Model inputs'!AM30*12 -> 173512.13 | M58: ='POA — Monthly financial forecas'!M57*'Model inputs'!AM30*12 -> 177825.45 | N58: ='POA — Monthly financial forecas'!N57*'Model inputs'!AM30*12 -> 181371.38 | O58: ='POA — Monthly financial forecas'!O57*'Model inputs'!AM30*12 -> 184917.3 | P58: ='POA — Monthly financial forecas'!P57*'Model inputs'!AM30*12 -> 188463.23 | Q58: ='POA — Monthly financial forecas'!Q57*'Model inputs'!AM30*12 -> 192009.15 | R58: ='POA — Monthly financial forecas'!R57*'Model inputs'!AM30*12 -> 195555.08 | S58: ='POA — Monthly financial forecas'!S57*'Model inputs'!AM30*12 -> 199101 | T58: ='POA — Monthly financial forecas'!T57*'Model inputs'!AM30*12 -> 200847.5 | U58: ='POA — Monthly financial forecas'!U57*'Model inputs'!AM30*12 -> 202594 | V58: ='POA — Monthly financial forecas'!V57*'Model inputs'!AM30*12 -> 204340.5 | W58: ='POA — Monthly financial forecas'!W57*'Model inputs'!AM30*12 -> 206087 | X58: ='POA — Monthly financial forecas'!X57*'Model inputs'!AM30*12 -> 207833.5 | Y58: ='POA — Monthly financial forecas'!Y57*'Model inputs'!AM30*12 -> 209580 | Z58: ='POA — Monthly financial forecas'!Z57*'Model inputs'!AM30*12 -> 211326.5 | AA58: ='POA — Monthly financial forecas'!AA57*'Model inputs'!AM30*12 -> 213073 | AB58: ='POA — Monthly financial forecas'!AB57*'Model inputs'!AM30*12 -> 214819.5 | AC58: ='POA — Monthly financial forecas'!AC57*'Model inputs'!AM30*12 -> 216566 | AD58: ='POA — Monthly financial forecas'!AD57*'Model inputs'!AM30*12 -> 218312.5 | AE58: ='POA — Monthly financial forecas'!AE57*'Model inputs'!AM30*12 -> 220059 | AF58: ='POA — Monthly financial forecas'!AF57*'Model inputs'!AM30*12 -> 221805.5 | AG58: ='POA — Monthly financial forecas'!AG57*'Model inputs'!AM30*12 -> 223552 | AH58: ='POA — Monthly financial forecas'!AH57*'Model inputs'!AM30*12 -> 225298.5 | AI58: ='POA — Monthly financial forecas'!AI57*'Model inputs'!AM30*12 -> 227045 | AJ58: ='POA — Monthly financial forecas'!AJ57*'Model inputs'!AM30*12 -> 228791.5 | AK58: ='POA — Monthly financial forecas'!AK57*'Model inputs'!AM30*12 -> 230538
A59: Blended LTV CAC ratio | B59: ='POA — Monthly financial forecas'!B58/('Model inputs'!AM11*'Model inputs'!AM10) -> 16.041223 | C59: ='POA — Monthly financial forecas'!C58/('Model inputs'!AM11*'Model inputs'!AM10) -> 16.136141 | D59: ='POA — Monthly financial forecas'!D58/('Model inputs'!AM11*'Model inputs'!AM10) -> 16.23106 | E59: ='POA — Monthly financial forecas'!E58/('Model inputs'!AM11*'Model inputs'!AM10) -> 16.325978 | F59: ='POA — Monthly financial forecas'!F58/('Model inputs'!AM11*'Model inputs'!AM10) -> 16.420897 | G59: ='POA — Monthly financial forecas'!G58/('Model inputs'!AM11*'Model inputs'!AM10) -> 16.515815 | H59: ='POA — Monthly financial forecas'!H58/('Model inputs'!AM11*'Model inputs'!AM10) -> 16.984655 | I59: ='POA — Monthly financial forecas'!I58/('Model inputs'!AM11*'Model inputs'!AM10) -> 17.453495 | J59: ='POA — Monthly financial forecas'!J58/('Model inputs'!AM11*'Model inputs'!AM10) -> 17.922334 | K59: ='POA — Monthly financial forecas'!K58/('Model inputs'!AM11*'Model inputs'!AM10) -> 18.391174 | L59: ='POA — Monthly financial forecas'!L58/('Model inputs'!AM11*'Model inputs'!AM10) -> 18.860014 | M59: ='POA — Monthly financial forecas'!M58/('Model inputs'!AM11*'Model inputs'!AM10) -> 19.328854 | N59: ='POA — Monthly financial forecas'!N58/('Model inputs'!AM11*'Model inputs'!AM10) -> 19.71428 | O59: ='POA — Monthly financial forecas'!O58/('Model inputs'!AM11*'Model inputs'!AM10) -> 20.099707 | P59: ='POA — Monthly financial forecas'!P58/('Model inputs'!AM11*'Model inputs'!AM10) -> 20.485133 | Q59: ='POA — Monthly financial forecas'!Q58/('Model inputs'!AM11*'Model inputs'!AM10) -> 20.87056 | R59: ='POA — Monthly financial forecas'!R58/('Model inputs'!AM11*'Model inputs'!AM10) -> 21.255986 | S59: ='POA — Monthly financial forecas'!S58/('Model inputs'!AM11*'Model inputs'!AM10) -> 21.641413 | T59: ='POA — Monthly financial forecas'!T58/('Model inputs'!AM11*'Model inputs'!AM10) -> 21.83125 | U59: ='POA — Monthly financial forecas'!U58/('Model inputs'!AM11*'Model inputs'!AM10) -> 22.021087 | V59: ='POA — Monthly financial forecas'!V58/('Model inputs'!AM11*'Model inputs'!AM10) -> 22.210924 | W59: ='POA — Monthly financial forecas'!W58/('Model inputs'!AM11*'Model inputs'!AM10) -> 22.400761 | X59: ='POA — Monthly financial forecas'!X58/('Model inputs'!AM11*'Model inputs'!AM10) -> 22.590598 | Y59: ='POA — Monthly financial forecas'!Y58/('Model inputs'!AM11*'Model inputs'!AM10) -> 22.780435 | Z59: ='POA — Monthly financial forecas'!Z58/('Model inputs'!AM11*'Model inputs'!AM10) -> 22.970272 | AA59: ='POA — Monthly financial forecas'!AA58/('Model inputs'!AM11*'Model inputs'!AM10) -> 23.160109 | AB59: ='POA — Monthly financial forecas'!AB58/('Model inputs'!AM11*'Model inputs'!AM10) -> 23.349946 | AC59: ='POA — Monthly financial forecas'!AC58/('Model inputs'!AM11*'Model inputs'!AM10) -> 23.539783 | AD59: ='POA — Monthly financial forecas'!AD58/('Model inputs'!AM11*'Model inputs'!AM10) -> 23.72962 | AE59: ='POA — Monthly financial forecas'!AE58/('Model inputs'!AM11*'Model inputs'!AM10) -> 23.919457 | AF59: ='POA — Monthly financial forecas'!AF58/('Model inputs'!AM11*'Model inputs'!AM10) -> 24.109293 | AG59: ='POA — Monthly financial forecas'!AG58/('Model inputs'!AM11*'Model inputs'!AM10) -> 24.29913 | AH59: ='POA — Monthly financial forecas'!AH58/('Model inputs'!AM11*'Model inputs'!AM10) -> 24.488967 | AI59: ='POA — Monthly financial forecas'!AI58/('Model inputs'!AM11*'Model inputs'!AM10) -> 24.678804 | AJ59: ='POA — Monthly financial forecas'!AJ58/('Model inputs'!AM11*'Model inputs'!AM10) -> 24.868641 | AK59: ='POA — Monthly financial forecas'!AK58/('Model inputs'!AM11*'Model inputs'!AM10) -> 25.058478
A60: Blended CAC payback months | B60: =('Model inputs'!AM11*'Model inputs'!AM10)/'POA — Monthly financial forecas'!B57 -> 2.6182543 | C60: =('Model inputs'!AM11*'Model inputs'!AM10)/'POA — Monthly financial forecas'!C57 -> 2.6028528 | D60: =('Model inputs'!AM11*'Model inputs'!AM10)/'POA — Monthly financial forecas'!D57 -> 2.5876314 | E60: =('Model inputs'!AM11*'Model inputs'!AM10)/'POA — Monthly financial forecas'!E57 -> 2.572587 | F60: =('Model inputs'!AM11*'Model inputs'!AM10)/'POA — Monthly financial forecas'!F57 -> 2.5577166 | G60: =('Model inputs'!AM11*'Model inputs'!AM10)/'POA — Monthly financial forecas'!G57 -> 2.5430171 | H60: =('Model inputs'!AM11*'Model inputs'!AM10)/'POA — Monthly financial forecas'!H57 -> 2.4728203 | I60: =('Model inputs'!AM11*'Model inputs'!AM10)/'POA — Monthly financial forecas'!I57 -> 2.4063949 | J60: =('Model inputs'!AM11*'Model inputs'!AM10)/'POA — Monthly financial forecas'!J57 -> 2.3434447 | K60: =('Model inputs'!AM11*'Model inputs'!AM10)/'POA — Monthly financial forecas'!K57 -> 2.2837041 | L60: =('Model inputs'!AM11*'Model inputs'!AM10)/'POA — Monthly financial forecas'!L57 -> 2.2269337 | M60: =('Model inputs'!AM11*'Model inputs'!AM10)/'POA — Monthly financial forecas'!M57 -> 2.1729173 | N60: =('Model inputs'!AM11*'Model inputs'!AM10)/'POA — Monthly financial forecas'!N57 -> 2.1304354 | O60: =('Model inputs'!AM11*'Model inputs'!AM10)/'POA — Monthly financial forecas'!O57 -> 2.0895827 | P60: =('Model inputs'!AM11*'Model inputs'!AM10)/'POA — Monthly financial forecas'!P57 -> 2.0502673 | Q60: =('Model inputs'!AM11*'Model inputs'!AM10)/'POA — Monthly financial forecas'!Q57 -> 2.0124041 | R60: =('Model inputs'!AM11*'Model inputs'!AM10)/'POA — Monthly financial forecas'!R57 -> 1.9759139 | S60: =('Model inputs'!AM11*'Model inputs'!AM10)/'POA — Monthly financial forecas'!S57 -> 1.9407236 | T60: =('Model inputs'!AM11*'Model inputs'!AM10)/'POA — Monthly financial forecas'!T57 -> 1.9238477 | U60: =('Model inputs'!AM11*'Model inputs'!AM10)/'POA — Monthly financial forecas'!U57 -> 1.9072628 | V60: =('Model inputs'!AM11*'Model inputs'!AM10)/'POA — Monthly financial forecas'!V57 -> 1.8909614 | W60: =('Model inputs'!AM11*'Model inputs'!AM10)/'POA — Monthly financial forecas'!W57 -> 1.8749363 | X60: =('Model inputs'!AM11*'Model inputs'!AM10)/'POA — Monthly financial forecas'!X57 -> 1.8591805 | Y60: =('Model inputs'!AM11*'Model inputs'!AM10)/'POA — Monthly financial forecas'!Y57 -> 1.8436874 | Z60: =('Model inputs'!AM11*'Model inputs'!AM10)/'POA — Monthly financial forecas'!Z57 -> 1.8284503 | AA60: =('Model inputs'!AM11*'Model inputs'!AM10)/'POA — Monthly financial forecas'!AA57 -> 1.813463 | AB60: =('Model inputs'!AM11*'Model inputs'!AM10)/'POA — Monthly financial forecas'!AB57 -> 1.7987194 | AC60: =('Model inputs'!AM11*'Model inputs'!AM10)/'POA — Monthly financial forecas'!AC57 -> 1.7842136 | AD60: =('Model inputs'!AM11*'Model inputs'!AM10)/'POA — Monthly financial forecas'!AD57 -> 1.7699399 | AE60: =('Model inputs'!AM11*'Model inputs'!AM10)/'POA — Monthly financial forecas'!AE57 -> 1.7558927 | AF60: =('Model inputs'!AM11*'Model inputs'!AM10)/'POA — Monthly financial forecas'!AF57 -> 1.7420668 | AG60: =('Model inputs'!AM11*'Model inputs'!AM10)/'POA — Monthly financial forecas'!AG57 -> 1.7284569 | AH60: =('Model inputs'!AM11*'Model inputs'!AM10)/'POA — Monthly financial forecas'!AH57 -> 1.715058 | AI60: =('Model inputs'!AM11*'Model inputs'!AM10)/'POA — Monthly financial forecas'!AI57 -> 1.7018653 | AJ60: =('Model inputs'!AM11*'Model inputs'!AM10)/'POA — Monthly financial forecas'!AJ57 -> 1.6888739 | AK60: =('Model inputs'!AM11*'Model inputs'!AM10)/'POA — Monthly financial forecas'!AK57 -> 1.6760794
A61: Accounts receivable | B61: ='Model inputs'!B6+'POA — Monthly financial forecas'!B27-'POA — Monthly financial forecas'!B53 -> 0 | C61: ='POA — Monthly financial forecas'!B61+'POA — Monthly financial forecas'!C27-'POA — Monthly financial forecas'!C53 -> 0 | D61: ='POA — Monthly financial forecas'!C61+'POA — Monthly financial forecas'!D27-'POA — Monthly financial forecas'!D53 -> 0 | E61: ='POA — Monthly financial forecas'!D61+'POA — Monthly financial forecas'!E27-'POA — Monthly financial forecas'!E53 -> 0 | F61: ='POA — Monthly financial forecas'!E61+'POA — Monthly financial forecas'!F27-'POA — Monthly financial forecas'!F53 -> 0 | G61: ='POA — Monthly financial forecas'!F61+'POA — Monthly financial forecas'!G27-'POA — Monthly financial forecas'!G53 -> 0 | H61: ='POA — Monthly financial forecas'!G61+'POA — Monthly financial forecas'!H27-'POA — Monthly financial forecas'!H53 -> 0 | I61: ='POA — Monthly financial forecas'!H61+'POA — Monthly financial forecas'!I27-'POA — Monthly financial forecas'!I53 -> 0 | J61: ='POA — Monthly financial forecas'!I61+'POA — Monthly financial forecas'!J27-'POA — Monthly financial forecas'!J53 -> 0 | ... AK61: ='POA — Monthly financial forecas'!AJ61+'POA — Monthly financial forecas'!AK27-'POA — Monthly financial forecas'!AK53 -> 0
A62: Opening cash | B62: =IF(IF(IF(ISERROR('POA — Monthly financial forecas'!B5=1),'POA — Monthly financial forecas'!B5=1,IF('POA — Monthly financial forecas'!B5="","",'POA — Monthly financial forecas'!B5=1))="",FALSE,IF(ISERROR('POA — Monthly financial forecas'!B5=1),'POA — Monthly financial forecas'!B5=1,IF('POA — Monthly financial forecas'!B5="","",'POA — Monthly financial forecas'!B5=1))),IF('Model inputs'!AM46="","",'Model inputs'!AM46),IF('Model inputs'!B34="","",'Model inputs'!B34)) -> 500000 | C62: =IF(IF(IF(ISERROR('POA — Monthly financial forecas'!C5=1),'POA — Monthly financial forecas'!C5=1,IF('POA — Monthly financial forecas'!C5="","",'POA — Monthly financial forecas'!C5=1))="",FALSE,IF(ISERROR('POA — Monthly financial forecas'!C5=1),'POA — Monthly financial forecas'!C5=1,IF('POA — Monthly financial forecas'!C5="","",'POA — Monthly financial forecas'!C5=1))),IF('Model inputs'!AM46="","",'Model inputs'!AM46),IF('POA — Monthly financial forecas'!B63="","",'POA — Monthly financial forecas'!B63)) -> 482230.46 | D62: =IF(IF(IF(ISERROR('POA — Monthly financial forecas'!D5=1),'POA — Monthly financial forecas'!D5=1,IF('POA — Monthly financial forecas'!D5="","",'POA — Monthly financial forecas'!D5=1))="",FALSE,IF(ISERROR('POA — Monthly financial forecas'!D5=1),'POA — Monthly financial forecas'!D5=1,IF('POA — Monthly financial forecas'!D5="","",'POA — Monthly financial forecas'!D5=1))),IF('Model inputs'!AM46="","",'Model inputs'!AM46),IF('POA — Monthly financial forecas'!C63="","",'POA — Monthly financial forecas'!C63)) -> 465713.91 | E62: =IF(IF(IF(ISERROR('POA — Monthly financial forecas'!E5=1),'POA — Monthly financial forecas'!E5=1,IF('POA — Monthly financial forecas'!E5="","",'POA — Monthly financial forecas'!E5=1))="",FALSE,IF(ISERROR('POA — Monthly financial forecas'!E5=1),'POA — Monthly financial forecas'!E5=1,IF('POA — Monthly financial forecas'!E5="","",'POA — Monthly financial forecas'!E5=1))),IF('Model inputs'!AM46="","",'Model inputs'!AM46),IF('POA — Monthly financial forecas'!D63="","",'POA — Monthly financial forecas'!D63)) -> 450491.94 | F62: =IF(IF(IF(ISERROR('POA — Monthly financial forecas'!F5=1),'POA — Monthly financial forecas'!F5=1,IF('POA — Monthly financial forecas'!F5="","",'POA — Monthly financial forecas'!F5=1))="",FALSE,IF(ISERROR('POA — Monthly financial forecas'!F5=1),'POA — Monthly financial forecas'!F5=1,IF('POA — Monthly financial forecas'!F5="","",'POA — Monthly financial forecas'!F5=1))),IF('Model inputs'!AM46="","",'Model inputs'!AM46),IF('POA — Monthly financial forecas'!E63="","",'POA — Monthly financial forecas'!E63)) -> 436606.13 | G62: =IF(IF(IF(ISERROR('POA — Monthly financial forecas'!G5=1),'POA — Monthly financial forecas'!G5=1,IF('POA — Monthly financial forecas'!G5="","",'POA — Monthly financial forecas'!G5=1))="",FALSE,IF(ISERROR('POA — Monthly financial forecas'!G5=1),'POA — Monthly financial forecas'!G5=1,IF('POA — Monthly financial forecas'!G5="","",'POA — Monthly financial forecas'!G5=1))),IF('Model inputs'!AM46="","",'Model inputs'!AM46),IF('POA — Monthly financial forecas'!F63="","",'POA — Monthly financial forecas'!F63)) -> 424098.07 | H62: =IF(IF(IF(ISERROR('POA — Monthly financial forecas'!H5=1),'POA — Monthly financial forecas'!H5=1,IF('POA — Monthly financial forecas'!H5="","",'POA — Monthly financial forecas'!H5=1))="",FALSE,IF(ISERROR('POA — Monthly financial forecas'!H5=1),'POA — Monthly financial forecas'!H5=1,IF('POA — Monthly financial forecas'!H5="","",'POA — Monthly financial forecas'!H5=1))),IF('Model inputs'!AM46="","",'Model inputs'!AM46),IF('POA — Monthly financial forecas'!G63="","",'POA — Monthly financial forecas'!G63)) -> 413009.33 | I62: =IF(IF(IF(ISERROR('POA — Monthly financial forecas'!I5=1),'POA — Monthly financial forecas'!I5=1,IF('POA — Monthly financial forecas'!I5="","",'POA — Monthly financial forecas'!I5=1))="",FALSE,IF(ISERROR('POA — Monthly financial forecas'!I5=1),'POA — Monthly financial forecas'!I5=1,IF('POA — Monthly financial forecas'!I5="","",'POA — Monthly financial forecas'!I5=1))),IF('Model inputs'!AM46="","",'Model inputs'!AM46),IF('POA — Monthly financial forecas'!H63="","",'POA — Monthly financial forecas'!H63)) -> 392688.93 | J62: =IF(IF(IF(ISERROR('POA — Monthly financial forecas'!J5=1),'POA — Monthly financial forecas'!J5=1,IF('POA — Monthly financial forecas'!J5="","",'POA — Monthly financial forecas'!J5=1))="",FALSE,IF(ISERROR('POA — Monthly financial forecas'!J5=1),'POA — Monthly financial forecas'!J5=1,IF('POA — Monthly financial forecas'!J5="","",'POA — Monthly financial forecas'!J5=1))),IF('Model inputs'!AM46="","",'Model inputs'!AM46),IF('POA — Monthly financial forecas'!I63="","",'POA — Monthly financial forecas'!I63)) -> 378652.84 | K62: =IF(IF(IF(ISERROR('POA — Monthly financial forecas'!K5=1),'POA — Monthly financial forecas'!K5=1,IF('POA — Monthly financial forecas'!K5="","",'POA — Monthly financial forecas'!K5=1))="",FALSE,IF(ISERROR('POA — Monthly financial forecas'!K5=1),'POA — Monthly financial forecas'!K5=1,IF('POA — Monthly financial forecas'!K5="","",'POA — Monthly financial forecas'!K5=1))),IF('Model inputs'!AM46="","",'Model inputs'!AM46),IF('POA — Monthly financial forecas'!J63="","",'POA — Monthly financial forecas'!J63)) -> 371448.79 | L62: =IF(IF(IF(ISERROR('POA — Monthly financial forecas'!L5=1),'POA — Monthly financial forecas'!L5=1,IF('POA — Monthly financial forecas'!L5="","",'POA — Monthly financial forecas'!L5=1))="",FALSE,IF(ISERROR('POA — Monthly financial forecas'!L5=1),'POA — Monthly financial forecas'!L5=1,IF('POA — Monthly financial forecas'!L5="","",'POA — Monthly financial forecas'!L5=1))),IF('Model inputs'!AM46="","",'Model inputs'!AM46),IF('POA — Monthly financial forecas'!K63="","",'POA — Monthly financial forecas'!K63)) -> 371624.51 | M62: =IF(IF(IF(ISERROR('POA — Monthly financial forecas'!M5=1),'POA — Monthly financial forecas'!M5=1,IF('POA — Monthly financial forecas'!M5="","",'POA — Monthly financial forecas'!M5=1))="",FALSE,IF(ISERROR('POA — Monthly financial forecas'!M5=1),'POA — Monthly financial forecas'!M5=1,IF('POA — Monthly financial forecas'!M5="","",'POA — Monthly financial forecas'!M5=1))),IF('Model inputs'!AM46="","",'Model inputs'!AM46),IF('POA — Monthly financial forecas'!L63="","",'POA — Monthly financial forecas'!L63)) -> 379727.71 | N62: =IF(IF(IF(ISERROR('POA — Monthly financial forecas'!N5=1),'POA — Monthly financial forecas'!N5=1,IF('POA — Monthly financial forecas'!N5="","",'POA — Monthly financial forecas'!N5=1))="",FALSE,IF(ISERROR('POA — Monthly financial forecas'!N5=1),'POA — Monthly financial forecas'!N5=1,IF('POA — Monthly financial forecas'!N5="","",'POA — Monthly financial forecas'!N5=1))),IF('Model inputs'!AM46="","",'Model inputs'!AM46),IF('POA — Monthly financial forecas'!M63="","",'POA — Monthly financial forecas'!M63)) -> 396306.12 | O62: =IF(IF(IF(ISERROR('POA — Monthly financial forecas'!O5=1),'POA — Monthly financial forecas'!O5=1,IF('POA — Monthly financial forecas'!O5="","",'POA — Monthly financial forecas'!O5=1))="",FALSE,IF(ISERROR('POA — Monthly financial forecas'!O5=1),'POA — Monthly financial forecas'!O5=1,IF('POA — Monthly financial forecas'!O5="","",'POA — Monthly financial forecas'!O5=1))),IF('Model inputs'!AM46="","",'Model inputs'!AM46),IF('POA — Monthly financial forecas'!N63="","",'POA — Monthly financial forecas'!N63)) -> 399374.12 | P62: =IF(IF(IF(ISERROR('POA — Monthly financial forecas'!P5=1),'POA — Monthly financial forecas'!P5=1,IF('POA — Monthly financial forecas'!P5="","",'POA — Monthly financial forecas'!P5=1))="",FALSE,IF(ISERROR('POA — Monthly financial forecas'!P5=1),'POA — Monthly financial forecas'!P5=1,IF('POA — Monthly financial forecas'!P5="","",'POA — Monthly financial forecas'!P5=1))),IF('Model inputs'!AM46="","",'Model inputs'!AM46),IF('POA — Monthly financial forecas'!O63="","",'POA — Monthly financial forecas'!O63)) -> 422931.26 | Q62: =IF(IF(IF(ISERROR('POA — Monthly financial forecas'!Q5=1),'POA — Monthly financial forecas'!Q5=1,IF('POA — Monthly financial forecas'!Q5="","",'POA — Monthly financial forecas'!Q5=1))="",FALSE,IF(ISERROR('POA — Monthly financial forecas'!Q5=1),'POA — Monthly financial forecas'!Q5=1,IF('POA — Monthly financial forecas'!Q5="","",'POA — Monthly financial forecas'!Q5=1))),IF('Model inputs'!AM46="","",'Model inputs'!AM46),IF('POA — Monthly financial forecas'!P63="","",'POA — Monthly financial forecas'!P63)) -> 468046.95 | R62: =IF(IF(IF(ISERROR('POA — Monthly financial forecas'!R5=1),'POA — Monthly financial forecas'!R5=1,IF('POA — Monthly financial forecas'!R5="","",'POA — Monthly financial forecas'!R5=1))="",FALSE,IF(ISERROR('POA — Monthly financial forecas'!R5=1),'POA — Monthly financial forecas'!R5=1,IF('POA — Monthly financial forecas'!R5="","",'POA — Monthly financial forecas'!R5=1))),IF('Model inputs'!AM46="","",'Model inputs'!AM46),IF('POA — Monthly financial forecas'!Q63="","",'POA — Monthly financial forecas'!Q63)) -> 535790.59 | S62: =IF(IF(IF(ISERROR('POA — Monthly financial forecas'!S5=1),'POA — Monthly financial forecas'!S5=1,IF('POA — Monthly financial forecas'!S5="","",'POA — Monthly financial forecas'!S5=1))="",FALSE,IF(ISERROR('POA — Monthly financial forecas'!S5=1),'POA — Monthly financial forecas'!S5=1,IF('POA — Monthly financial forecas'!S5="","",'POA — Monthly financial forecas'!S5=1))),IF('Model inputs'!AM46="","",'Model inputs'!AM46),IF('POA — Monthly financial forecas'!R63="","",'POA — Monthly financial forecas'!R63)) -> 627231.6 | T62: =IF(IF(IF(ISERROR('POA — Monthly financial forecas'!T5=1),'POA — Monthly financial forecas'!T5=1,IF('POA — Monthly financial forecas'!T5="","",'POA — Monthly financial forecas'!T5=1))="",FALSE,IF(ISERROR('POA — Monthly financial forecas'!T5=1),'POA — Monthly financial forecas'!T5=1,IF('POA — Monthly financial forecas'!T5="","",'POA — Monthly financial forecas'!T5=1))),IF('Model inputs'!AM46="","",'Model inputs'!AM46),IF('POA — Monthly financial forecas'!S63="","",'POA — Monthly financial forecas'!S63)) -> 743439.38 | U62: =IF(IF(IF(ISERROR('POA — Monthly financial forecas'!U5=1),'POA — Monthly financial forecas'!U5=1,IF('POA — Monthly financial forecas'!U5="","",'POA — Monthly financial forecas'!U5=1))="",FALSE,IF(ISERROR('POA — Monthly financial forecas'!U5=1),'POA — Monthly financial forecas'!U5=1,IF('POA — Monthly financial forecas'!U5="","",'POA — Monthly financial forecas'!U5=1))),IF('Model inputs'!AM46="","",'Model inputs'!AM46),IF('POA — Monthly financial forecas'!T63="","",'POA — Monthly financial forecas'!T63)) -> 882602.08 | V62: =IF(IF(IF(ISERROR('POA — Monthly financial forecas'!V5=1),'POA — Monthly financial forecas'!V5=1,IF('POA — Monthly financial forecas'!V5="","",'POA — Monthly financial forecas'!V5=1))="",FALSE,IF(ISERROR('POA — Monthly financial forecas'!V5=1),'POA — Monthly financial forecas'!V5=1,IF('POA — Monthly financial forecas'!V5="","",'POA — Monthly financial forecas'!V5=1))),IF('Model inputs'!AM46="","",'Model inputs'!AM46),IF('POA — Monthly financial forecas'!U63="","",'POA — Monthly financial forecas'!U63)) -> 1048267.8 | W62: =IF(IF(IF(ISERROR('POA — Monthly financial forecas'!W5=1),'POA — Monthly financial forecas'!W5=1,IF('POA — Monthly financial forecas'!W5="","",'POA — Monthly financial forecas'!W5=1))="",FALSE,IF(ISERROR('POA — Monthly financial forecas'!W5=1),'POA — Monthly financial forecas'!W5=1,IF('POA — Monthly financial forecas'!W5="","",'POA — Monthly financial forecas'!W5=1))),IF('Model inputs'!AM46="","",'Model inputs'!AM46),IF('POA — Monthly financial forecas'!V63="","",'POA — Monthly financial forecas'!V63)) -> 1240991 | X62: =IF(IF(IF(ISERROR('POA — Monthly financial forecas'!X5=1),'POA — Monthly financial forecas'!X5=1,IF('POA — Monthly financial forecas'!X5="","",'POA — Monthly financial forecas'!X5=1))="",FALSE,IF(ISERROR('POA — Monthly financial forecas'!X5=1),'POA — Monthly financial forecas'!X5=1,IF('POA — Monthly financial forecas'!X5="","",'POA — Monthly financial forecas'!X5=1))),IF('Model inputs'!AM46="","",'Model inputs'!AM46),IF('POA — Monthly financial forecas'!W63="","",'POA — Monthly financial forecas'!W63)) -> 1461326 | Y62: =IF(IF(IF(ISERROR('POA — Monthly financial forecas'!Y5=1),'POA — Monthly financial forecas'!Y5=1,IF('POA — Monthly financial forecas'!Y5="","",'POA — Monthly financial forecas'!Y5=1))="",FALSE,IF(ISERROR('POA — Monthly financial forecas'!Y5=1),'POA — Monthly financial forecas'!Y5=1,IF('POA — Monthly financial forecas'!Y5="","",'POA — Monthly financial forecas'!Y5=1))),IF('Model inputs'!AM46="","",'Model inputs'!AM46),IF('POA — Monthly financial forecas'!X63="","",'POA — Monthly financial forecas'!X63)) -> 1709827.5 | Z62: =IF(IF(IF(ISERROR('POA — Monthly financial forecas'!Z5=1),'POA — Monthly financial forecas'!Z5=1,IF('POA — Monthly financial forecas'!Z5="","",'POA — Monthly financial forecas'!Z5=1))="",FALSE,IF(ISERROR('POA — Monthly financial forecas'!Z5=1),'POA — Monthly financial forecas'!Z5=1,IF('POA — Monthly financial forecas'!Z5="","",'POA — Monthly financial forecas'!Z5=1))),IF('Model inputs'!AM46="","",'Model inputs'!AM46),IF('POA — Monthly financial forecas'!Y63="","",'POA — Monthly financial forecas'!Y63)) -> 1987049.7 | AA62: =IF(IF(IF(ISERROR('POA — Monthly financial forecas'!AA5=1),'POA — Monthly financial forecas'!AA5=1,IF('POA — Monthly financial forecas'!AA5="","",'POA — Monthly financial forecas'!AA5=1))="",FALSE,IF(ISERROR('POA — Monthly financial forecas'!AA5=1),'POA — Monthly financial forecas'!AA5=1,IF('POA — Monthly financial forecas'!AA5="","",'POA — Monthly financial forecas'!AA5=1))),IF('Model inputs'!AM46="","",'Model inputs'!AM46),IF('POA — Monthly financial forecas'!Z63="","",'POA — Monthly financial forecas'!Z63)) -> 2298154.2 | AB62: =IF(IF(IF(ISERROR('POA — Monthly financial forecas'!AB5=1),'POA — Monthly financial forecas'!AB5=1,IF('POA — Monthly financial forecas'!AB5="","",'POA — Monthly financial forecas'!AB5=1))="",FALSE,IF(ISERROR('POA — Monthly financial forecas'!AB5=1),'POA — Monthly financial forecas'!AB5=1,IF('POA — Monthly financial forecas'!AB5="","",'POA — Monthly financial forecas'!AB5=1))),IF('Model inputs'!AM46="","",'Model inputs'!AM46),IF('POA — Monthly financial forecas'!AA63="","",'POA — Monthly financial forecas'!AA63)) -> 2636141.9 | AC62: =IF(IF(IF(ISERROR('POA — Monthly financial forecas'!AC5=1),'POA — Monthly financial forecas'!AC5=1,IF('POA — Monthly financial forecas'!AC5="","",'POA — Monthly financial forecas'!AC5=1))="",FALSE,IF(ISERROR('POA — Monthly financial forecas'!AC5=1),'POA — Monthly financial forecas'!AC5=1,IF('POA — Monthly financial forecas'!AC5="","",'POA — Monthly financial forecas'!AC5=1))),IF('Model inputs'!AM46="","",'Model inputs'!AM46),IF('POA — Monthly financial forecas'!AB63="","",'POA — Monthly financial forecas'!AB63)) -> 3001498.1 | AD62: =IF(IF(IF(ISERROR('POA — Monthly financial forecas'!AD5=1),'POA — Monthly financial forecas'!AD5=1,IF('POA — Monthly financial forecas'!AD5="","",'POA — Monthly financial forecas'!AD5=1))="",FALSE,IF(ISERROR('POA — Monthly financial forecas'!AD5=1),'POA — Monthly financial forecas'!AD5=1,IF('POA — Monthly financial forecas'!AD5="","",'POA — Monthly financial forecas'!AD5=1))),IF('Model inputs'!AM46="","",'Model inputs'!AM46),IF('POA — Monthly financial forecas'!AC63="","",'POA — Monthly financial forecas'!AC63)) -> 3394707.7 | AE62: =IF(IF(IF(ISERROR('POA — Monthly financial forecas'!AE5=1),'POA — Monthly financial forecas'!AE5=1,IF('POA — Monthly financial forecas'!AE5="","",'POA — Monthly financial forecas'!AE5=1))="",FALSE,IF(ISERROR('POA — Monthly financial forecas'!AE5=1),'POA — Monthly financial forecas'!AE5=1,IF('POA — Monthly financial forecas'!AE5="","",'POA — Monthly financial forecas'!AE5=1))),IF('Model inputs'!AM46="","",'Model inputs'!AM46),IF('POA — Monthly financial forecas'!AD63="","",'POA — Monthly financial forecas'!AD63)) -> 3816256.1 | AF62: =IF(IF(IF(ISERROR('POA — Monthly financial forecas'!AF5=1),'POA — Monthly financial forecas'!AF5=1,IF('POA — Monthly financial forecas'!AF5="","",'POA — Monthly financial forecas'!AF5=1))="",FALSE,IF(ISERROR('POA — Monthly financial forecas'!AF5=1),'POA — Monthly financial forecas'!AF5=1,IF('POA — Monthly financial forecas'!AF5="","",'POA — Monthly financial forecas'!AF5=1))),IF('Model inputs'!AM46="","",'Model inputs'!AM46),IF('POA — Monthly financial forecas'!AE63="","",'POA — Monthly financial forecas'!AE63)) -> 4266628.3 | AG62: =IF(IF(IF(ISERROR('POA — Monthly financial forecas'!AG5=1),'POA — Monthly financial forecas'!AG5=1,IF('POA — Monthly financial forecas'!AG5="","",'POA — Monthly financial forecas'!AG5=1))="",FALSE,IF(ISERROR('POA — Monthly financial forecas'!AG5=1),'POA — Monthly financial forecas'!AG5=1,IF('POA — Monthly financial forecas'!AG5="","",'POA — Monthly financial forecas'!AG5=1))),IF('Model inputs'!AM46="","",'Model inputs'!AM46),IF('POA — Monthly financial forecas'!AF63="","",'POA — Monthly financial forecas'!AF63)) -> 4753674.3 | AH62: =IF(IF(IF(ISERROR('POA — Monthly financial forecas'!AH5=1),'POA — Monthly financial forecas'!AH5=1,IF('POA — Monthly financial forecas'!AH5="","",'POA — Monthly financial forecas'!AH5=1))="",FALSE,IF(ISERROR('POA — Monthly financial forecas'!AH5=1),'POA — Monthly financial forecas'!AH5=1,IF('POA — Monthly financial forecas'!AH5="","",'POA — Monthly financial forecas'!AH5=1))),IF('Model inputs'!AM46="","",'Model inputs'!AM46),IF('POA — Monthly financial forecas'!AG63="","",'POA — Monthly financial forecas'!AG63)) -> 5262772.4 | AI62: =IF(IF(IF(ISERROR('POA — Monthly financial forecas'!AI5=1),'POA — Monthly financial forecas'!AI5=1,IF('POA — Monthly financial forecas'!AI5="","",'POA — Monthly financial forecas'!AI5=1))="",FALSE,IF(ISERROR('POA — Monthly financial forecas'!AI5=1),'POA — Monthly financial forecas'!AI5=1,IF('POA — Monthly financial forecas'!AI5="","",'POA — Monthly financial forecas'!AI5=1))),IF('Model inputs'!AM46="","",'Model inputs'!AM46),IF('POA — Monthly financial forecas'!AH63="","",'POA — Monthly financial forecas'!AH63)) -> 5794269.1 | AJ62: =IF(IF(IF(ISERROR('POA — Monthly financial forecas'!AJ5=1),'POA — Monthly financial forecas'!AJ5=1,IF('POA — Monthly financial forecas'!AJ5="","",'POA — Monthly financial forecas'!AJ5=1))="",FALSE,IF(ISERROR('POA — Monthly financial forecas'!AJ5=1),'POA — Monthly financial forecas'!AJ5=1,IF('POA — Monthly financial forecas'!AJ5="","",'POA — Monthly financial forecas'!AJ5=1))),IF('Model inputs'!AM46="","",'Model inputs'!AM46),IF('POA — Monthly financial forecas'!AI63="","",'POA — Monthly financial forecas'!AI63)) -> 6348511 | AK62: =IF(IF(IF(ISERROR('POA — Monthly financial forecas'!AK5=1),'POA — Monthly financial forecas'!AK5=1,IF('POA — Monthly financial forecas'!AK5="","",'POA — Monthly financial forecas'!AK5=1))="",FALSE,IF(ISERROR('POA — Monthly financial forecas'!AK5=1),'POA — Monthly financial forecas'!AK5=1,IF('POA — Monthly financial forecas'!AK5="","",'POA — Monthly financial forecas'!AK5=1))),IF('Model inputs'!AM46="","",'Model inputs'!AM46),IF('POA — Monthly financial forecas'!AJ63="","",'POA — Monthly financial forecas'!AJ63)) -> 6925844.5
A63: Ending cash | B63: ='POA — Monthly financial forecas'!B62+'POA — Monthly financial forecas'!B55 -> 482230.46 | C63: ='POA — Monthly financial forecas'!C62+'POA — Monthly financial forecas'!C55 -> 465713.91 | D63: ='POA — Monthly financial forecas'!D62+'POA — Monthly financial forecas'!D55 -> 450491.94 | E63: ='POA — Monthly financial forecas'!E62+'POA — Monthly financial forecas'!E55 -> 436606.13 | F63: ='POA — Monthly financial forecas'!F62+'POA — Monthly financial forecas'!F55 -> 424098.07 | G63: ='POA — Monthly financial forecas'!G62+'POA — Monthly financial forecas'!G55 -> 413009.33 | H63: ='POA — Monthly financial forecas'!H62+'POA — Monthly financial forecas'!H55 -> 392688.93 | I63: ='POA — Monthly financial forecas'!I62+'POA — Monthly financial forecas'!I55 -> 378652.84 | ... AK63: ='POA — Monthly financial forecas'!AK62+'POA — Monthly financial forecas'!AK55 -> 7526616.2
A64: Cash above reserve | B64: ='POA — Monthly financial forecas'!B63-'Model inputs'!AM40 -> 382230.46 | C64: ='POA — Monthly financial forecas'!C63-'Model inputs'!AM40 -> 365713.91 | D64: ='POA — Monthly financial forecas'!D63-'Model inputs'!AM40 -> 350491.94 | E64: ='POA — Monthly financial forecas'!E63-'Model inputs'!AM40 -> 336606.13 | F64: ='POA — Monthly financial forecas'!F63-'Model inputs'!AM40 -> 324098.07 | G64: ='POA — Monthly financial forecas'!G63-'Model inputs'!AM40 -> 313009.33 | H64: ='POA — Monthly financial forecas'!H63-'Model inputs'!AM40 -> 292688.93 | I64: ='POA — Monthly financial forecas'!I63-'Model inputs'!AM40 -> 278652.84 | J64: ='POA — Monthly financial forecas'!J63-'Model inputs'!AM40 -> 271448.79 | K64: ='POA — Monthly financial forecas'!K63-'Model inputs'!AM40 -> 271624.51 | L64: ='POA — Monthly financial forecas'!L63-'Model inputs'!AM40 -> 279727.71 | M64: ='POA — Monthly financial forecas'!M63-'Model inputs'!AM40 -> 296306.12 | N64: ='POA — Monthly financial forecas'!N63-'Model inputs'!AM40 -> 299374.12 | O64: ='POA — Monthly financial forecas'!O63-'Model inputs'!AM40 -> 322931.26 | P64: ='POA — Monthly financial forecas'!P63-'Model inputs'!AM40 -> 368046.95 | Q64: ='POA — Monthly financial forecas'!Q63-'Model inputs'!AM40 -> 435790.59 | R64: ='POA — Monthly financial forecas'!R63-'Model inputs'!AM40 -> 527231.6 | S64: ='POA — Monthly financial forecas'!S63-'Model inputs'!AM40 -> 643439.38 | T64: ='POA — Monthly financial forecas'!T63-'Model inputs'!AM40 -> 782602.08 | U64: ='POA — Monthly financial forecas'!U63-'Model inputs'!AM40 -> 948267.79 | V64: ='POA — Monthly financial forecas'!V63-'Model inputs'!AM40 -> 1140991 | W64: ='POA — Monthly financial forecas'!W63-'Model inputs'!AM40 -> 1361326 | X64: ='POA — Monthly financial forecas'!X63-'Model inputs'!AM40 -> 1609827.5 | Y64: ='POA — Monthly financial forecas'!Y63-'Model inputs'!AM40 -> 1887049.7 | Z64: ='POA — Monthly financial forecas'!Z63-'Model inputs'!AM40 -> 2198154.2 | AA64: ='POA — Monthly financial forecas'!AA63-'Model inputs'!AM40 -> 2536141.9 | AB64: ='POA — Monthly financial forecas'!AB63-'Model inputs'!AM40 -> 2901498.1 | AC64: ='POA — Monthly financial forecas'!AC63-'Model inputs'!AM40 -> 3294707.7 | AD64: ='POA — Monthly financial forecas'!AD63-'Model inputs'!AM40 -> 3716256.1 | AE64: ='POA — Monthly financial forecas'!AE63-'Model inputs'!AM40 -> 4166628.3 | AF64: ='POA — Monthly financial forecas'!AF63-'Model inputs'!AM40 -> 4653674.3 | AG64: ='POA — Monthly financial forecas'!AG63-'Model inputs'!AM40 -> 5162772.4 | AH64: ='POA — Monthly financial forecas'!AH63-'Model inputs'!AM40 -> 5694269.1 | AI64: ='POA — Monthly financial forecas'!AI63-'Model inputs'!AM40 -> 6248511 | AJ64: ='POA — Monthly financial forecas'!AJ63-'Model inputs'!AM40 -> 6825844.5 | AK64: ='POA — Monthly financial forecas'!AK63-'Model inputs'!AM40 -> 7426616.2
A65: Runway at current monthly burn | B65: =IF(IF(IF(ISERROR('POA — Monthly financial forecas'!B56>0),'POA — Monthly financial forecas'!B56>0,IF('POA — Monthly financial forecas'!B56="","",'POA — Monthly financial forecas'!B56>0))="",FALSE,IF(ISERROR('POA — Monthly financial forecas'!B56>0),'POA — Monthly financial forecas'!B56>0,IF('POA — Monthly financial forecas'!B56="","",'POA — Monthly financial forecas'!B56>0))),MAX('POA — Monthly financial forecas'!B63,0)/'POA — Monthly financial forecas'!B56,"") -> 27.138036 | C65: =IF(IF(IF(ISERROR('POA — Monthly financial forecas'!C56>0),'POA — Monthly financial forecas'!C56>0,IF('POA — Monthly financial forecas'!C56="","",'POA — Monthly financial forecas'!C56>0))="",FALSE,IF(ISERROR('POA — Monthly financial forecas'!C56>0),'POA — Monthly financial forecas'!C56>0,IF('POA — Monthly financial forecas'!C56="","",'POA — Monthly financial forecas'!C56>0))),MAX('POA — Monthly financial forecas'!C63,0)/'POA — Monthly financial forecas'!C56,"") -> 28.196807 | D65: =IF(IF(IF(ISERROR('POA — Monthly financial forecas'!D56>0),'POA — Monthly financial forecas'!D56>0,IF('POA — Monthly financial forecas'!D56="","",'POA — Monthly financial forecas'!D56>0))="",FALSE,IF(ISERROR('POA — Monthly financial forecas'!D56>0),'POA — Monthly financial forecas'!D56>0,IF('POA — Monthly financial forecas'!D56="","",'POA — Monthly financial forecas'!D56>0))),MAX('POA — Monthly financial forecas'!D63,0)/'POA — Monthly financial forecas'!D56,"") -> 29.594851 | E65: =IF(IF(IF(ISERROR('POA — Monthly financial forecas'!E56>0),'POA — Monthly financial forecas'!E56>0,IF('POA — Monthly financial forecas'!E56="","",'POA — Monthly financial forecas'!E56>0))="",FALSE,IF(ISERROR('POA — Monthly financial forecas'!E56>0),'POA — Monthly financial forecas'!E56>0,IF('POA — Monthly financial forecas'!E56="","",'POA — Monthly financial forecas'!E56>0))),MAX('POA — Monthly financial forecas'!E63,0)/'POA — Monthly financial forecas'!E56,"") -> 31.442613 | F65: =IF(IF(IF(ISERROR('POA — Monthly financial forecas'!F56>0),'POA — Monthly financial forecas'!F56>0,IF('POA — Monthly financial forecas'!F56="","",'POA — Monthly financial forecas'!F56>0))="",FALSE,IF(ISERROR('POA — Monthly financial forecas'!F56>0),'POA — Monthly financial forecas'!F56>0,IF('POA — Monthly financial forecas'!F56="","",'POA — Monthly financial forecas'!F56>0))),MAX('POA — Monthly financial forecas'!F63,0)/'POA — Monthly financial forecas'!F56,"") -> 33.905968 | G65: =IF(IF(IF(ISERROR('POA — Monthly financial forecas'!G56>0),'POA — Monthly financial forecas'!G56>0,IF('POA — Monthly financial forecas'!G56="","",'POA — Monthly financial forecas'!G56>0))="",FALSE,IF(ISERROR('POA — Monthly financial forecas'!G56>0),'POA — Monthly financial forecas'!G56>0,IF('POA — Monthly financial forecas'!G56="","",'POA — Monthly financial forecas'!G56>0))),MAX('POA — Monthly financial forecas'!G63,0)/'POA — Monthly financial forecas'!G56,"") -> 37.245837 | H65: =IF(IF(IF(ISERROR('POA — Monthly financial forecas'!H56>0),'POA — Monthly financial forecas'!H56>0,IF('POA — Monthly financial forecas'!H56="","",'POA — Monthly financial forecas'!H56>0))="",FALSE,IF(ISERROR('POA — Monthly financial forecas'!H56>0),'POA — Monthly financial forecas'!H56>0,IF('POA — Monthly financial forecas'!H56="","",'POA — Monthly financial forecas'!H56>0))),MAX('POA — Monthly financial forecas'!H63,0)/'POA — Monthly financial forecas'!H56,"") -> 19.324861 | I65: =IF(IF(IF(ISERROR('POA — Monthly financial forecas'!I56>0),'POA — Monthly financial forecas'!I56>0,IF('POA — Monthly financial forecas'!I56="","",'POA — Monthly financial forecas'!I56>0))="",FALSE,IF(ISERROR('POA — Monthly financial forecas'!I56>0),'POA — Monthly financial forecas'!I56>0,IF('POA — Monthly financial forecas'!I56="","",'POA — Monthly financial forecas'!I56>0))),MAX('POA — Monthly financial forecas'!I63,0)/'POA — Monthly financial forecas'!I56,"") -> 26.977096 | ... AK65: =IF(IF(IF(ISERROR('POA — Monthly financial forecas'!AK56>0),'POA — Monthly financial forecas'!AK56>0,IF('POA — Monthly financial forecas'!AK56="","",'POA — Monthly financial forecas'!AK56>0))="",FALSE,IF(ISERROR('POA — Monthly financial forecas'!AK56>0),'POA — Monthly financial forecas'!AK56>0,IF('POA — Monthly financial forecas'!AK56="","",'POA — Monthly financial forecas'!AK56>0))),MAX('POA — Monthly financial forecas'!AK63,0)/'POA — Monthly financial forecas'!AK56,"")

Sheet POA — Reconciliation checks
A1: POA — Reconciliation checks
A2: POA — Financial Forecast · Main Scenario
A4: Variable / dimension | B4: 2026-10 | C4: 2026-11 | D4: 2026-12 | E4: 2027-01 | F4: 2027-02 | G4: 2027-03 | H4: 2027-04 | I4: 2027-05 | J4: 2027-06 | K4: 2027-07 | L4: 2027-08 | M4: 2027-09 | N4: 2027-10 | O4: 2027-11 | P4: 2027-12 | Q4: 2028-01 | R4: 2028-02 | S4: 2028-03 | T4: 2028-04 | U4: 2028-05 | V4: 2028-06 | W4: 2028-07 | X4: 2028-08 | Y4: 2028-09 | Z4: 2028-10 | AA4: 2028-11 | AB4: 2028-12 | AC4: 2029-01 | AD4: 2029-02 | AE4: 2029-03 | AF4: 2029-04 | AG4: 2029-05 | AH4: 2029-06 | AI4: 2029-07 | AJ4: 2029-08 | AK4: 2029-09
A5: Customer rollforward check | B5: ='POA — Monthly financial forecas'!B8+'POA — Monthly financial forecas'!B11-'POA — Monthly financial forecas'!B9-'POA — Monthly financial forecas'!B7 -> 0 | C5: ='POA — Monthly financial forecas'!C8+'POA — Monthly financial forecas'!C11-'POA — Monthly financial forecas'!C9-'POA — Monthly financial forecas'!C7 -> 0 | D5: ='POA — Monthly financial forecas'!D8+'POA — Monthly financial forecas'!D11-'POA — Monthly financial forecas'!D9-'POA — Monthly financial forecas'!D7 -> 0 | E5: ='POA — Monthly financial forecas'!E8+'POA — Monthly financial forecas'!E11-'POA — Monthly financial forecas'!E9-'POA — Monthly financial forecas'!E7 -> -4.4408921e-16 | F5: ='POA — Monthly financial forecas'!F8+'POA — Monthly financial forecas'!F11-'POA — Monthly financial forecas'!F9-'POA — Monthly financial forecas'!F7 -> 0 | G5: ='POA — Monthly financial forecas'!G8+'POA — Monthly financial forecas'!G11-'POA — Monthly financial forecas'!G9-'POA — Monthly financial forecas'!G7 -> 0 | H5: ='POA — Monthly financial forecas'!H8+'POA — Monthly financial forecas'!H11-'POA — Monthly financial forecas'!H9-'POA — Monthly financial forecas'!H7 -> 0 | I5: ='POA — Monthly financial forecas'!I8+'POA — Monthly financial forecas'!I11-'POA — Monthly financial forecas'!I9-'POA — Monthly financial forecas'!I7 -> 0 | ... AK5: ='POA — Monthly financial forecas'!AK8+'POA — Monthly financial forecas'!AK11-'POA — Monthly financial forecas'!AK9-'POA — Monthly financial forecas'!AK7 -> 0
A6: Revenue bridge check | B6: ='POA — Monthly financial forecas'!B18+'POA — Monthly financial forecas'!B22-'POA — Monthly financial forecas'!B27 -> 0 | C6: ='POA — Monthly financial forecas'!C18+'POA — Monthly financial forecas'!C22-'POA — Monthly financial forecas'!C27 -> 0 | D6: ='POA — Monthly financial forecas'!D18+'POA — Monthly financial forecas'!D22-'POA — Monthly financial forecas'!D27 -> 0 | E6: ='POA — Monthly financial forecas'!E18+'POA — Monthly financial forecas'!E22-'POA — Monthly financial forecas'!E27 -> 0 | F6: ='POA — Monthly financial forecas'!F18+'POA — Monthly financial forecas'!F22-'POA — Monthly financial forecas'!F27 -> 0 | G6: ='POA — Monthly financial forecas'!G18+'POA — Monthly financial forecas'!G22-'POA — Monthly financial forecas'!G27 -> 0 | H6: ='POA — Monthly financial forecas'!H18+'POA — Monthly financial forecas'!H22-'POA — Monthly financial forecas'!H27 -> 0 | I6: ='POA — Monthly financial forecas'!I18+'POA — Monthly financial forecas'!I22-'POA — Monthly financial forecas'!I27 -> 0 | ... AK6: ='POA — Monthly financial forecas'!AK18+'POA — Monthly financial forecas'!AK22-'POA — Monthly financial forecas'!AK27 -> 0
A7: Cash rollforward check | B7: ='POA — Monthly financial forecas'!B62+'POA — Monthly financial forecas'!B55-'POA — Monthly financial forecas'!B63 -> 0 | C7: ='POA — Monthly financial forecas'!C62+'POA — Monthly financial forecas'!C55-'POA — Monthly financial forecas'!C63 -> 0 | D7: ='POA — Monthly financial forecas'!D62+'POA — Monthly financial forecas'!D55-'POA — Monthly financial forecas'!D63 -> 0 | E7: ='POA — Monthly financial forecas'!E62+'POA — Monthly financial forecas'!E55-'POA — Monthly financial forecas'!E63 -> 0 | F7: ='POA — Monthly financial forecas'!F62+'POA — Monthly financial forecas'!F55-'POA — Monthly financial forecas'!F63 -> 0 | G7: ='POA — Monthly financial forecas'!G62+'POA — Monthly financial forecas'!G55-'POA — Monthly financial forecas'!G63 -> 0 | H7: ='POA — Monthly financial forecas'!H62+'POA — Monthly financial forecas'!H55-'POA — Monthly financial forecas'!H63 -> 0 | I7: ='POA — Monthly financial forecas'!I62+'POA — Monthly financial forecas'!I55-'POA — Monthly financial forecas'!I63 -> 0 | ... AK7: ='POA — Monthly financial forecas'!AK62+'POA — Monthly financial forecas'!AK55-'POA — Monthly financial forecas'!AK63 -> 0
A8: Restitution fee check | B8: ='POA — Monthly financial forecas'!B26*'Model inputs'!AM14-'POA — Monthly financial forecas'!B22 -> 0 | C8: ='POA — Monthly financial forecas'!C26*'Model inputs'!AM14-'POA — Monthly financial forecas'!C22 -> 0 | D8: ='POA — Monthly financial forecas'!D26*'Model inputs'!AM14-'POA — Monthly financial forecas'!D22 -> 0 | E8: ='POA — Monthly financial forecas'!E26*'Model inputs'!AM14-'POA — Monthly financial forecas'!E22 -> 0 | F8: ='POA — Monthly financial forecas'!F26*'Model inputs'!AM14-'POA — Monthly financial forecas'!F22 -> 0 | G8: ='POA — Monthly financial forecas'!G26*'Model inputs'!AM14-'POA — Monthly financial forecas'!G22 -> 0 | H8: ='POA — Monthly financial forecas'!H26*'Model inputs'!AM14-'POA — Monthly financial forecas'!H22 -> 0 | I8: ='POA — Monthly financial forecas'!I26*'Model inputs'!AM14-'POA — Monthly financial forecas'!I22 -> 0 | J8: ='POA — Monthly financial forecas'!J26*'Model inputs'!AM14-'POA — Monthly financial forecas'!J22 -> 0 | K8: ='POA — Monthly financial forecas'!K26*'Model inputs'!AM14-'POA — Monthly financial forecas'!K22 -> 0 | L8: ='POA — Monthly financial forecas'!L26*'Model inputs'!AM14-'POA — Monthly financial forecas'!L22 -> 0 | M8: ='POA — Monthly financial forecas'!M26*'Model inputs'!AM14-'POA — Monthly financial forecas'!M22 -> -1.8189894e-12 | N8: ='POA — Monthly financial forecas'!N26*'Model inputs'!AM14-'POA — Monthly financial forecas'!N22 -> 0 | O8: ='POA — Monthly financial forecas'!O26*'Model inputs'!AM14-'POA — Monthly financial forecas'!O22 -> 0 | P8: ='POA — Monthly financial forecas'!P26*'Model inputs'!AM14-'POA — Monthly financial forecas'!P22 -> 0 | Q8: ='POA — Monthly financial forecas'!Q26*'Model inputs'!AM14-'POA — Monthly financial forecas'!Q22 -> 0 | R8: ='POA — Monthly financial forecas'!R26*'Model inputs'!AM14-'POA — Monthly financial forecas'!R22 -> 0 | S8: ='POA — Monthly financial forecas'!S26*'Model inputs'!AM14-'POA — Monthly financial forecas'!S22 -> 0 | T8: ='POA — Monthly financial forecas'!T26*'Model inputs'!AM14-'POA — Monthly financial forecas'!T22 -> 0 | U8: ='POA — Monthly financial forecas'!U26*'Model inputs'!AM14-'POA — Monthly financial forecas'!U22 -> 0 | V8: ='POA — Monthly financial forecas'!V26*'Model inputs'!AM14-'POA — Monthly financial forecas'!V22 -> 0 | W8: ='POA — Monthly financial forecas'!W26*'Model inputs'!AM14-'POA — Monthly financial forecas'!W22 -> -1.4551915e-11 | X8: ='POA — Monthly financial forecas'!X26*'Model inputs'!AM14-'POA — Monthly financial forecas'!X22 -> 0 | Y8: ='POA — Monthly financial forecas'!Y26*'Model inputs'!AM14-'POA — Monthly financial forecas'!Y22 -> 0 | Z8: ='POA — Monthly financial forecas'!Z26*'Model inputs'!AM14-'POA — Monthly financial forecas'!Z22 -> 0 | AA8: ='POA — Monthly financial forecas'!AA26*'Model inputs'!AM14-'POA — Monthly financial forecas'!AA22 -> 0 | AB8: ='POA — Monthly financial forecas'!AB26*'Model inputs'!AM14-'POA — Monthly financial forecas'!AB22 -> 0 | AC8: ='POA — Monthly financial forecas'!AC26*'Model inputs'!AM14-'POA — Monthly financial forecas'!AC22 -> 0 | AD8: ='POA — Monthly financial forecas'!AD26*'Model inputs'!AM14-'POA — Monthly financial forecas'!AD22 -> -2.910383e-11 | AE8: ='POA — Monthly financial forecas'!AE26*'Model inputs'!AM14-'POA — Monthly financial forecas'!AE22 -> 0 | AF8: ='POA — Monthly financial forecas'!AF26*'Model inputs'!AM14-'POA — Monthly financial forecas'!AF22 -> -2.910383e-11 | AG8: ='POA — Monthly financial forecas'!AG26*'Model inputs'!AM14-'POA — Monthly financial forecas'!AG22 -> 0 | AH8: ='POA — Monthly financial forecas'!AH26*'Model inputs'!AM14-'POA — Monthly financial forecas'!AH22 -> 0 | AI8: ='POA — Monthly financial forecas'!AI26*'Model inputs'!AM14-'POA — Monthly financial forecas'!AI22 -> 0 | AJ8: ='POA — Monthly financial forecas'!AJ26*'Model inputs'!AM14-'POA — Monthly financial forecas'!AJ22 -> 0 | AK8: ='POA — Monthly financial forecas'!AK26*'Model inputs'!AM14-'POA — Monthly financial forecas'!AK22 -> 0
A9: Gross profit check | B9: ='POA — Monthly financial forecas'!B27-'POA — Monthly financial forecas'!B37-'POA — Monthly financial forecas'!B38 -> 0 | C9: ='POA — Monthly financial forecas'!C27-'POA — Monthly financial forecas'!C37-'POA — Monthly financial forecas'!C38 -> 0 | D9: ='POA — Monthly financial forecas'!D27-'POA — Monthly financial forecas'!D37-'POA — Monthly financial forecas'!D38 -> 0 | E9: ='POA — Monthly financial forecas'!E27-'POA — Monthly financial forecas'!E37-'POA — Monthly financial forecas'!E38 -> 0 | F9: ='POA — Monthly financial forecas'!F27-'POA — Monthly financial forecas'!F37-'POA — Monthly financial forecas'!F38 -> 0 | G9: ='POA — Monthly financial forecas'!G27-'POA — Monthly financial forecas'!G37-'POA — Monthly financial forecas'!G38 -> 0 | H9: ='POA — Monthly financial forecas'!H27-'POA — Monthly financial forecas'!H37-'POA — Monthly financial forecas'!H38 -> 0 | I9: ='POA — Monthly financial forecas'!I27-'POA — Monthly financial forecas'!I37-'POA — Monthly financial forecas'!I38 -> 0 | ... AK9: ='POA — Monthly financial forecas'!AK27-'POA — Monthly financial forecas'!AK37-'POA — Monthly financial forecas'!AK38 -> 0
A10: Operating budget check | B10: ='POA — Monthly financial forecas'!B41-'POA — Monthly financial forecas'!B40 -> 0 | C10: ='POA — Monthly financial forecas'!C41-'POA — Monthly financial forecas'!C40 -> 1.8189894e-12 | D10: ='POA — Monthly financial forecas'!D41-'POA — Monthly financial forecas'!D40 -> 0 | E10: ='POA — Monthly financial forecas'!E41-'POA — Monthly financial forecas'!E40 -> 0 | F10: ='POA — Monthly financial forecas'!F41-'POA — Monthly financial forecas'!F40 -> 0 | G10: ='POA — Monthly financial forecas'!G41-'POA — Monthly financial forecas'!G40 -> 0 | H10: ='POA — Monthly financial forecas'!H41-'POA — Monthly financial forecas'!H40 -> 0 | I10: ='POA — Monthly financial forecas'!I41-'POA — Monthly financial forecas'!I40 -> 3.6379788e-12 | ... AK10: ='POA — Monthly financial forecas'!AK41-'POA — Monthly financial forecas'!AK40 -> 0

Sheet Model inputs
A1: Model inputs
A2: Integration values are aggregated snapshots; raw source records are not included.
A4: Variables
A5: Variable / segment | B5: 2026-09 | C5: 2026-10 | D5: 2026-11 | E5: 2026-12 | F5: 2027-01 | G5: 2027-02 | H5: 2027-03 | I5: 2027-04 | J5: 2027-05 | K5: 2027-06 | L5: 2027-07 | M5: 2027-08 | N5: 2027-09 | O5: 2027-10 | P5: 2027-11 | Q5: 2027-12 | R5: 2028-01 | S5: 2028-02 | T5: 2028-03 | U5: 2028-04 | V5: 2028-05 | W5: 2028-06 | X5: 2028-07 | Y5: 2028-08 | Z5: 2028-09 | AA5: 2028-10 | AB5: 2028-11 | AC5: 2028-12 | AD5: 2029-01 | AE5: 2029-02 | AF5: 2029-03 | AG5: 2029-04 | AH5: 2029-05 | AI5: 2029-06 | AJ5: 2029-07 | AK5: 2029-08 | AL5: 2029-09 | AM5: Value
A6: Accounts receivable | B6: 0 | C6: ='Model inputs'!B6+'Model inputs'!C85-'Model inputs'!C91 -> 0 | D6: ='Model inputs'!C6+'Model inputs'!D85-'Model inputs'!D91 -> 0 | E6: ='Model inputs'!D6+'Model inputs'!E85-'Model inputs'!E91 -> 0 | F6: ='Model inputs'!E6+'Model inputs'!F85-'Model inputs'!F91 -> 0 | G6: ='Model inputs'!F6+'Model inputs'!G85-'Model inputs'!G91 -> 0 | H6: ='Model inputs'!G6+'Model inputs'!H85-'Model inputs'!H91 -> 0 | I6: ='Model inputs'!H6+'Model inputs'!I85-'Model inputs'!I91 -> 0 | J6: ='Model inputs'!I6+'Model inputs'!J85-'Model inputs'!J91 -> 0 | ... AL6: ='Model inputs'!AK6+'Model inputs'!AL85-'Model inputs'!AL91 -> 0
